Workbook

Sheet стратегия 2 под 100 тыс (отриц)
A1: Проект | B1: Мощность проекта, м2 | D1: Этажность | E1: Срок реализации, мес | F1: 3 кв. 2022 | G1: 4 кв. 2022 | J1: 1 кв. 2023 | M1: 2 кв. 2023 | P1: 3 кв. 2023 | S1: 4 кв. 2023 | V1: 1 кв. 2024 | Y1: 2 кв. 2024 | AB1: 3 кв. 2024 | AE1: 4 кв. 2024 | AH1: 1 кв. 2025 | AK1: 2 кв. 2025 | AN1: 3 кв. 2025 | AQ1: 4 кв. 2025 | AT1: 1 кв. 2026 | AW1: 2 кв. 2026 | AZ1: 3 кв. 2026 | BC1: 4 кв. 2026 | BF1: 1 кв. 2027 | BI1: 2 кв. 2027 | BL1: 3 кв. 2027 | BO1: 4 кв. 2027
F2: 44805 | G2: 44835 | H2: 44866 | I2: 44896 | J2: 44927 | K2: 44958 | L2: 44986 | M2: 45017 | N2: 45047 | O2: 45078 | P2: 45108 | Q2: 45139 | R2: 45170 | S2: 45200 | T2: 45231 | U2: 45261 | V2: 45292 | W2: 45323 | X2: 45352 | Y2: 45383 | Z2: 45413 | AA2: 45444 | AB2: 45474 | AC2: 45505 | AD2: 45536 | AE2: 45566 | AF2: 45597 | AG2: 45627 | AH2: 45658 | AI2: 45689 | AJ2: 45717 | AK2: 45748 | AL2: 45778 | AM2: 45809 | AN2: 45839 | AO2: 45870 | AP2: 45901 | AQ2: 45931 | AR2: 45962 | AS2: 45992 | AT2: 46023 | AU2: 46054 | AV2: 46082 | AW2: 46113 | AX2: 46143 | AY2: 46174 | AZ2: 46204 | BA2: 46235 | BB2: 46266 | BC2: 46296 | BD2: 46327 | BE2: 46357 | BF2: 46388 | BG2: 46419 | BH2: 46447 | BI2: 46478 | BJ2: 46508 | BK2: 46539 | BL2: 46569 | BM2: 46600 | BN2: 46631 | BO2: 46661 | BP2: 46692 | BQ2: 46722
B3: Продаваемая площадь | C3: Общая площадь | F3: 1 | G3: 2 | H3: 3 | I3: 4 | J3: 5 | K3: 6 | L3: 7 | M3: 8 | N3: 9 | O3: 10 | P3: 11 | Q3: 12 | R3: 13 | S3: 14 | T3: 15 | U3: 16 | V3: 17 | W3: 18 | X3: 19 | Y3: 20 | Z3: 21 | AA3: 22 | AB3: 23 | AC3: 24 | AD3: 25 | AE3: 26 | AF3: 27 | AG3: 28 | AH3: 29 | AI3: 30 | AJ3: 31 | AK3: 32 | AL3: 33 | AM3: 34 | AN3: 35 | AO3: 36 | AP3: 37 | AQ3: 38 | AR3: 39 | AS3: 40 | AT3: 41 | AU3: 42 | AV3: 43 | AW3: 44 | AX3: 45 | AY3: 46 | AZ3: 47 | BA3: 48 | BB3: 49 | BC3: 50 | BD3: 51 | BE3: 52 | BF3: 53 | BG3: 54 | BH3: 55 | BI3: 53 | BJ3: 54 | BK3: 55 | BL3: 53 | BM3: 54 | BN3: 55 | BO3: 53 | BP3: 54 | BQ3: 55
A4: Доп.продажи К2, тыс.руб. | I4: =I5*I6 -> 0 | J4: =J5*J6 -> 0 | K4: =K5*K6 -> 0 | L4: =L5*L6 -> 0 | M4: =M5*M6 -> 0 | N4: =N21 -> 0 | O4: =O21 -> 0 | P4: =P21 -> 0 | Q4: =Q21 -> 0 | R4: =R21 -> 0
A5: Кедровый 2, м2 | I5: =309.6*0 -> 0 | J5: =288.50755988024*0 -> 0 | K5: =117.09*0 -> 0 | L5: =321.4*0 -> 0 | M5: =301.52*0 -> 0
A6: Кедровый 2, тыс.руб./м2 | I6: 66.106935 | J6: 61.662707 | K6: 66.090554 | L6: 65.329107 | M6: 64.8
A7: Наполнение эскроу К2, тыс.руб. | I7: =I8*I9 -> 25901.975 | J7: =J8*J9 -> 21615 | K7: =K8*K9 -> 27342.975 | L7: =L8*L9 -> 33462 | M7: =M8*M9 -> 28256.8 | N7: =N8*N9 -> 46900 | O7: =O8*O9 -> 50625 | P7: =P8*P9 -> 53430 | ... R7: =R8*R9 -> 72280
A8: Кедровый 2, м2 | F8: =F10/F12 -> 1.1373577 | I8: =719*0.55 -> 395.45 | J8: =600*0.55 -> 330 | K8: =759*0.55 -> 417.45 | L8: =900*0.55 -> 495 | M8: =760*0.55 -> 418 | N8: 700 | O8: 750 | P8: 780 | Q8: 930 | R8: 1040
A9: Кедровый 2, тыс.руб./м2 | I9: 65.5 | J9: 65.5 | K9: 65.5 | L9: 67.6 | M9: 67.6 | N9: 67 | O9: 67.5 | P9: 68.5 | Q9: 69.5 | R9: 69.5
A10: Наполнение ЭСКРОУ накопительно | F10: 265886.42 | G10: 296491.57 | H10: 318795.86 | I10: =H10+I7 -> 344697.84 | J10: =I10+J7 -> 366312.84 | K10: =J10+K7 -> 393655.81 | L10: =K10+L7 -> 427117.81 | M10: =L10+M7 -> 455374.61 | N10: =M10+N7 -> 502274.61 | O10: =N10+O7 -> 552899.61 | P10: =O10+P7 -> 606329.61 | ... R10: =Q10+R7 -> 743244.61
A11: Выборка НКЛ К2 (с дек.22 расчетно) | F11: 36485.232 | G11: 31537.208 | H11: 27893.471 | I11: 32000 | J11: 32000 | K11: 32000 | L11: 32000 | M11: 32000 | N11: 32000 | O11: 50000 | P11: 50000 | Q11: 61135.156 | R11: 61135.156
A12: Остаток ссудной задолженности | F12: 233775.55 | G12: 265312.76 | H12: 293206.23 | I12: =H12+I11 -> 325206.23 | J12: =I12+J11 -> 357206.23 | K12: =J12+K11 -> 389206.23 | L12: =K12+L11 -> 421206.23 | M12: =L12+M11 -> 453206.23 | N12: =M12+N11 -> 485206.23 | O12: =N12+O11 -> 535206.23 | P12: =O12+P11 -> 585206.23 | ... R12: =Q12+R11 -> 707476.54
A13: Ставка по эскроу, исходя из наполнения | F13: =IF(F10/F12>1.5,#REF!,IF(F10/F12>1.4,#REF!,IF(F10/F12>1.3,#REF!,IF(F10/F12>1.2,#REF!,IF(F10/F12>1.1,#REF!,IF(F10/F12>1,#REF!,IF(F10/F12<1,17.73))))))) -> #REF! | G13: =IF(G10/G12>1.5,#REF!,IF(G10/G12>1.4,#REF!,IF(G10/G12>1.3,#REF!,IF(G10/G12>1.2,#REF!,IF(G10/G12>1.1,#REF!,IF(G10/G12>1,#REF!,IF(G10/G12<1,17.73))))))) -> #REF! | H13: =IF(H10/H12>1.5,#REF!,IF(H10/H12>1.4,#REF!,IF(H10/H12>1.3,#REF!,IF(H10/H12>1.2,#REF!,IF(H10/H12>1.1,#REF!,IF(H10/H12>1,#REF!,IF(H10/H12<1,17.73))))))) -> #REF! | I13: =IF(I10/I12>1.5,#REF!,IF(I10/I12>1.4,#REF!,IF(I10/I12>1.3,#REF!,IF(I10/I12>1.2,#REF!,IF(I10/I12>1.1,#REF!,IF(I10/I12>1,#REF!,IF(I10/I12<1,17.73))))))) -> #REF! | J13: =IF(J10/J12>1.5,#REF!,IF(J10/J12>1.4,#REF!,IF(J10/J12>1.3,#REF!,IF(J10/J12>1.2,#REF!,IF(J10/J12>1.1,#REF!,IF(J10/J12>1,#REF!,IF(J10/J12<1,17.73))))))) -> #REF! | K13: =IF(K10/K12>1.5,#REF!,IF(K10/K12>1.4,#REF!,IF(K10/K12>1.3,#REF!,IF(K10/K12>1.2,#REF!,IF(K10/K12>1.1,#REF!,IF(K10/K12>1,#REF!,IF(K10/K12<1,17.73))))))) -> #REF! | L13: =IF(L10/L12>1.5,#REF!,IF(L10/L12>1.4,#REF!,IF(L10/L12>1.3,#REF!,IF(L10/L12>1.2,#REF!,IF(L10/L12>1.1,#REF!,IF(L10/L12>1,#REF!,IF(L10/L12<1,17.73))))))) -> #REF! | M13: =IF(M10/M12>1.5,#REF!,IF(M10/M12>1.4,#REF!,IF(M10/M12>1.3,#REF!,IF(M10/M12>1.2,#REF!,IF(M10/M12>1.1,#REF!,IF(M10/M12>1,#REF!,IF(M10/M12<1,17.73))))))) -> #REF! | ... R13: =IF(R10/R12>1.5,#REF!,IF(R10/R12>1.4,#REF!,IF(R10/R12>1.3,#REF!,IF(R10/R12>1.2,#REF!,IF(R10/R12>1.1,#REF!,IF(R10/R12>1,#REF!,IF(R10/R12<1,17.73))))))) -> #REF!
A14: Кедровый 1 | B14: 14439.4 | F14: РНВ
A15: Кедровый 2 | B15: 18331.74 | C15: 27707.46 | D15: 9 | E15: 26 | T15: РНВ | V15: закончить продажи (продаем по 60,875 млн в месяц в среднем)
A16: Павловск 1 | B16: 10065.54 | C16: 13453.37 | D16: 9 | E16: 24 | F16: кредит | L16: 18000 | U16: РНВ | V16: закончить продажи (продаем по 39 млн в месяц в среднем)
A17: Богучар 1 | B17: 10000 | C17: 13365.771 | D17: 9 | E17: 18 | F17: ЗУ | J17: 19000 | K17: проект (П+Р) + Благоустр (отдать на проектирование за 2 месяца) | L17: РНС - начало строительства (подготовить СП, набрать сотрудников, они должны изучить проект) | O17: кредит | AC17: РНВ | AD17: закончить продажи (продаем по 32 млн в месяц в среднем - депонирование)
A18: Муром 1 | B18: 25000 | C18: =B18*1.33 -> 33250 | D18: 9 | E18: 18 | J18: =15000+2500 -> 17500 | L18: 22000 | M18: проект (П+Р) + Благоустр (отдать на проектирование за 2 месяца) | N18: предпродажи (подготовить офис, набрать сотрудников) | O18: РНС - начало строительства (подготовить СП, набрать сотрудников, они должны изучить проект) | R18: кредит | AF18: РНВ | AG18: закончить продажи (продаем по 81 млн в месяц в среднем - депонирование)
A19: Старый Оскол | B19: 14000 | C19: =B19*1.33 -> 18620 | D19: 9 | E19: 18 | I19: 5000 | J19: 3000 | M19: 20000 | N19: проект (П+Р) + Благоустр (отдать на проектирование за 2 месяца) | O19: предпродажи (подготовить офис, набрать сотрудников) | P19: РНС - начало строительства (подготовить СП, набрать сотрудников, они должны изучить проект) | S19: кредит | AG19: РНВ | AH19: закончить продажи (продаем по 36 млн в месяц в среднем - депонирование)
A20: Павловск 2 (возможна замена локации) | B20: 18534.63 | C20: =B20*1.33 -> 24651.058 | D20: 9 | E20: 18 | F20: ЗУ | G20: ТУ | H20: проект (П+Р) + Благоустр (отдать на проектирование за 2 месяца) | I20: экспертиза | J20: предпродажи (подготовить офис, набрать сотрудников) | P20: РНС - начало строительства (подготовить СП, набрать сотрудников, они должны изучить проект) | S20: кредит | AG20: РНВ | AH20: закончить продажи (продаем по 53 млн в месяц в среднем - депонирование)
A21: Итого РАСХОДЫ, тыс.руб. | I21: =I19 -> 5000 | J21: =J19+J18+J17 -> 39500 | L21: =L18 -> 22000 | M21: =M19 -> 20000
A22: Итого | B22: =SUM(B14:B20) -> 110371.31
A23: Богучар 2 | B23: 10000 | C23: 13365.771 | D23: 9 | E23: 18 | F23: ЗУ (вместе с Б1) | G23: ТУ (вместе с Б1) | H23: проект (П+Р) + Благоустр (отдать на проектирование за 2 месяца) | I23: экспертиза | J23: предпродажи (подготовить офис, набрать сотрудников) | X23: РНС - начало строительства (подготовить СП, набрать сотрудников, они должны изучить проект) | AA23: кредит | AO23: РНВ | AP23: закончить продажи (продаем по 32 млн в месяц в среднем - депонирование)
A24: Муром 2 | B24: 25000 | C24: =C18 -> 33250 | D24: 10 | E24: 18 | I24: ЗУ | M24: проект (П+Р) + Благоустр (отдать на проектирование за 2 месяца) | N24: предпродажи (подготовить офис, набрать сотрудников) | Z24: РНС - начало строительства (подготовить СП, набрать сотрудников, они должны изучить проект) | AC24: кредит | AQ24: РНВ | AR24: закончить продажи (продаем по 81 млн в месяц в среднем - депонирование)
A25: Старый Оскол | B25: 6000 | C25: =B25*1.33 -> 7980 | D25: 9 | E25: 18 | H25: ЗУ | N25: проект (П+Р) + Благоустр (отдать на проектирование за 2 месяца) | O25: предпродажи (подготовить офис, набрать сотрудников) | P25: РНС - начало строительства (подготовить СП, набрать сотрудников, они должны изучить проект) | S25: кредит | AC25: РНС - начало строительства (подготовить СП, набрать сотрудников, они должны изучить проект) | AF25: кредит | AT25: РНВ | AU25: закончить продажи (продаем по 36 млн в месяц в среднем - депонирование)
A26: За стратегией | B26: =B25+B23+B24 -> 41000 | C26: =C25+C23+C24 -> 54595.771
J31: =B15+B16+B14 -> 42836.68 | V31: =B17+B18+B20+B19+#REF! -> #REF! | AH31: =#REF!+B22+#REF!+B23 -> #REF! | AT31: =#REF!++B22+#REF! -> #REF!
V32: =V31+J31 -> #REF! | AH32: =AH31+V32 -> #REF!
AL34: нужно 2-3 локации (если один литер 18-20 м2) | AM34: =AH31-100000 -> #REF!

Sheet 1_вариант
C1: 12_2022 | D1: 01_2023 | E1: 02_2023 | F1: 03_2023 | G1: 04_2023 | H1: 05_2023 | I1: 06_2023 | J1: 07_2023 | K1: 08_2023 | L1: 09_2023 | M1: 10_2023 | N1: 11_2023 | O1: 12_2023 | P1: 01_2024 | Q1: 02_2024 | R1: 03_2024 | S1: 04_2024 | T1: 05_2024 | U1: 06_2024 | V1: 07_2024 | W1: 08_2024 | X1: 09_2024 | Y1: 10_2024 | Z1: 11_2024 | AA1: 12_2024
A2: Доп.продажи К2, тыс.руб. | C2: =C3*C5*C6*C4 -> 0 | D2: =D3*D5*D6*D4 -> 0 | E2: =E3*E5*E6*E4 -> 0 | F2: =F3*F5*F6*F4 -> 0 | G2: =G3*G5*G6*G4 -> 0 | H2: =H3*H5*H6*H4 -> 0 | I2: =I3*I5*I6*I4 -> 0 | J2: =J3*J5*J6*J4 -> 0 | ... AA2: =AA3*AA5*AA6*AA4 -> 0
A3: Кедровый 2, м2 | B3: =SUM(список_МСА!B2:B34) -> 1452.91 | C3: =SUM(список_МСА!$B2:$B8) -> 351.02 | D3: =SUM(список_МСА!$B9:$B15) -> 284.07 | E3: =SUM(список_МСА!$B16:$B23) -> 319.2 | F3: =SUM(список_МСА!$B24:$B29) -> 257.36 | G3: =SUM(список_МСА!$B30:$B33) -> 198.92 | H3: =список_МСА!B34 -> 42.34
A4: Процент выполнения по объему продаж | C4: 0 | D4: 0 | E4: 0 | F4: 0 | G4: 0 | H4: 0 | I4: 1 | J4: 1 | K4: 1 | L4: 1 | M4: 1 | N4: 1 | O4: 1 | P4: 1 | Q4: 1 | R4: 1 | S4: 1 | T4: 1 | U4: 1 | V4: 1 | W4: 1 | X4: 1 | Y4: 1 | Z4: 1 | AA4: 1
A5: Кедровый 2, тыс.руб./м2 | C5: =SUM(список_МСА!$L2:$L8)/C3/1000 -> 64.900732 | D5: =SUM(список_МСА!$L9:$L15)/D3/1000 -> 66.128662 | E5: =SUM(список_МСА!$L16:$L23)/E3/1000 -> 65.525417 | F5: =SUM(список_МСА!$L24:$L29)/F3/1000 -> 64.491743 | G5: =SUM(список_МСА!$L33:$L230)/G3/1000 -> 31.569299 | H5: =список_МСА!H34/список_МСА!B34/1000 -> 63.3
A6: Процент выполнения по объему продаж | C6: 1 | D6: 1 | E6: 1 | F6: 1 | G6: 1 | H6: 1 | I6: 1 | J6: 1 | K6: 1 | L6: 1 | M6: 1 | N6: 1 | O6: 1 | P6: 1 | Q6: 1 | R6: 1 | S6: 1 | T6: 1 | U6: 1 | V6: 1 | W6: 1 | X6: 1 | Y6: 1 | Z6: 1 | AA6: 1
A7: Наполнение эскроу К2, тыс.руб. | C7: =C8*C10 -> #REF! | D7: =D8*D10 -> #REF! | E7: =E8*E10 -> #REF! | F7: =F8*F10 -> #REF! | G7: =G8*G10 -> #REF! | H7: =H8*H10 -> #REF! | I7: =I8*I10 -> #REF! | J7: =J8*J10 -> #REF! | ... AA7: =AA8*AA10 -> #REF!
A8: Объем продаж, м2 | B8: 18442.2 | C8: =#REF!*C9 -> #REF! | D8: =IF(($B$8-#REF!-SUM('1_вариант'!$C$8:C8)-SUM('1_вариант'!$C$3:C3))>0,#REF!,0)*D9 -> #REF! | E8: =IF(($B$8-#REF!-SUM('1_вариант'!$C$8:D8)-SUM('1_вариант'!$C$3:D3))>0,#REF!,0)*E9 -> #REF! | F8: =IF(($B$8-#REF!-SUM('1_вариант'!$C$8:E8)-SUM('1_вариант'!$C$3:E3))>0,#REF!,0)*F9 -> #REF! | G8: =IF(($B$8-#REF!-SUM('1_вариант'!$C$8:F8)-SUM('1_вариант'!$C$3:F3))>0,#REF!,0)*G9 -> #REF! | H8: =IF(($B$8-#REF!-SUM('1_вариант'!$C$8:G8)-SUM('1_вариант'!$C$3:G3))>0,#REF!,0)*H9 -> #REF! | I8: =IF(($B$8-#REF!-SUM('1_вариант'!$C$8:H8)-SUM('1_вариант'!$C$3:H3))>0,#REF!,0)*I9 -> #REF! | J8: =IF(($B$8-#REF!-SUM('1_вариант'!$C$8:I8)-SUM('1_вариант'!$C$3:I3))>0,#REF!,0)*J9 -> #REF! | K8: =IF(($B$8-#REF!-SUM('1_вариант'!$C$8:J8)-SUM('1_вариант'!$C$3:J3))>0,#REF!,0)*K9 -> #REF! | ... Q8: =IF(($B$8-#REF!-SUM('1_вариант'!$C$8:P8)-SUM('1_вариант'!$C$3:P3))>0,#REF!,0)*Q9 -> #REF! | R8: =($B$8-#REF!-SUM($C$8:$Q$8,$C$3:$R$3))*R9 -> #REF! | S8: =($B$8-#REF!-SUM('1_вариант'!$C$8:R8)-SUM($C$3:R3))*S9 -> #REF! | T8: =($B$8-#REF!-SUM('1_вариант'!$C$8:S8)-SUM($C$3:S3))*T9 -> #REF! | U8: =($B$8-#REF!-SUM('1_вариант'!$C$8:T8)-SUM($C$3:T3))*U9 -> #REF! | V8: =($B$8-#REF!-SUM('1_вариант'!$C$8:U8)-SUM($C$3:U3))*V9 -> #REF! | W8: =($B$8-#REF!-SUM('1_вариант'!$C$8:V8)-SUM($C$3:V3))*W9 -> #REF! | X8: =($B$8-#REF!-SUM('1_вариант'!$C$8:W8)-SUM($C$3:W3))*X9 -> #REF! | Y8: =($B$8-#REF!-SUM('1_вариант'!$C$8:X8)-SUM($C$3:X3))*Y9 -> #REF! | Z8: =($B$8-#REF!-SUM('1_вариант'!$C$8:Y8)-SUM($C$3:Y3))*Z9 -> #REF! | AA8: =($B$8-#REF!-SUM('1_вариант'!$C$8:Z8)-SUM($C$3:Z3))*AA9 -> #REF!
A9: Процент выполнения по объему продаж | C9: 1 | D9: 1 | E9: 1 | F9: 1 | G9: 1 | H9: 1 | I9: 1 | J9: 1 | K9: 1 | L9: 1 | M9: 1 | N9: 1 | O9: 1 | P9: 1 | Q9: 1 | R9: 1 | S9: 1 | T9: 1 | U9: 1 | V9: 1 | W9: 1 | X9: 1 | Y9: 1 | Z9: 1 | AA9: 1
A10: Цена продаж тыс.руб./м2 | C10: =#REF!*'1_вариант'!C11 -> #REF! | D10: =#REF!*'1_вариант'!D11 -> #REF! | E10: =#REF!*'1_вариант'!E11 -> #REF! | F10: =#REF!*'1_вариант'!F11 -> #REF! | G10: =#REF!*'1_вариант'!G11 -> #REF! | H10: =#REF!*'1_вариант'!H11 -> #REF! | I10: =#REF!*'1_вариант'!I11 -> #REF! | J10: =#REF!*'1_вариант'!J11 -> #REF! | ... AA10: =#REF!*'1_вариант'!AA11 -> #REF!
A11: Процент выполнения по объему продаж | C11: 1 | D11: 1 | E11: 1 | F11: 1 | G11: 1 | H11: 1 | I11: 1 | J11: 1 | K11: 1 | L11: 1 | M11: 1 | N11: 1 | O11: 1 | P11: 1 | Q11: 1 | R11: 1 | S11: 1 | T11: 1 | U11: 1 | V11: 1 | W11: 1 | X11: 1 | Y11: 1 | Z11: 1 | AA11: 1
A12: Наполнение ЭСКРОУ накопительно | C12: ='стратегия 2 под 100 тыс (отриц)'!$H$10+C7 -> #REF! | D12: =C12+D7 -> #REF! | E12: =D12+E7 -> #REF! | F12: =E12+F7 -> #REF! | G12: =F12+G7 -> #REF! | H12: =G12+H7 -> #REF! | I12: =H12+I7 -> #REF! | J12: =I12+J7 -> #REF! | K12: =J12+K7 -> #REF! | ... AA12: =Z12+AA7 -> #REF!
A13: Выборка НКЛ К2 (с дек.22 расчетно) | C13: 32000 | D13: 32000 | E13: 32000 | F13: 45000 | G13: 50000 | H13: 50000 | I13: 50000 | J13: 50000 | K13: 50000 | L13: 60000 | M13: =IF(756476.54-SUM('стратегия 2 под 100 тыс (отриц)'!$H$12,$C$13:L13)>0,(756476.54-SUM('стратегия 2 под 100 тыс (отриц)'!$H$12,$C$13:L13)),0) -> 12270.311 | N13: =IF(756476.54-SUM('стратегия 2 под 100 тыс (отриц)'!$H$12,$C$13:M13)>0,(756476.54-SUM('стратегия 2 под 100 тыс (отриц)'!$H$12,$C$13:M13)),0)/2 -> 0 | O13: =IF(756476.54-SUM('стратегия 2 под 100 тыс (отриц)'!$H$12,$C$13:N13)>0,(756476.54-SUM('стратегия 2 под 100 тыс (отриц)'!$H$12,$C$13:N13)),0)/2 -> 0 | P13: =IF(756476.54-SUM('стратегия 2 под 100 тыс (отриц)'!$H$12,$C$13:O13)>0,(756476.54-SUM('стратегия 2 под 100 тыс (отриц)'!$H$12,$C$13:O13)),0)/2 -> 0 | Q13: =IF(756476.54-SUM('стратегия 2 под 100 тыс (отриц)'!$H$12,$C$13:P13)>0,(756476.54-SUM('стратегия 2 под 100 тыс (отриц)'!$H$12,$C$13:P13)),0)/2 -> 0 | R13: =IF(756476.54-SUM('стратегия 2 под 100 тыс (отриц)'!$H$12,$C$13:Q13)>0,(756476.54-SUM('стратегия 2 под 100 тыс (отриц)'!$H$12,$C$13:Q13)),0)/2 -> 0 | S13: =IF(756476.54-SUM('стратегия 2 под 100 тыс (отриц)'!$H$12,$C$13:R13)>0,(756476.54-SUM('стратегия 2 под 100 тыс (отриц)'!$H$12,$C$13:R13)),0)/2 -> 0 | T13: =IF(756476.54-SUM('стратегия 2 под 100 тыс (отриц)'!$H$12,$C$13:S13)>0,(756476.54-SUM('стратегия 2 под 100 тыс (отриц)'!$H$12,$C$13:S13)),0)/2 -> 0 | U13: =IF(756476.54-SUM('стратегия 2 под 100 тыс (отриц)'!$H$12,$C$13:T13)>0,(756476.54-SUM('стратегия 2 под 100 тыс (отриц)'!$H$12,$C$13:T13)),0)/2 -> 0 | ... W13: =IF(756476.54-SUM('стратегия 2 под 100 тыс (отриц)'!$H$12,$C$13:V13)>0,(756476.54-SUM('стратегия 2 под 100 тыс (отриц)'!$H$12,$C$13:V13)),0)/2 -> 0
A14: Остаток ссудной задолженности | C14: ='стратегия 2 под 100 тыс (отриц)'!H12+C13 -> 325206.23 | D14: =C14+D13 -> 357206.23 | E14: =D14+E13 -> 389206.23 | F14: =E14+F13 -> 434206.23 | G14: =F14+G13 -> 484206.23 | H14: =G14+H13 -> 534206.23 | I14: =H14+I13 -> 584206.23 | J14: =I14+J13 -> 634206.23 | K14: =J14+K13 -> 684206.23 | ... M14: =L14+M13 -> 756476.54
A15: Ставка по эскроу, исходя из наполнения | C15: =IF(C$12/C$14>1.5,#REF!,IF(C$12/C$14>1.4,#REF!,IF(C$12/C$14>1.3,#REF!,IF(C$12/C$14>1.2,#REF!,IF(C$12/C$14>1.1,#REF!,IF(C$12/C$14>1,#REF!,IF(C$12/C$14<1,17.73))))))) -> #REF! | D15: =IF(D$12/D$14>1.5,#REF!,IF(D$12/D$14>1.4,#REF!,IF(D$12/D$14>1.3,#REF!,IF(D$12/D$14>1.2,#REF!,IF(D$12/D$14>1.1,#REF!,IF(D$12/D$14>1,#REF!,IF(D$12/D$14<1,17.73))))))) -> #REF! | E15: =IF(E$12/E$14>1.5,#REF!,IF(E$12/E$14>1.4,#REF!,IF(E$12/E$14>1.3,#REF!,IF(E$12/E$14>1.2,#REF!,IF(E$12/E$14>1.1,#REF!,IF(E$12/E$14>1,#REF!,IF(E$12/E$14<1,17.73))))))) -> #REF! | F15: =IF(F$12/F$14>1.5,#REF!,IF(F$12/F$14>1.4,#REF!,IF(F$12/F$14>1.3,#REF!,IF(F$12/F$14>1.2,#REF!,IF(F$12/F$14>1.1,#REF!,IF(F$12/F$14>1,#REF!,IF(F$12/F$14<1,17.73))))))) -> #REF! | G15: =IF(G$12/G$14>1.5,#REF!,IF(G$12/G$14>1.4,#REF!,IF(G$12/G$14>1.3,#REF!,IF(G$12/G$14>1.2,#REF!,IF(G$12/G$14>1.1,#REF!,IF(G$12/G$14>1,#REF!,IF(G$12/G$14<1,17.73))))))) -> #REF! | H15: =IF(H$12/H$14>1.5,#REF!,IF(H$12/H$14>1.4,#REF!,IF(H$12/H$14>1.3,#REF!,IF(H$12/H$14>1.2,#REF!,IF(H$12/H$14>1.1,#REF!,IF(H$12/H$14>1,#REF!,IF(H$12/H$14<1,17.73))))))) -> #REF! | I15: =IF(I$12/I$14>1.5,#REF!,IF(I$12/I$14>1.4,#REF!,IF(I$12/I$14>1.3,#REF!,IF(I$12/I$14>1.2,#REF!,IF(I$12/I$14>1.1,#REF!,IF(I$12/I$14>1,#REF!,IF(I$12/I$14<1,17.73))))))) -> #REF! | J15: =IF(J$12/J$14>1.5,#REF!,IF(J$12/J$14>1.4,#REF!,IF(J$12/J$14>1.3,#REF!,IF(J$12/J$14>1.2,#REF!,IF(J$12/J$14>1.1,#REF!,IF(J$12/J$14>1,#REF!,IF(J$12/J$14<1,17.73))))))) -> #REF! | ... M15: =IF(M$12/M$14>1.5,#REF!,IF(M$12/M$14>1.4,#REF!,IF(M$12/M$14>1.3,#REF!,IF(M$12/M$14>1.2,#REF!,IF(M$12/M$14>1.1,#REF!,IF(M$12/M$14>1,#REF!,IF(M$12/M$14<1,17.73))))))) -> #REF!
A16: доходность, руб./м2 | B16: =(AA12-#REF!/1000-#REF!/1000)/B8 -> #REF! | C16: =($AA$12-#REF!/1000-#REF!/1000)/'1_вариант'!$B$8 -> #REF! | D16: =($AA$12-#REF!/1000-#REF!/1000)/'1_вариант'!$B$8 -> #REF! | E16: =($AA$12-#REF!/1000-#REF!/1000)/'1_вариант'!$B$8 -> #REF! | F16: =($AA$12-#REF!/1000-#REF!/1000)/'1_вариант'!$B$8 -> #REF! | G16: =($AA$12-#REF!/1000-#REF!/1000)/'1_вариант'!$B$8 -> #REF! | H16: =($AA$12-#REF!/1000-#REF!/1000)/'1_вариант'!$B$8 -> #REF! | I16: =($AA$12-#REF!/1000-#REF!/1000)/'1_вариант'!$B$8 -> #REF! | J16: =($AA$12-#REF!/1000-#REF!/1000)/'1_вариант'!$B$8 -> #REF! | ... AA16: =($AA$12-#REF!/1000-#REF!/1000)/'1_вариант'!$B$8 -> #REF!
A17: Богучар 1 | D17: 19000
A18: Муром 1 | D18: 17500 | F18: 22000
A19: Старый Оскол | C19: =4442.9748+370.2479 -> 4813.2227 | D19: 3000 | E19: =4442974.8/1000 -> 4442.9748 | G19: 20000
A20: Павловск 2 (возможна замена локации)
A21: Итого потребность в ДС | C21: =SUM(C17:C20) -> 4813.2227 | D21: =SUM(D17:D20) -> 39500 | E21: =SUM(E17:E20) -> 4442.9748 | F21: =SUM(F17:F20) -> 22000 | G21: =SUM(G17:G20) -> 20000 | H21: =SUM(H17:H20) -> 0 | I21: =SUM(I17:I20) -> 0 | J21: =SUM(J17:J20) -> 0 | ... AA21: =SUM(AA17:AA20) -> 0
A22: ИзбытокДС(+)/ДефицитДС(-) | B22: (доп.продажи) | D22: =C22+D2-D21 -> -39500 | E22: =D22+E2-E21 -> -43942.975 | F22: =E22+F2-F21 -> -65942.975 | G22: =F22+G2-G21 -> -85942.975 | H22: =G22+H2-H21 -> -85942.975 | I22: =H22+I2-I21 -> -85942.975 | J22: =I22+J2-J21 -> -85942.975 | K22: =J22+K2-K21 -> -85942.975 | ... AA22: =Z22+AA2-AA21 -> -85942.975
A23: Покрытие потребности за счет НКЛ | B23: НКЛ К2 | C23: =C19 -> 4813.2227 | D23: =IF(D22<0,-D22,0) -> 39500 | E23: =IF(E22<0,-E22,0) -> 43942.975 | F23: =IF(F22<0,-F22,0) -> 65942.975 | G23: =IF(G22<0,-G22,0) -> 85942.975 | H23: =IF(H22<0,-H22,0) -> 85942.975 | I23: =IF(I22<0,-I22,0) -> 85942.975 | J23: =IF(J22<0,-J22,0) -> 85942.975 | K23: =IF(K22<0,-K22,0) -> 85942.975 | ... AA23: =IF(AA22<0,-AA22,0) -> 85942.975
A24: !Ставка по эскроу (доп.вывод на инвестиции) | C24: =IF(C$12/(C$14+C21)>1.5,#REF!,IF(C$12/(C$14+C21)>1.4,#REF!,IF(C$12/(C$14+C21)>1.3,#REF!,IF(C$12/(C$14+C21)>1.2,#REF!,IF(C$12/(C$14+C21)>1.1,#REF!,IF(C$12/(C$14+C21)>1,#REF!,IF(C$12/(C$14+C21)<1,17.73))))))) -> #REF! | D24: =IF(D$12/(D$14+D21)>1.5,#REF!,IF(D$12/(D$14+D21)>1.4,#REF!,IF(D$12/(D$14+D21)>1.3,#REF!,IF(D$12/(D$14+D21)>1.2,#REF!,IF(D$12/(D$14+D21)>1.1,#REF!,IF(D$12/(D$14+D21)>1,#REF!,IF(D$12/(D$14+D21)<1,17.73))))))) -> #REF! | E24: =IF(E$12/(E$14+E21)>1.5,#REF!,IF(E$12/(E$14+E21)>1.4,#REF!,IF(E$12/(E$14+E21)>1.3,#REF!,IF(E$12/(E$14+E21)>1.2,#REF!,IF(E$12/(E$14+E21)>1.1,#REF!,IF(E$12/(E$14+E21)>1,#REF!,IF(E$12/(E$14+E21)<1,17.73))))))) -> #REF! | F24: =IF(F$12/(F$14+F21)>1.5,#REF!,IF(F$12/(F$14+F21)>1.4,#REF!,IF(F$12/(F$14+F21)>1.3,#REF!,IF(F$12/(F$14+F21)>1.2,#REF!,IF(F$12/(F$14+F21)>1.1,#REF!,IF(F$12/(F$14+F21)>1,#REF!,IF(F$12/(F$14+F21)<1,17.73))))))) -> #REF! | G24: =IF(G$12/(G$14+G21)>1.5,#REF!,IF(G$12/(G$14+G21)>1.4,#REF!,IF(G$12/(G$14+G21)>1.3,#REF!,IF(G$12/(G$14+G21)>1.2,#REF!,IF(G$12/(G$14+G21)>1.1,#REF!,IF(G$12/(G$14+G21)>1,#REF!,IF(G$12/(G$14+G21)<1,17.73))))))) -> #REF! | H24: =IF(H$12/(H$14+H21)>1.5,#REF!,IF(H$12/(H$14+H21)>1.4,#REF!,IF(H$12/(H$14+H21)>1.3,#REF!,IF(H$12/(H$14+H21)>1.2,#REF!,IF(H$12/(H$14+H21)>1.1,#REF!,IF(H$12/(H$14+H21)>1,#REF!,IF(H$12/(H$14+H21)<1,17.73))))))) -> #REF! | I24: =IF(I$12/(I$14+I21)>1.5,#REF!,IF(I$12/(I$14+I21)>1.4,#REF!,IF(I$12/(I$14+I21)>1.3,#REF!,IF(I$12/(I$14+I21)>1.2,#REF!,IF(I$12/(I$14+I21)>1.1,#REF!,IF(I$12/(I$14+I21)>1,#REF!,IF(I$12/(I$14+I21)<1,17.73))))))) -> #REF! | J24: =IF(J$12/(J$14+J21)>1.5,#REF!,IF(J$12/(J$14+J21)>1.4,#REF!,IF(J$12/(J$14+J21)>1.3,#REF!,IF(J$12/(J$14+J21)>1.2,#REF!,IF(J$12/(J$14+J21)>1.1,#REF!,IF(J$12/(J$14+J21)>1,#REF!,IF(J$12/(J$14+J21)<1,17.73))))))) -> #REF! | ... M24: =IF(M$12/(M$14+M21)>1.5,#REF!,IF(M$12/(M$14+M21)>1.4,#REF!,IF(M$12/(M$14+M21)>1.3,#REF!,IF(M$12/(M$14+M21)>1.2,#REF!,IF(M$12/(M$14+M21)>1.1,#REF!,IF(M$12/(M$14+M21)>1,#REF!,IF(M$12/(M$14+M21)<1,17.73))))))) -> #REF!

Sheet список_МСА
A1: № кв | B1: м2 | C1: цена, руб/м2 | D1: № дог. | E1: комн. | F1: тип
A2: 14 | B2: 47.42 | C2: 64000 | D2: 42 | E2: 2 | F2: 2ЕА | G2: Мозолин Сергей Анатольевич | H2: 3034880 | I2: 44764 | J2: 0 | K2: - | L2: 3034880 | M2: 64000 | N2: 42-К-2-1-3-14 | O2: 44764 | P2: 44769 | Q2: 3 034 880,00 - 28.07.2022 | R2: 1
A3: 17 | B3: 59.61 | C3: 67700 | D3: 43 | E3: 2 | F3: 2А | G3: Мозолин Сергей Анатольевич | H3: 4035597 | I3: 44767 | J3: 0 | K3: - | L3: 4035597 | M3: 67700 | N3: 43-К-2-1-3-17 | O3: 44767 | P3: 44769 | Q3: 4 035 597,00 - 28.07.2022 | R3: 1
A4: 21 | B4: 47.42 | C4: 64000 | D4: 44 | E4: 2 | F4: 2ЕА | G4: Мозолин Сергей Анатольевич | H4: 3034880 | I4: 44767 | J4: 0 | K4: - | L4: 3034880 | M4: 64000 | N4: 44-К-2-1-4-21 | O4: 44767 | P4: 44769 | Q4: 3 034 880,00 - 28.07.2022 | R4: 1
A5: 28 | B5: 47.32 | C5: 63300 | D5: 48 | E5: 2 | F5: 2ЕА | G5: Мозолин Сергей Анатольевич | H5: 3001686 | I5: 44767 | J5: 0 | K5: - | L5: 3001686 | M5: 63433.77 | N5: 48-К-2-1-5-28 | O5: 44767 | P5: 44769 | Q5: 3 001 686,00 - 28.07.2022 | R5: 1
A6: 31 | B6: 59.61 | C6: 67000 | D6: 47 | E6: 2 | F6: 2А | G6: Мозолин Сергей Анатольевич | H6: 3993870 | I6: 44767 | J6: 0 | K6: - | L6: 3993870 | M6: 67000 | N6: 47-К-2-1-5-31 | O6: 44767 | P6: 44769 | Q6: 3 993 870,00 - 28.07.2022 | R6: 1
A7: 32 | B7: 42.32 | C7: 63300 | D7: 49 | E7: 2 | F7: 2ЕА | G7: Мозолин Сергей Анатольевич | H7: 2678856 | I7: 44767 | J7: 0 | K7: - | L7: 2678856 | M7: 63300 | N7: 49-К-2-1-5-32 | O7: 44767 | P7: 44769 | Q7: 2 678 856,00 - 28.07.2022 | R7: 1
A8: 42 | B8: 47.32 | C8: 63300 | D8: 50 | E8: 2 | F8: 2ЕА | G8: Мозолин Сергей Анатольевич | H8: 3001686 | I8: 44767 | J8: 0 | K8: - | L8: 3001686 | M8: 63300 | N8: 50-К-2-1-7-42 | O8: 44767 | P8: 44769 | Q8: 3 001 686,00 - 28.07.2022 | R8: 1
A9: 45 | B9: 59.61 | C9: 67000 | D9: 51 | E9: 2 | F9: 2А | G9: Мозолин Сергей Анатольевич | H9: 3993870 | I9: 44767 | J9: 0 | K9: - | L9: 3993870 | M9: 67000 | N9: 51-К-2-1-7-45 | O9: 44767 | P9: 44769 | Q9: 3 993 870,00 - 28.07.2022 | R9: 1
A10: 79 | B10: 40.17 | C10: 64000 | D10: 52 | E10: 2 | F10: 2ЕА | G10: Мозолин Сергей Анатольевич | H10: 2570880 | I10: 44767 | J10: 0 | K10: - | L10: 2570880 | M10: 64000 | N10: 52-К-2-3-79 | O10: 44767 | P10: 44769 | Q10: 2 570 880,00 - 28.07.2022 | R10: 1
A11: 85 | B11: 36.03 | C11: 67500 | D11: 53 | E11: 1 | F11: 1А | G11: Мозолин Сергей Анатольевич | H11: 2432025 | I11: 44767 | J11: 0 | K11: - | L11: 2432025 | M11: 67500 | N11: 53-К-2-2-3-85 | O11: 44767 | P11: 44769 | Q11: 2 432 025,00 - 28.07.2022 | R11: 1
A12: 93 | B12: 36.03 | C12: 67500 | D12: 54 | E12: 1 | F12: 1А | G12: Мозолин Сергей Анатольевич | H12: 2432025 | I12: 44767 | J12: 0 | K12: - | L12: 2432025 | M12: 67500 | N12: 54-К-2-2-4-93 | O12: 44767 | P12: 44769 | Q12: 2 432025,00 - 28.07.2022 | R12: 1
A13: 101 | B13: 36.03 | C13: 66800 | D13: 56 | E13: 2 | F13: 2ЕА | G13: Мозолин Сергей Анатольевич | H13: 2406804 | I13: 44767 | J13: 0 | K13: - | L13: 2406804 | M13: 66800 | N13: 56-К-2-2-5-101 | O13: 44767 | P13: 44774 | Q13: 2 406 804,00 - 02.08.2022 | R13: 1
... A34: 316 | B34: 42.34 | C34: 63300 | D34: 46 | E34: 2 | F34: 2ЕА | G34: Мозолин Сергей Анатольевич | H34: 2680122 | I34: 44767 | J34: 0 | K34: - | L34: 2680122 | M34: 63300 | N34: 46-К-2-6-5-316 | O34: 44767 | P34: 44769 | Q34: 2 680 122,00 - 28.07.2022 | R34: 1

Sheet Стратегия 23 - 27
A1: Мастер - карта стратегического развития
A3: № | B3: Проект | C3: Текущий статус | D3: Кол-во секций | E3: Продаваемая площадь (М2) | F3: Срок реализации, мес | G3: 45200 | H3: 45231 | I3: 45261 | J3: 2023 | K3: 45292 | L3: 45323 | M3: 45352 | N3: 45383 | O3: 45413 | P3: 45444 | Q3: 45474 | R3: 45505 | S3: 45536 | T3: 45566 | U3: 45597 | V3: 45627 | W3: 2024 | X3: 45658 | Y3: 45689 | Z3: 45717 | AA3: 45748 | AB3: 45778 | AC3: 45809 | AD3: 45839 | AE3: 45870 | AF3: 45901 | AG3: 45931 | AH3: 45962 | AI3: 45992 | AJ3: 2025 | AK3: 46023 | AL3: 46054 | AM3: 46082 | AN3: 46113 | AO3: 46143 | AP3: 46174 | AQ3: 46204 | AR3: 46235 | AS3: 46266 | AT3: 46296 | AU3: 46327 | AV3: 46357 | AW3: 2026 | AX3: 46388 | AY3: 46419 | AZ3: 46447 | BA3: 46478 | BB3: 46508 | BC3: 46539 | BD3: 46569 | BE3: 46600 | BF3: 46631 | BG3: 46661 | BH3: 46692 | BI3: 46722 | BJ3: 2027 | BK3: 46753 | BL3: 46784 | BM3: 46813 | BN3: 46844 | BO3: 46874 | BP3: 46905 | BQ3: 46935 | BR3: 46966 | BS3: 46997 | BT3: 47027 | BU3: 47058 | BV3: 47088 | BW3: 2028 | BX3: 47119 | BY3: 47150 | BZ3: 47178 | CA3: 47209 | CB3: 47239 | CC3: 47270 | CD3: 47300 | CE3: 47331 | CF3: 47362 | CG3: 47392 | CH3: 47423 | CI3: 47453 | CJ3: 2029
G4: накопительно с 2021 года | J4: =J6+25629+1062 -> 45188 | K4: накопительно с 2021 года | W4: =J4+W6 -> 55406 | X4: накопительно с 2021 года | AJ4: =W4+AJ6 -> 83537 | AK4: накопительно с 2021 года | AW4: =AJ4+AW6 -> 121008.24 | AX4: накопительно с 2021 года | BJ4: =AW4+BJ6 -> 171358.7 | BK4: накопительно с 2021 года | BW4: =BJ4+BW6 -> 286260.68 | BX4: накопительно с 2021 года | CJ4: =BW4+CJ6 -> 351481.4
G6: всего за 2023 год | J6: =J7+J9 -> 18497 | K6: всего за 2024 год | W6: =SUM(W7:W86) -> 10218 | X6: всего за 2025 год | AJ6: =SUM(AJ7:AJ86) -> 28131 | AK6: всего за 2026 год | AW6: =SUM(AW7:AW86) -> 37471.24 | AX6: всего за 2027 год | BJ6: =SUM(BJ7:BJ86) -> 50350.46 | BK6: всего за 2028 год | BW6: =SUM(BW7:BW86) -> 114901.98 | BX6: всего за 2029 год | CJ6: =SUM(CJ7:CJ86) -> 65220.72
A7: 1 | B7: Кедровый №2 | C7: Завершен | D7: 6 | E7: 18497 | F7: =COUNTA(K7:V7,X7:AI7,AK7:AV7,AX7:BI7,BK7:BV7,BX7:CI7) -> 0 | G7: 1 | H7: 1 | I7: 1 | J7: =E7 -> 18497 | W7: =IF(K7="РНВ",$E7,IF(L7="РНВ",$E7,IF(M7="РНВ",$E7,IF(N7="РНВ",$E7,IF(O7="РНВ",$E7,IF(P7="РНВ",$E7,IF(Q7="РНВ",$E7,IF(R7="РНВ",$E7,IF(S7="РНВ",$E7,IF(T7="РНВ",$E7,IF(U7="РНВ",$E7,IF(V7="РНВ",$E7,0)))))))))))) -> 0 | AJ7: =IF(X7="РНВ",$E7,IF(Y7="РНВ",$E7,IF(Z7="РНВ",$E7,IF(AA7="РНВ",$E7,IF(AB7="РНВ",$E7,IF(AC7="РНВ",$E7,IF(AD7="РНВ",$E7,IF(AE7="РНВ",$E7,IF(AF7="РНВ",$E7,IF(AG7="РНВ",$E7,IF(AH7="РНВ",$E7,IF(AI7="РНВ",$E7,0)))))))))))) -> 0 | AW7: =IF(AK7="РНВ",$E7,IF(AL7="РНВ",$E7,IF(AM7="РНВ",$E7,IF(AN7="РНВ",$E7,IF(AO7="РНВ",$E7,IF(AP7="РНВ",$E7,IF(AQ7="РНВ",$E7,IF(AR7="РНВ",$E7,IF(AS7="РНВ",$E7,IF(AT7="РНВ",$E7,IF(AU7="РНВ",$E7,IF(AV7="РНВ",$E7,0)))))))))))) -> 0 | BJ7: =IF(AX7="РНВ",$E7,IF(AY7="РНВ",$E7,IF(AZ7="РНВ",$E7,IF(BA7="РНВ",$E7,IF(BB7="РНВ",$E7,IF(BC7="РНВ",$E7,IF(BD7="РНВ",$E7,IF(BE7="РНВ",$E7,IF(BF7="РНВ",$E7,IF(BG7="РНВ",$E7,IF(BH7="РНВ",$E7,IF(BI7="РНВ",$E7,0)))))))))))) -> 0 | BW7: =IF(BK7="РНВ",$E7,IF(BL7="РНВ",$E7,IF(BM7="РНВ",$E7,IF(BN7="РНВ",$E7,IF(BO7="РНВ",$E7,IF(BP7="РНВ",$E7,IF(BQ7="РНВ",$E7,IF(BR7="РНВ",$E7,IF(BS7="РНВ",$E7,IF(BT7="РНВ",$E7,IF(BU7="РНВ",$E7,IF(BV7="РНВ",$E7,0)))))))))))) -> 0 | CJ7: =IF(BX7="РНВ",$E7,IF(BY7="РНВ",$E7,IF(BZ7="РНВ",$E7,IF(CA7="РНВ",$E7,IF(CB7="РНВ",$E7,IF(CC7="РНВ",$E7,IF(CD7="РНВ",$E7,IF(CE7="РНВ",$E7,IF(CF7="РНВ",$E7,IF(CG7="РНВ",$E7,IF(CH7="РНВ",$E7,IF(CI7="РНВ",$E7,0)))))))))))) -> 0
AK8: =IF(AK7>0,$E7/$F7,0) -> 0 | AL8: =IF(AL7>0,$E7/$F7,0) -> 0 | AM8: =IF(AM7>0,$E7/$F7,0) -> 0 | AN8: =IF(AN7>0,$E7/$F7,0) -> 0 | AO8: =IF(AO7>0,$E7/$F7,0) -> 0 | AP8: =IF(AP7>0,$E7/$F7,0) -> 0 | AQ8: =IF(AQ7>0,$E7/$F7,0) -> 0 | AR8: =IF(AR7>0,$E7/$F7,0) -> 0 | ... AV8: =IF(AV7>0,$E7/$F7,0) -> 0 | AX8: =IF(AX7>0,$E7/$F7,0) -> 0 | AY8: =IF(AY7>0,$E7/$F7,0) -> 0 | AZ8: =IF(AZ7>0,$E7/$F7,0) -> 0 | BA8: =IF(BA7>0,$E7/$F7,0) -> 0 | BB8: =IF(BB7>0,$E7/$F7,0) -> 0 | BC8: =IF(BC7>0,$E7/$F7,0) -> 0 | BD8: =IF(BD7>0,$E7/$F7,0) -> 0 | BE8: =IF(BE7>0,$E7/$F7,0) -> 0 | ... BI8: =IF(BI7>0,$E7/$F7,0) -> 0 | BK8: =IF(BK7>0,$E7/$F7,0) -> 0 | BL8: =IF(BL7>0,$E7/$F7,0) -> 0 | BM8: =IF(BM7>0,$E7/$F7,0) -> 0 | BN8: =IF(BN7>0,$E7/$F7,0) -> 0 | BO8: =IF(BO7>0,$E7/$F7,0) -> 0 | BP8: =IF(BP7>0,$E7/$F7,0) -> 0 | BQ8: =IF(BQ7>0,$E7/$F7,0) -> 0 | BR8: =IF(BR7>0,$E7/$F7,0) -> 0 | ... BV8: =IF(BV7>0,$E7/$F7,0) -> 0 | BX8: =IF(BX7>0,$E7/$F7,0) -> 0 | BY8: =IF(BY7>0,$E7/$F7,0) -> 0 | BZ8: =IF(BZ7>0,$E7/$F7,0) -> 0 | CA8: =IF(CA7>0,$E7/$F7,0) -> 0 | CB8: =IF(CB7>0,$E7/$F7,0) -> 0 | CC8: =IF(CC7>0,$E7/$F7,0) -> 0 | CD8: =IF(CD7>0,$E7/$F7,0) -> 0 | CE8: =IF(CE7>0,$E7/$F7,0) -> 0 | ... CI8: =IF(CI7>0,$E7/$F7,0) -> 0
A9: 2 | B9: Павловск №1 | C9: Завершен | D9: 3 | E9: 10218 | F9: =COUNTA(K9:V9,X9:AI9,AK9:AV9,AX9:BI9,BK9:BV9,BX9:CI9) -> 2 | G9: 1 | H9: 1 | I9: 1 | K9: 1 | L9: 1 | W9: =E9 -> 10218 | AJ9: =IF(X9="РНВ",$E9,IF(Y9="РНВ",$E9,IF(Z9="РНВ",$E9,IF(AA9="РНВ",$E9,IF(AB9="РНВ",$E9,IF(AC9="РНВ",$E9,IF(AD9="РНВ",$E9,IF(AE9="РНВ",$E9,IF(AF9="РНВ",$E9,IF(AG9="РНВ",$E9,IF(AH9="РНВ",$E9,IF(AI9="РНВ",$E9,0)))))))))))) -> 0 | AW9: =IF(AK9="РНВ",$E9,IF(AL9="РНВ",$E9,IF(AM9="РНВ",$E9,IF(AN9="РНВ",$E9,IF(AO9="РНВ",$E9,IF(AP9="РНВ",$E9,IF(AQ9="РНВ",$E9,IF(AR9="РНВ",$E9,IF(AS9="РНВ",$E9,IF(AT9="РНВ",$E9,IF(AU9="РНВ",$E9,IF(AV9="РНВ",$E9,0)))))))))))) -> 0 | BJ9: =IF(AX9="РНВ",$E9,IF(AY9="РНВ",$E9,IF(AZ9="РНВ",$E9,IF(BA9="РНВ",$E9,IF(BB9="РНВ",$E9,IF(BC9="РНВ",$E9,IF(BD9="РНВ",$E9,IF(BE9="РНВ",$E9,IF(BF9="РНВ",$E9,IF(BG9="РНВ",$E9,IF(BH9="РНВ",$E9,IF(BI9="РНВ",$E9,0)))))))))))) -> 0 | BW9: =IF(BK9="РНВ",$E9,IF(BL9="РНВ",$E9,IF(BM9="РНВ",$E9,IF(BN9="РНВ",$E9,IF(BO9="РНВ",$E9,IF(BP9="РНВ",$E9,IF(BQ9="РНВ",$E9,IF(BR9="РНВ",$E9,IF(BS9="РНВ",$E9,IF(BT9="РНВ",$E9,IF(BU9="РНВ",$E9,IF(BV9="РНВ",$E9,0)))))))))))) -> 0 | CJ9: =IF(BX9="РНВ",$E9,IF(BY9="РНВ",$E9,IF(BZ9="РНВ",$E9,IF(CA9="РНВ",$E9,IF(CB9="РНВ",$E9,IF(CC9="РНВ",$E9,IF(CD9="РНВ",$E9,IF(CE9="РНВ",$E9,IF(CF9="РНВ",$E9,IF(CG9="РНВ",$E9,IF(CH9="РНВ",$E9,IF(CI9="РНВ",$E9,0)))))))))))) -> 0
AK10: =IF(AK9>0,$E9/$F9,0) -> 0 | AL10: =IF(AL9>0,$E9/$F9,0) -> 0 | AM10: =IF(AM9>0,$E9/$F9,0) -> 0 | AN10: =IF(AN9>0,$E9/$F9,0) -> 0 | AO10: =IF(AO9>0,$E9/$F9,0) -> 0 | AP10: =IF(AP9>0,$E9/$F9,0) -> 0 | AQ10: =IF(AQ9>0,$E9/$F9,0) -> 0 | AR10: =IF(AR9>0,$E9/$F9,0) -> 0 | ... AV10: =IF(AV9>0,$E9/$F9,0) -> 0 | AX10: =IF(AX9>0,$E9/$F9,0) -> 0 | AY10: =IF(AY9>0,$E9/$F9,0) -> 0 | AZ10: =IF(AZ9>0,$E9/$F9,0) -> 0 | BA10: =IF(BA9>0,$E9/$F9,0) -> 0 | BB10: =IF(BB9>0,$E9/$F9,0) -> 0 | BC10: =IF(BC9>0,$E9/$F9,0) -> 0 | BD10: =IF(BD9>0,$E9/$F9,0) -> 0 | BE10: =IF(BE9>0,$E9/$F9,0) -> 0 | ... BI10: =IF(BI9>0,$E9/$F9,0) -> 0 | BK10: =IF(BK9>0,$E9/$F9,0) -> 0 | BL10: =IF(BL9>0,$E9/$F9,0) -> 0 | BM10: =IF(BM9>0,$E9/$F9,0) -> 0 | BN10: =IF(BN9>0,$E9/$F9,0) -> 0 | BO10: =IF(BO9>0,$E9/$F9,0) -> 0 | BP10: =IF(BP9>0,$E9/$F9,0) -> 0 | BQ10: =IF(BQ9>0,$E9/$F9,0) -> 0 | BR10: =IF(BR9>0,$E9/$F9,0) -> 0 | ... BV10: =IF(BV9>0,$E9/$F9,0) -> 0 | BX10: =IF(BX9>0,$E9/$F9,0) -> 0 | BY10: =IF(BY9>0,$E9/$F9,0) -> 0 | BZ10: =IF(BZ9>0,$E9/$F9,0) -> 0 | CA10: =IF(CA9>0,$E9/$F9,0) -> 0 | CB10: =IF(CB9>0,$E9/$F9,0) -> 0 | CC10: =IF(CC9>0,$E9/$F9,0) -> 0 | CD10: =IF(CD9>0,$E9/$F9,0) -> 0 | CE10: =IF(CE9>0,$E9/$F9,0) -> 0 | ... CI10: =IF(CI9>0,$E9/$F9,0) -> 0
A11: 3 | B11: Павловск №2 | C11: Завершен | D11: 6 | E11: 18352 | F11: =COUNTA(K11:V11,X11:AI11,AK11:AV11,AX11:BI11,BK11:BV11,BX11:CI11) -> 16 | G11: 1 | H11: 1 | I11: 1 | K11: 1 | L11: 1 | M11: 1 | N11: 1 | O11: 1 | P11: 1 | Q11: 1 | R11: 1 | S11: 1 | T11: 1 | U11: 1 | V11: 1 | W11: =IF(K11="РНВ",$E11,IF(L11="РНВ",$E11,IF(M11="РНВ",$E11,IF(N11="РНВ",$E11,IF(O11="РНВ",$E11,IF(P11="РНВ",$E11,IF(Q11="РНВ",$E11,IF(R11="РНВ",$E11,IF(S11="РНВ",$E11,IF(T11="РНВ",$E11,IF(U11="РНВ",$E11,IF(V11="РНВ",$E11,0)))))))))))) -> 0 | X11: 1 | Y11: 1 | Z11: 1 | AA11: РНВ | AJ11: =IF(X11="РНВ",$E11,IF(Y11="РНВ",$E11,IF(Z11="РНВ",$E11,IF(AA11="РНВ",$E11,IF(AB11="РНВ",$E11,IF(AC11="РНВ",$E11,IF(AD11="РНВ",$E11,IF(AE11="РНВ",$E11,IF(AF11="РНВ",$E11,IF(AG11="РНВ",$E11,IF(AH11="РНВ",$E11,IF(AI11="РНВ",$E11,0)))))))))))) -> 18352 | AW11: =IF(AK11="РНВ",$E11,IF(AL11="РНВ",$E11,IF(AM11="РНВ",$E11,IF(AN11="РНВ",$E11,IF(AO11="РНВ",$E11,IF(AP11="РНВ",$E11,IF(AQ11="РНВ",$E11,IF(AR11="РНВ",$E11,IF(AS11="РНВ",$E11,IF(AT11="РНВ",$E11,IF(AU11="РНВ",$E11,IF(AV11="РНВ",$E11,0)))))))))))) -> 0 | BJ11: =IF(AX11="РНВ",$E11,IF(AY11="РНВ",$E11,IF(AZ11="РНВ",$E11,IF(BA11="РНВ",$E11,IF(BB11="РНВ",$E11,IF(BC11="РНВ",$E11,IF(BD11="РНВ",$E11,IF(BE11="РНВ",$E11,IF(BF11="РНВ",$E11,IF(BG11="РНВ",$E11,IF(BH11="РНВ",$E11,IF(BI11="РНВ",$E11,0)))))))))))) -> 0 | BW11: =IF(BK11="РНВ",$E11,IF(BL11="РНВ",$E11,IF(BM11="РНВ",$E11,IF(BN11="РНВ",$E11,IF(BO11="РНВ",$E11,IF(BP11="РНВ",$E11,IF(BQ11="РНВ",$E11,IF(BR11="РНВ",$E11,IF(BS11="РНВ",$E11,IF(BT11="РНВ",$E11,IF(BU11="РНВ",$E11,IF(BV11="РНВ",$E11,0)))))))))))) -> 0 | CJ11: =IF(BX11="РНВ",$E11,IF(BY11="РНВ",$E11,IF(BZ11="РНВ",$E11,IF(CA11="РНВ",$E11,IF(CB11="РНВ",$E11,IF(CC11="РНВ",$E11,IF(CD11="РНВ",$E11,IF(CE11="РНВ",$E11,IF(CF11="РНВ",$E11,IF(CG11="РНВ",$E11,IF(CH11="РНВ",$E11,IF(CI11="РНВ",$E11,0)))))))))))) -> 0
AK12: =IF(AK11>0,$E11/$F11,0) -> 0 | AL12: =IF(AL11>0,$E11/$F11,0) -> 0 | AM12: =IF(AM11>0,$E11/$F11,0) -> 0 | AN12: =IF(AN11>0,$E11/$F11,0) -> 0 | AO12: =IF(AO11>0,$E11/$F11,0) -> 0 | AP12: =IF(AP11>0,$E11/$F11,0) -> 0 | AQ12: =IF(AQ11>0,$E11/$F11,0) -> 0 | AR12: =IF(AR11>0,$E11/$F11,0) -> 0 | ... AV12: =IF(AV11>0,$E11/$F11,0) -> 0 | AX12: =IF(AX11>0,$E11/$F11,0) -> 0 | AY12: =IF(AY11>0,$E11/$F11,0) -> 0 | AZ12: =IF(AZ11>0,$E11/$F11,0) -> 0 | BA12: =IF(BA11>0,$E11/$F11,0) -> 0 | BB12: =IF(BB11>0,$E11/$F11,0) -> 0 | BC12: =IF(BC11>0,$E11/$F11,0) -> 0 | BD12: =IF(BD11>0,$E11/$F11,0) -> 0 | BE12: =IF(BE11>0,$E11/$F11,0) -> 0 | ... BI12: =IF(BI11>0,$E11/$F11,0) -> 0 | BK12: =IF(BK11>0,$E11/$F11,0) -> 0 | BL12: =IF(BL11>0,$E11/$F11,0) -> 0 | BM12: =IF(BM11>0,$E11/$F11,0) -> 0 | BN12: =IF(BN11>0,$E11/$F11,0) -> 0 | BO12: =IF(BO11>0,$E11/$F11,0) -> 0 | BP12: =IF(BP11>0,$E11/$F11,0) -> 0 | BQ12: =IF(BQ11>0,$E11/$F11,0) -> 0 | BR12: =IF(BR11>0,$E11/$F11,0) -> 0 | ... BV12: =IF(BV11>0,$E11/$F11,0) -> 0 | BX12: =IF(BX11>0,$E11/$F11,0) -> 0 | BY12: =IF(BY11>0,$E11/$F11,0) -> 0 | BZ12: =IF(BZ11>0,$E11/$F11,0) -> 0 | CA12: =IF(CA11>0,$E11/$F11,0) -> 0 | CB12: =IF(CB11>0,$E11/$F11,0) -> 0 | CC12: =IF(CC11>0,$E11/$F11,0) -> 0 | CD12: =IF(CD11>0,$E11/$F11,0) -> 0 | CE12: =IF(CE11>0,$E11/$F11,0) -> 0 | ... CI12: =IF(CI11>0,$E11/$F11,0) -> 0
A13: 4 | B13: Богучар №1 | C13: Завершен | D13: 3 | E13: 9779 | F13: =COUNTA(K13:V13,X13:AI13,AK13:AV13,AX13:BI13,BK13:BV13,BX13:CI13) -> 20 | G13: 1 | H13: 1 | I13: 1 | K13: 1 | L13: 1 | M13: 1 | N13: 1 | O13: 1 | P13: 1 | Q13: 1 | R13: 1 | S13: 1 | T13: 1 | U13: 1 | V13: 1 | W13: =IF(K13="РНВ",$E13,IF(L13="РНВ",$E13,IF(M13="РНВ",$E13,IF(N13="РНВ",$E13,IF(O13="РНВ",$E13,IF(P13="РНВ",$E13,IF(Q13="РНВ",$E13,IF(R13="РНВ",$E13,IF(S13="РНВ",$E13,IF(T13="РНВ",$E13,IF(U13="РНВ",$E13,IF(V13="РНВ",$E13,0)))))))))))) -> 0 | X13: 1 | Y13: 1 | Z13: 1 | AA13: 1 | AB13: 1 | AC13: 1 | AD13: 1 | AE13: РНВ | AJ13: =IF(X13="РНВ",$E13,IF(Y13="РНВ",$E13,IF(Z13="РНВ",$E13,IF(AA13="РНВ",$E13,IF(AB13="РНВ",$E13,IF(AC13="РНВ",$E13,IF(AD13="РНВ",$E13,IF(AE13="РНВ",$E13,IF(AF13="РНВ",$E13,IF(AG13="РНВ",$E13,IF(AH13="РНВ",$E13,IF(AI13="РНВ",$E13,0)))))))))))) -> 9779 | AW13: =IF(AK13="РНВ",$E13,IF(AL13="РНВ",$E13,IF(AM13="РНВ",$E13,IF(AN13="РНВ",$E13,IF(AO13="РНВ",$E13,IF(AP13="РНВ",$E13,IF(AQ13="РНВ",$E13,IF(AR13="РНВ",$E13,IF(AS13="РНВ",$E13,IF(AT13="РНВ",$E13,IF(AU13="РНВ",$E13,IF(AV13="РНВ",$E13,0)))))))))))) -> 0 | BJ13: =IF(AX13="РНВ",$E13,IF(AY13="РНВ",$E13,IF(AZ13="РНВ",$E13,IF(BA13="РНВ",$E13,IF(BB13="РНВ",$E13,IF(BC13="РНВ",$E13,IF(BD13="РНВ",$E13,IF(BE13="РНВ",$E13,IF(BF13="РНВ",$E13,IF(BG13="РНВ",$E13,IF(BH13="РНВ",$E13,IF(BI13="РНВ",$E13,0)))))))))))) -> 0 | BW13: =IF(BK13="РНВ",$E13,IF(BL13="РНВ",$E13,IF(BM13="РНВ",$E13,IF(BN13="РНВ",$E13,IF(BO13="РНВ",$E13,IF(BP13="РНВ",$E13,IF(BQ13="РНВ",$E13,IF(BR13="РНВ",$E13,IF(BS13="РНВ",$E13,IF(BT13="РНВ",$E13,IF(BU13="РНВ",$E13,IF(BV13="РНВ",$E13,0)))))))))))) -> 0 | CJ13: =IF(BX13="РНВ",$E13,IF(BY13="РНВ",$E13,IF(BZ13="РНВ",$E13,IF(CA13="РНВ",$E13,IF(CB13="РНВ",$E13,IF(CC13="РНВ",$E13,IF(CD13="РНВ",$E13,IF(CE13="РНВ",$E13,IF(CF13="РНВ",$E13,IF(CG13="РНВ",$E13,IF(CH13="РНВ",$E13,IF(CI13="РНВ",$E13,0)))))))))))) -> 0
AK14: =IF(AK13>0,$E13/$F13,0) -> 0 | AL14: =IF(AL13>0,$E13/$F13,0) -> 0 | AM14: =IF(AM13>0,$E13/$F13,0) -> 0 | AN14: =IF(AN13>0,$E13/$F13,0) -> 0 | AO14: =IF(AO13>0,$E13/$F13,0) -> 0 | AP14: =IF(AP13>0,$E13/$F13,0) -> 0 | AQ14: =IF(AQ13>0,$E13/$F13,0) -> 0 | AR14: =IF(AR13>0,$E13/$F13,0) -> 0 | ... AV14: =IF(AV13>0,$E13/$F13,0) -> 0 | AX14: =IF(AX13>0,$E13/$F13,0) -> 0 | AY14: =IF(AY13>0,$E13/$F13,0) -> 0 | AZ14: =IF(AZ13>0,$E13/$F13,0) -> 0 | BA14: =IF(BA13>0,$E13/$F13,0) -> 0 | BB14: =IF(BB13>0,$E13/$F13,0) -> 0 | BC14: =IF(BC13>0,$E13/$F13,0) -> 0 | BD14: =IF(BD13>0,$E13/$F13,0) -> 0 | BE14: =IF(BE13>0,$E13/$F13,0) -> 0 | ... BI14: =IF(BI13>0,$E13/$F13,0) -> 0 | BK14: =IF(BK13>0,$E13/$F13,0) -> 0 | BL14: =IF(BL13>0,$E13/$F13,0) -> 0 | BM14: =IF(BM13>0,$E13/$F13,0) -> 0 | BN14: =IF(BN13>0,$E13/$F13,0) -> 0 | BO14: =IF(BO13>0,$E13/$F13,0) -> 0 | BP14: =IF(BP13>0,$E13/$F13,0) -> 0 | BQ14: =IF(BQ13>0,$E13/$F13,0) -> 0 | BR14: =IF(BR13>0,$E13/$F13,0) -> 0 | ... BV14: =IF(BV13>0,$E13/$F13,0) -> 0 | BX14: =IF(BX13>0,$E13/$F13,0) -> 0 | BY14: =IF(BY13>0,$E13/$F13,0) -> 0 | BZ14: =IF(BZ13>0,$E13/$F13,0) -> 0 | CA14: =IF(CA13>0,$E13/$F13,0) -> 0 | CB14: =IF(CB13>0,$E13/$F13,0) -> 0 | CC14: =IF(CC13>0,$E13/$F13,0) -> 0 | CD14: =IF(CD13>0,$E13/$F13,0) -> 0 | CE14: =IF(CE13>0,$E13/$F13,0) -> 0 | ... CI14: =IF(CI13>0,$E13/$F13,0) -> 0
A15: 5 | B15: Богучар №2 | C15: Строительство | D15: 3 | E15: 9572.31 | F15: =COUNTA(K15:V15,X15:AI15,AK15:AV15,AX15:BI15,BK15:BV15,BX15:CI15) -> 22 | W15: =IF(K15="РНВ",$E15,IF(L15="РНВ",$E15,IF(M15="РНВ",$E15,IF(N15="РНВ",$E15,IF(O15="РНВ",$E15,IF(P15="РНВ",$E15,IF(Q15="РНВ",$E15,IF(R15="РНВ",$E15,IF(S15="РНВ",$E15,IF(T15="РНВ",$E15,IF(U15="РНВ",$E15,IF(V15="РНВ",$E15,0)))))))))))) -> 0 | Z15: 1 | AA15: 1 | AB15: 1 | AC15: 1 | AD15: 1 | AE15: 1 | AF15: 1 | AG15: 1 | AH15: 1 | AI15: 1 | AJ15: =IF(X15="РНВ",$E15,IF(Y15="РНВ",$E15,IF(Z15="РНВ",$E15,IF(AA15="РНВ",$E15,IF(AB15="РНВ",$E15,IF(AC15="РНВ",$E15,IF(AD15="РНВ",$E15,IF(AE15="РНВ",$E15,IF(AF15="РНВ",$E15,IF(AG15="РНВ",$E15,IF(AH15="РНВ",$E15,IF(AI15="РНВ",$E15,0)))))))))))) -> 0 | AK15: 1 | AL15: 1 | AM15: 1 | AN15: 1 | AO15: 1 | AP15: 1 | AQ15: 1 | AR15: 1 | AS15: 1 | AT15: 1 | AU15: 1 | AV15: РНВ | AW15: =IF(AK15="РНВ",$E15,IF(AL15="РНВ",$E15,IF(AM15="РНВ",$E15,IF(AN15="РНВ",$E15,IF(AO15="РНВ",$E15,IF(AP15="РНВ",$E15,IF(AQ15="РНВ",$E15,IF(AR15="РНВ",$E15,IF(AS15="РНВ",$E15,IF(AT15="РНВ",$E15,IF(AU15="РНВ",$E15,IF(AV15="РНВ",$E15,0)))))))))))) -> 9572.31 | BJ15: =IF(AX15="РНВ",$E15,IF(AY15="РНВ",$E15,IF(AZ15="РНВ",$E15,IF(BA15="РНВ",$E15,IF(BB15="РНВ",$E15,IF(BC15="РНВ",$E15,IF(BD15="РНВ",$E15,IF(BE15="РНВ",$E15,IF(BF15="РНВ",$E15,IF(BG15="РНВ",$E15,IF(BH15="РНВ",$E15,IF(BI15="РНВ",$E15,0)))))))))))) -> 0 | BW15: =IF(BK15="РНВ",$E15,IF(BL15="РНВ",$E15,IF(BM15="РНВ",$E15,IF(BN15="РНВ",$E15,IF(BO15="РНВ",$E15,IF(BP15="РНВ",$E15,IF(BQ15="РНВ",$E15,IF(BR15="РНВ",$E15,IF(BS15="РНВ",$E15,IF(BT15="РНВ",$E15,IF(BU15="РНВ",$E15,IF(BV15="РНВ",$E15,0)))))))))))) -> 0 | CJ15: =IF(BX15="РНВ",$E15,IF(BY15="РНВ",$E15,IF(BZ15="РНВ",$E15,IF(CA15="РНВ",$E15,IF(CB15="РНВ",$E15,IF(CC15="РНВ",$E15,IF(CD15="РНВ",$E15,IF(CE15="РНВ",$E15,IF(CF15="РНВ",$E15,IF(CG15="РНВ",$E15,IF(CH15="РНВ",$E15,IF(CI15="РНВ",$E15,0)))))))))))) -> 0
AK16: =IF(AK15>0,$E15/$F15,0) -> 435.105 | AL16: =IF(AL15>0,$E15/$F15,0) -> 435.105 | AM16: =IF(AM15>0,$E15/$F15,0) -> 435.105 | AN16: =IF(AN15>0,$E15/$F15,0) -> 435.105 | AO16: =IF(AO15>0,$E15/$F15,0) -> 435.105 | AP16: =IF(AP15>0,$E15/$F15,0) -> 435.105 | AQ16: =IF(AQ15>0,$E15/$F15,0) -> 435.105 | AR16: =IF(AR15>0,$E15/$F15,0) -> 435.105 | ... AV16: =IF(AV15>0,$E15/$F15,0) -> 435.105 | AX16: =IF(AX15>0,$E15/$F15,0) -> 0 | AY16: =IF(AY15>0,$E15/$F15,0) -> 0 | AZ16: =IF(AZ15>0,$E15/$F15,0) -> 0 | BA16: =IF(BA15>0,$E15/$F15,0) -> 0 | BB16: =IF(BB15>0,$E15/$F15,0) -> 0 | BC16: =IF(BC15>0,$E15/$F15,0) -> 0 | BD16: =IF(BD15>0,$E15/$F15,0) -> 0 | BE16: =IF(BE15>0,$E15/$F15,0) -> 0 | ... BI16: =IF(BI15>0,$E15/$F15,0) -> 0 | BK16: =IF(BK15>0,$E15/$F15,0) -> 0 | BL16: =IF(BL15>0,$E15/$F15,0) -> 0 | BM16: =IF(BM15>0,$E15/$F15,0) -> 0 | BN16: =IF(BN15>0,$E15/$F15,0) -> 0 | BO16: =IF(BO15>0,$E15/$F15,0) -> 0 | BP16: =IF(BP15>0,$E15/$F15,0) -> 0 | BQ16: =IF(BQ15>0,$E15/$F15,0) -> 0 | BR16: =IF(BR15>0,$E15/$F15,0) -> 0 | ... BV16: =IF(BV15>0,$E15/$F15,0) -> 0 | BX16: =IF(BX15>0,$E15/$F15,0) -> 0 | BY16: =IF(BY15>0,$E15/$F15,0) -> 0 | BZ16: =IF(BZ15>0,$E15/$F15,0) -> 0 | CA16: =IF(CA15>0,$E15/$F15,0) -> 0 | CB16: =IF(CB15>0,$E15/$F15,0) -> 0 | CC16: =IF(CC15>0,$E15/$F15,0) -> 0 | CD16: =IF(CD15>0,$E15/$F15,0) -> 0 | CE16: =IF(CE15>0,$E15/$F15,0) -> 0 | ... CI16: =IF(CI15>0,$E15/$F15,0) -> 0
A17: 6 | B17: Старый Оскол №1 | C17: Проектирование, экспертиза, получение РНС | D17: 1 | E17: 2532.72 | F17: =COUNTA(K17:V17,X17:AI17,AK17:AV17,AX17:BI17,BK17:BV17,BX17:CI17) -> 23 | W17: =IF(K17="РНВ",$E17,IF(L17="РНВ",$E17,IF(M17="РНВ",$E17,IF(N17="РНВ",$E17,IF(O17="РНВ",$E17,IF(P17="РНВ",$E17,IF(Q17="РНВ",$E17,IF(R17="РНВ",$E17,IF(S17="РНВ",$E17,IF(T17="РНВ",$E17,IF(U17="РНВ",$E17,IF(V17="РНВ",$E17,0)))))))))))) -> 0 | AJ17: =IF(X17="РНВ",$E17,IF(Y17="РНВ",$E17,IF(Z17="РНВ",$E17,IF(AA17="РНВ",$E17,IF(AB17="РНВ",$E17,IF(AC17="РНВ",$E17,IF(AD17="РНВ",$E17,IF(AE17="РНВ",$E17,IF(AF17="РНВ",$E17,IF(AG17="РНВ",$E17,IF(AH17="РНВ",$E17,IF(AI17="РНВ",$E17,0)))))))))))) -> 0 | AT17: 1 | AU17: 1 | AV17: 1 | AW17: =IF(AK17="РНВ",$E17,IF(AL17="РНВ",$E17,IF(AM17="РНВ",$E17,IF(AN17="РНВ",$E17,IF(AO17="РНВ",$E17,IF(AP17="РНВ",$E17,IF(AQ17="РНВ",$E17,IF(AR17="РНВ",$E17,IF(AS17="РНВ",$E17,IF(AT17="РНВ",$E17,IF(AU17="РНВ",$E17,IF(AV17="РНВ",$E17,0)))))))))))) -> 0 | AX17: 1 | AY17: 1 | AZ17: 1 | BA17: 1 | BB17: 1 | BC17: 1 | BD17: 1 | BE17: 1 | BF17: 1 | BG17: 1 | BH17: 1 | BI17: 1 | BJ17: =IF(AX17="РНВ",$E17,IF(AY17="РНВ",$E17,IF(AZ17="РНВ",$E17,IF(BA17="РНВ",$E17,IF(BB17="РНВ",$E17,IF(BC17="РНВ",$E17,IF(BD17="РНВ",$E17,IF(BE17="РНВ",$E17,IF(BF17="РНВ",$E17,IF(BG17="РНВ",$E17,IF(BH17="РНВ",$E17,IF(BI17="РНВ",$E17,0)))))))))))) -> 0 | BK17: 1 | BL17: 1 | BM17: 1 | BN17: 1 | BO17: 1 | BP17: 1 | BQ17: 1 | BR17: РНВ | BW17: =IF(BK17="РНВ",$E17,IF(BL17="РНВ",$E17,IF(BM17="РНВ",$E17,IF(BN17="РНВ",$E17,IF(BO17="РНВ",$E17,IF(BP17="РНВ",$E17,IF(BQ17="РНВ",$E17,IF(BR17="РНВ",$E17,IF(BS17="РНВ",$E17,IF(BT17="РНВ",$E17,IF(BU17="РНВ",$E17,IF(BV17="РНВ",$E17,0)))))))))))) -> 2532.72 | CJ17: =IF(BX17="РНВ",$E17,IF(BY17="РНВ",$E17,IF(BZ17="РНВ",$E17,IF(CA17="РНВ",$E17,IF(CB17="РНВ",$E17,IF(CC17="РНВ",$E17,IF(CD17="РНВ",$E17,IF(CE17="РНВ",$E17,IF(CF17="РНВ",$E17,IF(CG17="РНВ",$E17,IF(CH17="РНВ",$E17,IF(CI17="РНВ",$E17,0)))))))))))) -> 0
AK18: =IF(AK17>0,$E17/$F17,0) -> 0 | AL18: =IF(AL17>0,$E17/$F17,0) -> 0 | AM18: =IF(AM17>0,$E17/$F17,0) -> 0 | AN18: =IF(AN17>0,$E17/$F17,0) -> 0 | AO18: =IF(AO17>0,$E17/$F17,0) -> 0 | AP18: =IF(AP17>0,$E17/$F17,0) -> 0 | AQ18: =IF(AQ17>0,$E17/$F17,0) -> 0 | AR18: =IF(AR17>0,$E17/$F17,0) -> 0 | ... AV18: =IF(AV17>0,$E17/$F17,0) -> 110.11826 | AX18: =IF(AX17>0,$E17/$F17,0) -> 110.11826 | AY18: =IF(AY17>0,$E17/$F17,0) -> 110.11826 | AZ18: =IF(AZ17>0,$E17/$F17,0) -> 110.11826 | BA18: =IF(BA17>0,$E17/$F17,0) -> 110.11826 | BB18: =IF(BB17>0,$E17/$F17,0) -> 110.11826 | BC18: =IF(BC17>0,$E17/$F17,0) -> 110.11826 | BD18: =IF(BD17>0,$E17/$F17,0) -> 110.11826 | BE18: =IF(BE17>0,$E17/$F17,0) -> 110.11826 | ... BI18: =IF(BI17>0,$E17/$F17,0) -> 110.11826 | BK18: =IF(BK17>0,$E17/$F17,0) -> 110.11826 | BL18: =IF(BL17>0,$E17/$F17,0) -> 110.11826 | BM18: =IF(BM17>0,$E17/$F17,0) -> 110.11826 | BN18: =IF(BN17>0,$E17/$F17,0) -> 110.11826 | BO18: =IF(BO17>0,$E17/$F17,0) -> 110.11826 | BP18: =IF(BP17>0,$E17/$F17,0) -> 110.11826 | BQ18: =IF(BQ17>0,$E17/$F17,0) -> 110.11826 | BR18: =IF(BR17>0,$E17/$F17,0) -> 110.11826 | ... BV18: =IF(BV17>0,$E17/$F17,0) -> 0 | BX18: =IF(BX17>0,$E17/$F17,0) -> 0 | BY18: =IF(BY17>0,$E17/$F17,0) -> 0 | BZ18: =IF(BZ17>0,$E17/$F17,0) -> 0 | CA18: =IF(CA17>0,$E17/$F17,0) -> 0 | CB18: =IF(CB17>0,$E17/$F17,0) -> 0 | CC18: =IF(CC17>0,$E17/$F17,0) -> 0 | CD18: =IF(CD17>0,$E17/$F17,0) -> 0 | CE18: =IF(CE17>0,$E17/$F17,0) -> 0 | ... CI18: =IF(CI17>0,$E17/$F17,0) -> 0
A19: 7 | B19: Старый Оскол №2 | C19: Проектирование, экспертиза, получение РНС | D19: 3 | E19: 9013.14 | F19: =COUNTA(K19:V19,X19:AI19,AK19:AV19,AX19:BI19,BK19:BV19,BX19:CI19) -> 20 | W19: =IF(K19="РНВ",$E19,IF(L19="РНВ",$E19,IF(M19="РНВ",$E19,IF(N19="РНВ",$E19,IF(O19="РНВ",$E19,IF(P19="РНВ",$E19,IF(Q19="РНВ",$E19,IF(R19="РНВ",$E19,IF(S19="РНВ",$E19,IF(T19="РНВ",$E19,IF(U19="РНВ",$E19,IF(V19="РНВ",$E19,0)))))))))))) -> 0 | AJ19: =IF(X19="РНВ",$E19,IF(Y19="РНВ",$E19,IF(Z19="РНВ",$E19,IF(AA19="РНВ",$E19,IF(AB19="РНВ",$E19,IF(AC19="РНВ",$E19,IF(AD19="РНВ",$E19,IF(AE19="РНВ",$E19,IF(AF19="РНВ",$E19,IF(AG19="РНВ",$E19,IF(AH19="РНВ",$E19,IF(AI19="РНВ",$E19,0)))))))))))) -> 0 | AW19: =IF(AK19="РНВ",$E19,IF(AL19="РНВ",$E19,IF(AM19="РНВ",$E19,IF(AN19="РНВ",$E19,IF(AO19="РНВ",$E19,IF(AP19="РНВ",$E19,IF(AQ19="РНВ",$E19,IF(AR19="РНВ",$E19,IF(AS19="РНВ",$E19,IF(AT19="РНВ",$E19,IF(AU19="РНВ",$E19,IF(AV19="РНВ",$E19,0)))))))))))) -> 0 | BB19: 1 | BC19: 1 | BD19: 1 | BE19: 1 | BF19: 1 | BG19: 1 | BH19: 1 | BI19: 1 | BJ19: =IF(AX19="РНВ",$E19,IF(AY19="РНВ",$E19,IF(AZ19="РНВ",$E19,IF(BA19="РНВ",$E19,IF(BB19="РНВ",$E19,IF(BC19="РНВ",$E19,IF(BD19="РНВ",$E19,IF(BE19="РНВ",$E19,IF(BF19="РНВ",$E19,IF(BG19="РНВ",$E19,IF(BH19="РНВ",$E19,IF(BI19="РНВ",$E19,0)))))))))))) -> 0 | BK19: 1 | BL19: 1 | BM19: 1 | BN19: 1 | BO19: 1 | BP19: 1 | BQ19: 1 | BR19: 1 | BS19: 1 | BT19: 1 | BU19: 1 | BV19: РНВ | BW19: =IF(BK19="РНВ",$E19,IF(BL19="РНВ",$E19,IF(BM19="РНВ",$E19,IF(BN19="РНВ",$E19,IF(BO19="РНВ",$E19,IF(BP19="РНВ",$E19,IF(BQ19="РНВ",$E19,IF(BR19="РНВ",$E19,IF(BS19="РНВ",$E19,IF(BT19="РНВ",$E19,IF(BU19="РНВ",$E19,IF(BV19="РНВ",$E19,0)))))))))))) -> 9013.14 | CJ19: =IF(BX19="РНВ",$E19,IF(BY19="РНВ",$E19,IF(BZ19="РНВ",$E19,IF(CA19="РНВ",$E19,IF(CB19="РНВ",$E19,IF(CC19="РНВ",$E19,IF(CD19="РНВ",$E19,IF(CE19="РНВ",$E19,IF(CF19="РНВ",$E19,IF(CG19="РНВ",$E19,IF(CH19="РНВ",$E19,IF(CI19="РНВ",$E19,0)))))))))))) -> 0
AK20: =IF(AK19>0,$E19/$F19,0) -> 0 | AL20: =IF(AL19>0,$E19/$F19,0) -> 0 | AM20: =IF(AM19>0,$E19/$F19,0) -> 0 | AN20: =IF(AN19>0,$E19/$F19,0) -> 0 | AO20: =IF(AO19>0,$E19/$F19,0) -> 0 | AP20: =IF(AP19>0,$E19/$F19,0) -> 0 | AQ20: =IF(AQ19>0,$E19/$F19,0) -> 0 | AR20: =IF(AR19>0,$E19/$F19,0) -> 0 | ... AV20: =IF(AV19>0,$E19/$F19,0) -> 0 | AX20: =IF(AX19>0,$E19/$F19,0) -> 0 | AY20: =IF(AY19>0,$E19/$F19,0) -> 0 | AZ20: =IF(AZ19>0,$E19/$F19,0) -> 0 | BA20: =IF(BA19>0,$E19/$F19,0) -> 0 | BB20: =IF(BB19>0,$E19/$F19,0) -> 450.657 | BC20: =IF(BC19>0,$E19/$F19,0) -> 450.657 | BD20: =IF(BD19>0,$E19/$F19,0) -> 450.657 | BE20: =IF(BE19>0,$E19/$F19,0) -> 450.657 | ... BI20: =IF(BI19>0,$E19/$F19,0) -> 450.657 | BK20: =IF(BK19>0,$E19/$F19,0) -> 450.657 | BL20: =IF(BL19>0,$E19/$F19,0) -> 450.657 | BM20: =IF(BM19>0,$E19/$F19,0) -> 450.657 | BN20: =IF(BN19>0,$E19/$F19,0) -> 450.657 | BO20: =IF(BO19>0,$E19/$F19,0) -> 450.657 | BP20: =IF(BP19>0,$E19/$F19,0) -> 450.657 | BQ20: =IF(BQ19>0,$E19/$F19,0) -> 450.657 | BR20: =IF(BR19>0,$E19/$F19,0) -> 450.657 | ... BV20: =IF(BV19>0,$E19/$F19,0) -> 450.657 | BX20: =IF(BX19>0,$E19/$F19,0) -> 0 | BY20: =IF(BY19>0,$E19/$F19,0) -> 0 | BZ20: =IF(BZ19>0,$E19/$F19,0) -> 0 | CA20: =IF(CA19>0,$E19/$F19,0) -> 0 | CB20: =IF(CB19>0,$E19/$F19,0) -> 0 | CC20: =IF(CC19>0,$E19/$F19,0) -> 0 | CD20: =IF(CD19>0,$E19/$F19,0) -> 0 | CE20: =IF(CE19>0,$E19/$F19,0) -> 0 | ... CI20: =IF(CI19>0,$E19/$F19,0) -> 0
A21: 8 | B21: Старый Оскол №3 | C21: Проектирование, экспертиза, получение РНС | D21: 2 | E21: 5404.72 | F21: =COUNTA(K21:V21,X21:AI21,AK21:AV21,AX21:BI21,BK21:BV21,BX21:CI21) -> 21 | W21: =IF(K21="РНВ",$E21,IF(L21="РНВ",$E21,IF(M21="РНВ",$E21,IF(N21="РНВ",$E21,IF(O21="РНВ",$E21,IF(P21="РНВ",$E21,IF(Q21="РНВ",$E21,IF(R21="РНВ",$E21,IF(S21="РНВ",$E21,IF(T21="РНВ",$E21,IF(U21="РНВ",$E21,IF(V21="РНВ",$E21,0)))))))))))) -> 0 | AJ21: =IF(X21="РНВ",$E21,IF(Y21="РНВ",$E21,IF(Z21="РНВ",$E21,IF(AA21="РНВ",$E21,IF(AB21="РНВ",$E21,IF(AC21="РНВ",$E21,IF(AD21="РНВ",$E21,IF(AE21="РНВ",$E21,IF(AF21="РНВ",$E21,IF(AG21="РНВ",$E21,IF(AH21="РНВ",$E21,IF(AI21="РНВ",$E21,0)))))))))))) -> 0 | AW21: =IF(AK21="РНВ",$E21,IF(AL21="РНВ",$E21,IF(AM21="РНВ",$E21,IF(AN21="РНВ",$E21,IF(AO21="РНВ",$E21,IF(AP21="РНВ",$E21,IF(AQ21="РНВ",$E21,IF(AR21="РНВ",$E21,IF(AS21="РНВ",$E21,IF(AT21="РНВ",$E21,IF(AU21="РНВ",$E21,IF(AV21="РНВ",$E21,0)))))))))))) -> 0 | BJ21: =IF(AX21="РНВ",$E21,IF(AY21="РНВ",$E21,IF(AZ21="РНВ",$E21,IF(BA21="РНВ",$E21,IF(BB21="РНВ",$E21,IF(BC21="РНВ",$E21,IF(BD21="РНВ",$E21,IF(BE21="РНВ",$E21,IF(BF21="РНВ",$E21,IF(BG21="РНВ",$E21,IF(BH21="РНВ",$E21,IF(BI21="РНВ",$E21,0)))))))))))) -> 0 | BK21: 1 | BL21: 1 | BM21: 1 | BN21: 1 | BO21: 1 | BP21: 1 | BQ21: 1 | BR21: 1 | BS21: 1 | BT21: 1 | BU21: 1 | BV21: 1 | BW21: =IF(BK21="РНВ",$E21,IF(BL21="РНВ",$E21,IF(BM21="РНВ",$E21,IF(BN21="РНВ",$E21,IF(BO21="РНВ",$E21,IF(BP21="РНВ",$E21,IF(BQ21="РНВ",$E21,IF(BR21="РНВ",$E21,IF(BS21="РНВ",$E21,IF(BT21="РНВ",$E21,IF(BU21="РНВ",$E21,IF(BV21="РНВ",$E21,0)))))))))))) -> 0 | BX21: 1 | BY21: 1 | BZ21: 1 | CA21: 1 | CB21: 1 | CC21: 1 | CD21: 1 | CE21: 1 | CF21: РНВ | CJ21: =IF(BX21="РНВ",$E21,IF(BY21="РНВ",$E21,IF(BZ21="РНВ",$E21,IF(CA21="РНВ",$E21,IF(CB21="РНВ",$E21,IF(CC21="РНВ",$E21,IF(CD21="РНВ",$E21,IF(CE21="РНВ",$E21,IF(CF21="РНВ",$E21,IF(CG21="РНВ",$E21,IF(CH21="РНВ",$E21,IF(CI21="РНВ",$E21,0)))))))))))) -> 5404.72
AK22: =IF(AK21>0,$E21/$F21,0) -> 0 | AL22: =IF(AL21>0,$E21/$F21,0) -> 0 | AM22: =IF(AM21>0,$E21/$F21,0) -> 0 | AN22: =IF(AN21>0,$E21/$F21,0) -> 0 | AO22: =IF(AO21>0,$E21/$F21,0) -> 0 | AP22: =IF(AP21>0,$E21/$F21,0) -> 0 | AQ22: =IF(AQ21>0,$E21/$F21,0) -> 0 | AR22: =IF(AR21>0,$E21/$F21,0) -> 0 | ... AV22: =IF(AV21>0,$E21/$F21,0) -> 0 | AX22: =IF(AX21>0,$E21/$F21,0) -> 0 | AY22: =IF(AY21>0,$E21/$F21,0) -> 0 | AZ22: =IF(AZ21>0,$E21/$F21,0) -> 0 | BA22: =IF(BA21>0,$E21/$F21,0) -> 0 | BB22: =IF(BB21>0,$E21/$F21,0) -> 0 | BC22: =IF(BC21>0,$E21/$F21,0) -> 0 | BD22: =IF(BD21>0,$E21/$F21,0) -> 0 | BE22: =IF(BE21>0,$E21/$F21,0) -> 0 | ... BI22: =IF(BI21>0,$E21/$F21,0) -> 0 | BK22: =IF(BK21>0,$E21/$F21,0) -> 257.36762 | BL22: =IF(BL21>0,$E21/$F21,0) -> 257.36762 | BM22: =IF(BM21>0,$E21/$F21,0) -> 257.36762 | BN22: =IF(BN21>0,$E21/$F21,0) -> 257.36762 | BO22: =IF(BO21>0,$E21/$F21,0) -> 257.36762 | BP22: =IF(BP21>0,$E21/$F21,0) -> 257.36762 | BQ22: =IF(BQ21>0,$E21/$F21,0) -> 257.36762 | BR22: =IF(BR21>0,$E21/$F21,0) -> 257.36762 | ... BV22: =IF(BV21>0,$E21/$F21,0) -> 257.36762 | BX22: =IF(BX21>0,$E21/$F21,0) -> 257.36762 | BY22: =IF(BY21>0,$E21/$F21,0) -> 257.36762 | BZ22: =IF(BZ21>0,$E21/$F21,0) -> 257.36762 | CA22: =IF(CA21>0,$E21/$F21,0) -> 257.36762 | CB22: =IF(CB21>0,$E21/$F21,0) -> 257.36762 | CC22: =IF(CC21>0,$E21/$F21,0) -> 257.36762 | CD22: =IF(CD21>0,$E21/$F21,0) -> 257.36762 | CE22: =IF(CE21>0,$E21/$F21,0) -> 257.36762 | ... CI22: =IF(CI21>0,$E21/$F21,0) -> 0
A23: 9 | B23: Павловск №3 | C23: Строительство | D23: 5 | E23: 13670.6 | F23: =COUNTA(K23:V23,X23:AI23,AK23:AV23,AX23:BI23,BK23:BV23,BX23:CI23) -> 31 | P23: 1 | Q23: 1 | R23: 1 | S23: 1 | T23: 1 | U23: 1 | V23: 1 | W23: =IF(K23="РНВ",$E23,IF(L23="РНВ",$E23,IF(M23="РНВ",$E23,IF(N23="РНВ",$E23,IF(O23="РНВ",$E23,IF(P23="РНВ",$E23,IF(Q23="РНВ",$E23,IF(R23="РНВ",$E23,IF(S23="РНВ",$E23,IF(T23="РНВ",$E23,IF(U23="РНВ",$E23,IF(V23="РНВ",$E23,0)))))))))))) -> 0 | X23: 1 | Y23: 1 | Z23: 1 | AA23: 1 | AB23: 1 | AC23: 1 | AD23: 1 | AE23: 1 | AF23: 1 | AG23: 1 | AH23: 1 | AI23: 1 | AJ23: =IF(X23="РНВ",$E23,IF(Y23="РНВ",$E23,IF(Z23="РНВ",$E23,IF(AA23="РНВ",$E23,IF(AB23="РНВ",$E23,IF(AC23="РНВ",$E23,IF(AD23="РНВ",$E23,IF(AE23="РНВ",$E23,IF(AF23="РНВ",$E23,IF(AG23="РНВ",$E23,IF(AH23="РНВ",$E23,IF(AI23="РНВ",$E23,0)))))))))))) -> 0 | AK23: 1 | AL23: 1 | AM23: 1 | AN23: 1 | AO23: 1 | AP23: 1 | AQ23: 1 | AR23: 1 | AS23: 1 | AT23: 1 | AU23: 1 | AV23: РНВ | AW23: =IF(AK23="РНВ",$E23,IF(AL23="РНВ",$E23,IF(AM23="РНВ",$E23,IF(AN23="РНВ",$E23,IF(AO23="РНВ",$E23,IF(AP23="РНВ",$E23,IF(AQ23="РНВ",$E23,IF(AR23="РНВ",$E23,IF(AS23="РНВ",$E23,IF(AT23="РНВ",$E23,IF(AU23="РНВ",$E23,IF(AV23="РНВ",$E23,0)))))))))))) -> 13670.6 | BJ23: =IF(AX23="РНВ",$E23,IF(AY23="РНВ",$E23,IF(AZ23="РНВ",$E23,IF(BA23="РНВ",$E23,IF(BB23="РНВ",$E23,IF(BC23="РНВ",$E23,IF(BD23="РНВ",$E23,IF(BE23="РНВ",$E23,IF(BF23="РНВ",$E23,IF(BG23="РНВ",$E23,IF(BH23="РНВ",$E23,IF(BI23="РНВ",$E23,0)))))))))))) -> 0 | BW23: =IF(BK23="РНВ",$E23,IF(BL23="РНВ",$E23,IF(BM23="РНВ",$E23,IF(BN23="РНВ",$E23,IF(BO23="РНВ",$E23,IF(BP23="РНВ",$E23,IF(BQ23="РНВ",$E23,IF(BR23="РНВ",$E23,IF(BS23="РНВ",$E23,IF(BT23="РНВ",$E23,IF(BU23="РНВ",$E23,IF(BV23="РНВ",$E23,0)))))))))))) -> 0 | CJ23: =IF(BX23="РНВ",$E23,IF(BY23="РНВ",$E23,IF(BZ23="РНВ",$E23,IF(CA23="РНВ",$E23,IF(CB23="РНВ",$E23,IF(CC23="РНВ",$E23,IF(CD23="РНВ",$E23,IF(CE23="РНВ",$E23,IF(CF23="РНВ",$E23,IF(CG23="РНВ",$E23,IF(CH23="РНВ",$E23,IF(CI23="РНВ",$E23,0)))))))))))) -> 0
AK24: =IF(AK23>0,$E23/$F23,0) -> 440.9871 | AL24: =IF(AL23>0,$E23/$F23,0) -> 440.9871 | AM24: =IF(AM23>0,$E23/$F23,0) -> 440.9871 | AN24: =IF(AN23>0,$E23/$F23,0) -> 440.9871 | AO24: =IF(AO23>0,$E23/$F23,0) -> 440.9871 | AP24: =IF(AP23>0,$E23/$F23,0) -> 440.9871 | AQ24: =IF(AQ23>0,$E23/$F23,0) -> 440.9871 | AR24: =IF(AR23>0,$E23/$F23,0) -> 440.9871 | ... AV24: =IF(AV23>0,$E23/$F23,0) -> 440.9871 | AX24: =IF(AX23>0,$E23/$F23,0) -> 0 | AY24: =IF(AY23>0,$E23/$F23,0) -> 0 | AZ24: =IF(AZ23>0,$E23/$F23,0) -> 0 | BA24: =IF(BA23>0,$E23/$F23,0) -> 0 | BB24: =IF(BB23>0,$E23/$F23,0) -> 0 | BC24: =IF(BC23>0,$E23/$F23,0) -> 0 | BD24: =IF(BD23>0,$E23/$F23,0) -> 0 | BE24: =IF(BE23>0,$E23/$F23,0) -> 0 | ... BI24: =IF(BI23>0,$E23/$F23,0) -> 0 | BK24: =IF(BK23>0,$E23/$F23,0) -> 0 | BL24: =IF(BL23>0,$E23/$F23,0) -> 0 | BM24: =IF(BM23>0,$E23/$F23,0) -> 0 | BN24: =IF(BN23>0,$E23/$F23,0) -> 0 | BO24: =IF(BO23>0,$E23/$F23,0) -> 0 | BP24: =IF(BP23>0,$E23/$F23,0) -> 0 | BQ24: =IF(BQ23>0,$E23/$F23,0) -> 0 | BR24: =IF(BR23>0,$E23/$F23,0) -> 0 | ... BV24: =IF(BV23>0,$E23/$F23,0) -> 0 | BX24: =IF(BX23>0,$E23/$F23,0) -> 0 | BY24: =IF(BY23>0,$E23/$F23,0) -> 0 | BZ24: =IF(BZ23>0,$E23/$F23,0) -> 0 | CA24: =IF(CA23>0,$E23/$F23,0) -> 0 | CB24: =IF(CB23>0,$E23/$F23,0) -> 0 | CC24: =IF(CC23>0,$E23/$F23,0) -> 0 | CD24: =IF(CD23>0,$E23/$F23,0) -> 0 | CE24: =IF(CE23>0,$E23/$F23,0) -> 0 | ... CI24: =IF(CI23>0,$E23/$F23,0) -> 0
A25: 10 | B25: Павловск №4 | C25: Есть право на зу, ждет реализации | D25: 4 | E25: 10728.41 | F25: =COUNTA(K25:V25,X25:AI25,AK25:AV25,AX25:BI25,BK25:BV25,BX25:CI25) -> 0 | W25: =IF(K25="РНВ",$E25,IF(L25="РНВ",$E25,IF(M25="РНВ",$E25,IF(N25="РНВ",$E25,IF(O25="РНВ",$E25,IF(P25="РНВ",$E25,IF(Q25="РНВ",$E25,IF(R25="РНВ",$E25,IF(S25="РНВ",$E25,IF(T25="РНВ",$E25,IF(U25="РНВ",$E25,IF(V25="РНВ",$E25,0)))))))))))) -> 0 | AJ25: =IF(X25="РНВ",$E25,IF(Y25="РНВ",$E25,IF(Z25="РНВ",$E25,IF(AA25="РНВ",$E25,IF(AB25="РНВ",$E25,IF(AC25="РНВ",$E25,IF(AD25="РНВ",$E25,IF(AE25="РНВ",$E25,IF(AF25="РНВ",$E25,IF(AG25="РНВ",$E25,IF(AH25="РНВ",$E25,IF(AI25="РНВ",$E25,0)))))))))))) -> 0 | AW25: =IF(AK25="РНВ",$E25,IF(AL25="РНВ",$E25,IF(AM25="РНВ",$E25,IF(AN25="РНВ",$E25,IF(AO25="РНВ",$E25,IF(AP25="РНВ",$E25,IF(AQ25="РНВ",$E25,IF(AR25="РНВ",$E25,IF(AS25="РНВ",$E25,IF(AT25="РНВ",$E25,IF(AU25="РНВ",$E25,IF(AV25="РНВ",$E25,0)))))))))))) -> 0 | BJ25: =IF(AX25="РНВ",$E25,IF(AY25="РНВ",$E25,IF(AZ25="РНВ",$E25,IF(BA25="РНВ",$E25,IF(BB25="РНВ",$E25,IF(BC25="РНВ",$E25,IF(BD25="РНВ",$E25,IF(BE25="РНВ",$E25,IF(BF25="РНВ",$E25,IF(BG25="РНВ",$E25,IF(BH25="РНВ",$E25,IF(BI25="РНВ",$E25,0)))))))))))) -> 0 | BW25: =IF(BK25="РНВ",$E25,IF(BL25="РНВ",$E25,IF(BM25="РНВ",$E25,IF(BN25="РНВ",$E25,IF(BO25="РНВ",$E25,IF(BP25="РНВ",$E25,IF(BQ25="РНВ",$E25,IF(BR25="РНВ",$E25,IF(BS25="РНВ",$E25,IF(BT25="РНВ",$E25,IF(BU25="РНВ",$E25,IF(BV25="РНВ",$E25,0)))))))))))) -> 0 | CJ25: =IF(BX25="РНВ",$E25,IF(BY25="РНВ",$E25,IF(BZ25="РНВ",$E25,IF(CA25="РНВ",$E25,IF(CB25="РНВ",$E25,IF(CC25="РНВ",$E25,IF(CD25="РНВ",$E25,IF(CE25="РНВ",$E25,IF(CF25="РНВ",$E25,IF(CG25="РНВ",$E25,IF(CH25="РНВ",$E25,IF(CI25="РНВ",$E25,0)))))))))))) -> 0
AK26: =IF(AK25>0,$E25/$F25,0) -> 0 | AL26: =IF(AL25>0,$E25/$F25,0) -> 0 | AM26: =IF(AM25>0,$E25/$F25,0) -> 0 | AN26: =IF(AN25>0,$E25/$F25,0) -> 0 | AO26: =IF(AO25>0,$E25/$F25,0) -> 0 | AP26: =IF(AP25>0,$E25/$F25,0) -> 0 | AQ26: =IF(AQ25>0,$E25/$F25,0) -> 0 | AR26: =IF(AR25>0,$E25/$F25,0) -> 0 | ... AV26: =IF(AV25>0,$E25/$F25,0) -> 0 | AX26: =IF(AX25>0,$E25/$F25,0) -> 0 | AY26: =IF(AY25>0,$E25/$F25,0) -> 0 | AZ26: =IF(AZ25>0,$E25/$F25,0) -> 0 | BA26: =IF(BA25>0,$E25/$F25,0) -> 0 | BB26: =IF(BB25>0,$E25/$F25,0) -> 0 | BC26: =IF(BC25>0,$E25/$F25,0) -> 0 | BD26: =IF(BD25>0,$E25/$F25,0) -> 0 | BE26: =IF(BE25>0,$E25/$F25,0) -> 0 | ... BI26: =IF(BI25>0,$E25/$F25,0) -> 0 | BK26: =IF(BK25>0,$E25/$F25,0) -> 0 | BL26: =IF(BL25>0,$E25/$F25,0) -> 0 | BM26: =IF(BM25>0,$E25/$F25,0) -> 0 | BN26: =IF(BN25>0,$E25/$F25,0) -> 0 | BO26: =IF(BO25>0,$E25/$F25,0) -> 0 | BP26: =IF(BP25>0,$E25/$F25,0) -> 0 | BQ26: =IF(BQ25>0,$E25/$F25,0) -> 0 | BR26: =IF(BR25>0,$E25/$F25,0) -> 0 | ... BV26: =IF(BV25>0,$E25/$F25,0) -> 0 | BX26: =IF(BX25>0,$E25/$F25,0) -> 0 | BY26: =IF(BY25>0,$E25/$F25,0) -> 0 | BZ26: =IF(BZ25>0,$E25/$F25,0) -> 0 | CA26: =IF(CA25>0,$E25/$F25,0) -> 0 | CB26: =IF(CB25>0,$E25/$F25,0) -> 0 | CC26: =IF(CC25>0,$E25/$F25,0) -> 0 | CD26: =IF(CD25>0,$E25/$F25,0) -> 0 | CE26: =IF(CE25>0,$E25/$F25,0) -> 0 | ... CI26: =IF(CI25>0,$E25/$F25,0) -> 0
A27: 11 | B27: Выкса №1 | C27: Строительство | D27: 2 | E27: 5690.87 | F27: =COUNTA(K27:V27,X27:AI27,AK27:AV27,AX27:BI27,BK27:BV27,BX27:CI27) -> 22 | S27: 1 | T27: 1 | U27: 1 | V27: 1 | W27: =IF(K27="РНВ",$E27,IF(L27="РНВ",$E27,IF(M27="РНВ",$E27,IF(N27="РНВ",$E27,IF(O27="РНВ",$E27,IF(P27="РНВ",$E27,IF(Q27="РНВ",$E27,IF(R27="РНВ",$E27,IF(S27="РНВ",$E27,IF(T27="РНВ",$E27,IF(U27="РНВ",$E27,IF(V27="РНВ",$E27,0)))))))))))) -> 0 | X27: 1 | Y27: 1 | Z27: 1 | AA27: 1 | AB27: 1 | AC27: 1 | AD27: 1 | AE27: 1 | AF27: 1 | AG27: 1 | AH27: 1 | AI27: 1 | AJ27: =IF(X27="РНВ",$E27,IF(Y27="РНВ",$E27,IF(Z27="РНВ",$E27,IF(AA27="РНВ",$E27,IF(AB27="РНВ",$E27,IF(AC27="РНВ",$E27,IF(AD27="РНВ",$E27,IF(AE27="РНВ",$E27,IF(AF27="РНВ",$E27,IF(AG27="РНВ",$E27,IF(AH27="РНВ",$E27,IF(AI27="РНВ",$E27,0)))))))))))) -> 0 | AK27: 1 | AL27: 1 | AM27: 1 | AN27: 1 | AO27: 1 | AP27: РНВ | AW27: =IF(AK27="РНВ",$E27,IF(AL27="РНВ",$E27,IF(AM27="РНВ",$E27,IF(AN27="РНВ",$E27,IF(AO27="РНВ",$E27,IF(AP27="РНВ",$E27,IF(AQ27="РНВ",$E27,IF(AR27="РНВ",$E27,IF(AS27="РНВ",$E27,IF(AT27="РНВ",$E27,IF(AU27="РНВ",$E27,IF(AV27="РНВ",$E27,0)))))))))))) -> 5690.87 | BJ27: =IF(AX27="РНВ",$E27,IF(AY27="РНВ",$E27,IF(AZ27="РНВ",$E27,IF(BA27="РНВ",$E27,IF(BB27="РНВ",$E27,IF(BC27="РНВ",$E27,IF(BD27="РНВ",$E27,IF(BE27="РНВ",$E27,IF(BF27="РНВ",$E27,IF(BG27="РНВ",$E27,IF(BH27="РНВ",$E27,IF(BI27="РНВ",$E27,0)))))))))))) -> 0 | BW27: =IF(BK27="РНВ",$E27,IF(BL27="РНВ",$E27,IF(BM27="РНВ",$E27,IF(BN27="РНВ",$E27,IF(BO27="РНВ",$E27,IF(BP27="РНВ",$E27,IF(BQ27="РНВ",$E27,IF(BR27="РНВ",$E27,IF(BS27="РНВ",$E27,IF(BT27="РНВ",$E27,IF(BU27="РНВ",$E27,IF(BV27="РНВ",$E27,0)))))))))))) -> 0 | CJ27: =IF(BX27="РНВ",$E27,IF(BY27="РНВ",$E27,IF(BZ27="РНВ",$E27,IF(CA27="РНВ",$E27,IF(CB27="РНВ",$E27,IF(CC27="РНВ",$E27,IF(CD27="РНВ",$E27,IF(CE27="РНВ",$E27,IF(CF27="РНВ",$E27,IF(CG27="РНВ",$E27,IF(CH27="РНВ",$E27,IF(CI27="РНВ",$E27,0)))))))))))) -> 0
AK28: =IF(AK27>0,$E27/$F27,0) -> 258.67591 | AL28: =IF(AL27>0,$E27/$F27,0) -> 258.67591 | AM28: =IF(AM27>0,$E27/$F27,0) -> 258.67591 | AN28: =IF(AN27>0,$E27/$F27,0) -> 258.67591 | AO28: =IF(AO27>0,$E27/$F27,0) -> 258.67591 | AP28: =IF(AP27>0,$E27/$F27,0) -> 258.67591 | AQ28: =IF(AQ27>0,$E27/$F27,0) -> 0 | AR28: =IF(AR27>0,$E27/$F27,0) -> 0 | ... AV28: =IF(AV27>0,$E27/$F27,0) -> 0 | AX28: =IF(AX27>0,$E27/$F27,0) -> 0 | AY28: =IF(AY27>0,$E27/$F27,0) -> 0 | AZ28: =IF(AZ27>0,$E27/$F27,0) -> 0 | BA28: =IF(BA27>0,$E27/$F27,0) -> 0 | BB28: =IF(BB27>0,$E27/$F27,0) -> 0 | BC28: =IF(BC27>0,$E27/$F27,0) -> 0 | BD28: =IF(BD27>0,$E27/$F27,0) -> 0 | BE28: =IF(BE27>0,$E27/$F27,0) -> 0 | ... BI28: =IF(BI27>0,$E27/$F27,0) -> 0 | BK28: =IF(BK27>0,$E27/$F27,0) -> 0 | BL28: =IF(BL27>0,$E27/$F27,0) -> 0 | BM28: =IF(BM27>0,$E27/$F27,0) -> 0 | BN28: =IF(BN27>0,$E27/$F27,0) -> 0 | BO28: =IF(BO27>0,$E27/$F27,0) -> 0 | BP28: =IF(BP27>0,$E27/$F27,0) -> 0 | BQ28: =IF(BQ27>0,$E27/$F27,0) -> 0 | BR28: =IF(BR27>0,$E27/$F27,0) -> 0 | ... BV28: =IF(BV27>0,$E27/$F27,0) -> 0 | BX28: =IF(BX27>0,$E27/$F27,0) -> 0 | BY28: =IF(BY27>0,$E27/$F27,0) -> 0 | BZ28: =IF(BZ27>0,$E27/$F27,0) -> 0 | CA28: =IF(CA27>0,$E27/$F27,0) -> 0 | CB28: =IF(CB27>0,$E27/$F27,0) -> 0 | CC28: =IF(CC27>0,$E27/$F27,0) -> 0 | CD28: =IF(CD27>0,$E27/$F27,0) -> 0 | CE28: =IF(CE27>0,$E27/$F27,0) -> 0 | ... CI28: =IF(CI27>0,$E27/$F27,0) -> 0
A29: 12 | B29: Выкса №2 | C29: Строительство | D29: 3 | E29: 8537.46 | F29: =COUNTA(K29:V29,X29:AI29,AK29:AV29,AX29:BI29,BK29:BV29,BX29:CI29) -> 22 | W29: =IF(K29="РНВ",$E29,IF(L29="РНВ",$E29,IF(M29="РНВ",$E29,IF(N29="РНВ",$E29,IF(O29="РНВ",$E29,IF(P29="РНВ",$E29,IF(Q29="РНВ",$E29,IF(R29="РНВ",$E29,IF(S29="РНВ",$E29,IF(T29="РНВ",$E29,IF(U29="РНВ",$E29,IF(V29="РНВ",$E29,0)))))))))))) -> 0 | Y29: 1 | Z29: 1 | AA29: 1 | AB29: 1 | AC29: 1 | AD29: 1 | AE29: 1 | AF29: 1 | AG29: 1 | AH29: 1 | AI29: 1 | AJ29: =IF(X29="РНВ",$E29,IF(Y29="РНВ",$E29,IF(Z29="РНВ",$E29,IF(AA29="РНВ",$E29,IF(AB29="РНВ",$E29,IF(AC29="РНВ",$E29,IF(AD29="РНВ",$E29,IF(AE29="РНВ",$E29,IF(AF29="РНВ",$E29,IF(AG29="РНВ",$E29,IF(AH29="РНВ",$E29,IF(AI29="РНВ",$E29,0)))))))))))) -> 0 | AK29: 1 | AL29: 1 | AM29: 1 | AN29: 1 | AO29: 1 | AP29: 1 | AQ29: 1 | AR29: 1 | AS29: 1 | AT29: 1 | AU29: РНВ | AW29: =IF(AK29="РНВ",$E29,IF(AL29="РНВ",$E29,IF(AM29="РНВ",$E29,IF(AN29="РНВ",$E29,IF(AO29="РНВ",$E29,IF(AP29="РНВ",$E29,IF(AQ29="РНВ",$E29,IF(AR29="РНВ",$E29,IF(AS29="РНВ",$E29,IF(AT29="РНВ",$E29,IF(AU29="РНВ",$E29,IF(AV29="РНВ",$E29,0)))))))))))) -> 8537.46 | BJ29: =IF(AX29="РНВ",$E29,IF(AY29="РНВ",$E29,IF(AZ29="РНВ",$E29,IF(BA29="РНВ",$E29,IF(BB29="РНВ",$E29,IF(BC29="РНВ",$E29,IF(BD29="РНВ",$E29,IF(BE29="РНВ",$E29,IF(BF29="РНВ",$E29,IF(BG29="РНВ",$E29,IF(BH29="РНВ",$E29,IF(BI29="РНВ",$E29,0)))))))))))) -> 0 | BW29: =IF(BK29="РНВ",$E29,IF(BL29="РНВ",$E29,IF(BM29="РНВ",$E29,IF(BN29="РНВ",$E29,IF(BO29="РНВ",$E29,IF(BP29="РНВ",$E29,IF(BQ29="РНВ",$E29,IF(BR29="РНВ",$E29,IF(BS29="РНВ",$E29,IF(BT29="РНВ",$E29,IF(BU29="РНВ",$E29,IF(BV29="РНВ",$E29,0)))))))))))) -> 0 | CJ29: =IF(BX29="РНВ",$E29,IF(BY29="РНВ",$E29,IF(BZ29="РНВ",$E29,IF(CA29="РНВ",$E29,IF(CB29="РНВ",$E29,IF(CC29="РНВ",$E29,IF(CD29="РНВ",$E29,IF(CE29="РНВ",$E29,IF(CF29="РНВ",$E29,IF(CG29="РНВ",$E29,IF(CH29="РНВ",$E29,IF(CI29="РНВ",$E29,0)))))))))))) -> 0
AK30: =IF(AK29>0,$E29/$F29,0) -> 388.06636 | AL30: =IF(AL29>0,$E29/$F29,0) -> 388.06636 | AM30: =IF(AM29>0,$E29/$F29,0) -> 388.06636 | AN30: =IF(AN29>0,$E29/$F29,0) -> 388.06636 | AO30: =IF(AO29>0,$E29/$F29,0) -> 388.06636 | AP30: =IF(AP29>0,$E29/$F29,0) -> 388.06636 | AQ30: =IF(AQ29>0,$E29/$F29,0) -> 388.06636 | AR30: =IF(AR29>0,$E29/$F29,0) -> 388.06636 | ... AV30: =IF(AV29>0,$E29/$F29,0) -> 0 | AX30: =IF(AX29>0,$E29/$F29,0) -> 0 | AY30: =IF(AY29>0,$E29/$F29,0) -> 0 | AZ30: =IF(AZ29>0,$E29/$F29,0) -> 0 | BA30: =IF(BA29>0,$E29/$F29,0) -> 0 | BB30: =IF(BB29>0,$E29/$F29,0) -> 0 | BC30: =IF(BC29>0,$E29/$F29,0) -> 0 | BD30: =IF(BD29>0,$E29/$F29,0) -> 0 | BE30: =IF(BE29>0,$E29/$F29,0) -> 0 | ... BI30: =IF(BI29>0,$E29/$F29,0) -> 0 | BK30: =IF(BK29>0,$E29/$F29,0) -> 0 | BL30: =IF(BL29>0,$E29/$F29,0) -> 0 | BM30: =IF(BM29>0,$E29/$F29,0) -> 0 | BN30: =IF(BN29>0,$E29/$F29,0) -> 0 | BO30: =IF(BO29>0,$E29/$F29,0) -> 0 | BP30: =IF(BP29>0,$E29/$F29,0) -> 0 | BQ30: =IF(BQ29>0,$E29/$F29,0) -> 0 | BR30: =IF(BR29>0,$E29/$F29,0) -> 0 | ... BV30: =IF(BV29>0,$E29/$F29,0) -> 0 | BX30: =IF(BX29>0,$E29/$F29,0) -> 0 | BY30: =IF(BY29>0,$E29/$F29,0) -> 0 | BZ30: =IF(BZ29>0,$E29/$F29,0) -> 0 | CA30: =IF(CA29>0,$E29/$F29,0) -> 0 | CB30: =IF(CB29>0,$E29/$F29,0) -> 0 | CC30: =IF(CC29>0,$E29/$F29,0) -> 0 | CD30: =IF(CD29>0,$E29/$F29,0) -> 0 | CE30: =IF(CE29>0,$E29/$F29,0) -> 0 | ... CI30: =IF(CI29>0,$E29/$F29,0) -> 0
A31: 13 | B31: Выкса №3 | C31: Проектирование, экспертиза, получение РНС | D31: 3 | E31: 8537.46 | F31: =COUNTA(K31:V31,X31:AI31,AK31:AV31,AX31:BI31,BK31:BV31,BX31:CI31) -> 24 | W31: =IF(K31="РНВ",$E31,IF(L31="РНВ",$E31,IF(M31="РНВ",$E31,IF(N31="РНВ",$E31,IF(O31="РНВ",$E31,IF(P31="РНВ",$E31,IF(Q31="РНВ",$E31,IF(R31="РНВ",$E31,IF(S31="РНВ",$E31,IF(T31="РНВ",$E31,IF(U31="РНВ",$E31,IF(V31="РНВ",$E31,0)))))))))))) -> 0 | AH31: 1 | AI31: 1 | AJ31: =IF(X31="РНВ",$E31,IF(Y31="РНВ",$E31,IF(Z31="РНВ",$E31,IF(AA31="РНВ",$E31,IF(AB31="РНВ",$E31,IF(AC31="РНВ",$E31,IF(AD31="РНВ",$E31,IF(AE31="РНВ",$E31,IF(AF31="РНВ",$E31,IF(AG31="РНВ",$E31,IF(AH31="РНВ",$E31,IF(AI31="РНВ",$E31,0)))))))))))) -> 0 | AK31: 1 | AL31: 1 | AM31: 1 | AN31: 1 | AO31: 1 | AP31: 1 | AQ31: 1 | AR31: 1 | AS31: 1 | AT31: 1 | AU31: 1 | AV31: 1 | AW31: =IF(AK31="РНВ",$E31,IF(AL31="РНВ",$E31,IF(AM31="РНВ",$E31,IF(AN31="РНВ",$E31,IF(AO31="РНВ",$E31,IF(AP31="РНВ",$E31,IF(AQ31="РНВ",$E31,IF(AR31="РНВ",$E31,IF(AS31="РНВ",$E31,IF(AT31="РНВ",$E31,IF(AU31="РНВ",$E31,IF(AV31="РНВ",$E31,0)))))))))))) -> 0 | AX31: 1 | AY31: 1 | AZ31: 1 | BA31: 1 | BB31: 1 | BC31: 1 | BD31: 1 | BE31: 1 | BF31: 1 | BG31: РНВ | BJ31: =IF(AX31="РНВ",$E31,IF(AY31="РНВ",$E31,IF(AZ31="РНВ",$E31,IF(BA31="РНВ",$E31,IF(BB31="РНВ",$E31,IF(BC31="РНВ",$E31,IF(BD31="РНВ",$E31,IF(BE31="РНВ",$E31,IF(BF31="РНВ",$E31,IF(BG31="РНВ",$E31,IF(BH31="РНВ",$E31,IF(BI31="РНВ",$E31,0)))))))))))) -> 8537.46 | BW31: =IF(BK31="РНВ",$E31,IF(BL31="РНВ",$E31,IF(BM31="РНВ",$E31,IF(BN31="РНВ",$E31,IF(BO31="РНВ",$E31,IF(BP31="РНВ",$E31,IF(BQ31="РНВ",$E31,IF(BR31="РНВ",$E31,IF(BS31="РНВ",$E31,IF(BT31="РНВ",$E31,IF(BU31="РНВ",$E31,IF(BV31="РНВ",$E31,0)))))))))))) -> 0 | CJ31: =IF(BX31="РНВ",$E31,IF(BY31="РНВ",$E31,IF(BZ31="РНВ",$E31,IF(CA31="РНВ",$E31,IF(CB31="РНВ",$E31,IF(CC31="РНВ",$E31,IF(CD31="РНВ",$E31,IF(CE31="РНВ",$E31,IF(CF31="РНВ",$E31,IF(CG31="РНВ",$E31,IF(CH31="РНВ",$E31,IF(CI31="РНВ",$E31,0)))))))))))) -> 0
AK32: =IF(AK31>0,$E31/$F31,0) -> 355.7275 | AL32: =IF(AL31>0,$E31/$F31,0) -> 355.7275 | AM32: =IF(AM31>0,$E31/$F31,0) -> 355.7275 | AN32: =IF(AN31>0,$E31/$F31,0) -> 355.7275 | AO32: =IF(AO31>0,$E31/$F31,0) -> 355.7275 | AP32: =IF(AP31>0,$E31/$F31,0) -> 355.7275 | AQ32: =IF(AQ31>0,$E31/$F31,0) -> 355.7275 | AR32: =IF(AR31>0,$E31/$F31,0) -> 355.7275 | ... AV32: =IF(AV31>0,$E31/$F31,0) -> 355.7275 | AX32: =IF(AX31>0,$E31/$F31,0) -> 355.7275 | AY32: =IF(AY31>0,$E31/$F31,0) -> 355.7275 | AZ32: =IF(AZ31>0,$E31/$F31,0) -> 355.7275 | BA32: =IF(BA31>0,$E31/$F31,0) -> 355.7275 | BB32: =IF(BB31>0,$E31/$F31,0) -> 355.7275 | BC32: =IF(BC31>0,$E31/$F31,0) -> 355.7275 | BD32: =IF(BD31>0,$E31/$F31,0) -> 355.7275 | BE32: =IF(BE31>0,$E31/$F31,0) -> 355.7275 | ... BI32: =IF(BI31>0,$E31/$F31,0) -> 0 | BK32: =IF(BK31>0,$E31/$F31,0) -> 0 | BL32: =IF(BL31>0,$E31/$F31,0) -> 0 | BM32: =IF(BM31>0,$E31/$F31,0) -> 0 | BN32: =IF(BN31>0,$E31/$F31,0) -> 0 | BO32: =IF(BO31>0,$E31/$F31,0) -> 0 | BP32: =IF(BP31>0,$E31/$F31,0) -> 0 | BQ32: =IF(BQ31>0,$E31/$F31,0) -> 0 | BR32: =IF(BR31>0,$E31/$F31,0) -> 0 | ... BV32: =IF(BV31>0,$E31/$F31,0) -> 0 | BX32: =IF(BX31>0,$E31/$F31,0) -> 0 | BY32: =IF(BY31>0,$E31/$F31,0) -> 0 | BZ32: =IF(BZ31>0,$E31/$F31,0) -> 0 | CA32: =IF(CA31>0,$E31/$F31,0) -> 0 | CB32: =IF(CB31>0,$E31/$F31,0) -> 0 | CC32: =IF(CC31>0,$E31/$F31,0) -> 0 | CD32: =IF(CD31>0,$E31/$F31,0) -> 0 | CE32: =IF(CE31>0,$E31/$F31,0) -> 0 | ... CI32: =IF(CI31>0,$E31/$F31,0) -> 0
A33: 14 | B33: Выкса №4 | C33: Есть право на зу, ждет реализации | D33: 2 | E33: 5652.62 | F33: =COUNTA(K33:V33,X33:AI33,AK33:AV33,AX33:BI33,BK33:BV33,BX33:CI33) -> 18 | W33: =IF(K33="РНВ",$E33,IF(L33="РНВ",$E33,IF(M33="РНВ",$E33,IF(N33="РНВ",$E33,IF(O33="РНВ",$E33,IF(P33="РНВ",$E33,IF(Q33="РНВ",$E33,IF(R33="РНВ",$E33,IF(S33="РНВ",$E33,IF(T33="РНВ",$E33,IF(U33="РНВ",$E33,IF(V33="РНВ",$E33,0)))))))))))) -> 0 | AJ33: =IF(X33="РНВ",$E33,IF(Y33="РНВ",$E33,IF(Z33="РНВ",$E33,IF(AA33="РНВ",$E33,IF(AB33="РНВ",$E33,IF(AC33="РНВ",$E33,IF(AD33="РНВ",$E33,IF(AE33="РНВ",$E33,IF(AF33="РНВ",$E33,IF(AG33="РНВ",$E33,IF(AH33="РНВ",$E33,IF(AI33="РНВ",$E33,0)))))))))))) -> 0 | AT33: 1 | AU33: 1 | AV33: 1 | AW33: =IF(AK33="РНВ",$E33,IF(AL33="РНВ",$E33,IF(AM33="РНВ",$E33,IF(AN33="РНВ",$E33,IF(AO33="РНВ",$E33,IF(AP33="РНВ",$E33,IF(AQ33="РНВ",$E33,IF(AR33="РНВ",$E33,IF(AS33="РНВ",$E33,IF(AT33="РНВ",$E33,IF(AU33="РНВ",$E33,IF(AV33="РНВ",$E33,0)))))))))))) -> 0 | AX33: 1 | AY33: 1 | AZ33: 1 | BA33: 1 | BB33: 1 | BC33: 1 | BD33: 1 | BE33: 1 | BF33: 1 | BG33: 1 | BH33: 1 | BI33: 1 | BJ33: =IF(AX33="РНВ",$E33,IF(AY33="РНВ",$E33,IF(AZ33="РНВ",$E33,IF(BA33="РНВ",$E33,IF(BB33="РНВ",$E33,IF(BC33="РНВ",$E33,IF(BD33="РНВ",$E33,IF(BE33="РНВ",$E33,IF(BF33="РНВ",$E33,IF(BG33="РНВ",$E33,IF(BH33="РНВ",$E33,IF(BI33="РНВ",$E33,0)))))))))))) -> 0 | BK33: 1 | BL33: 1 | BM33: РНВ | BW33: =IF(BK33="РНВ",$E33,IF(BL33="РНВ",$E33,IF(BM33="РНВ",$E33,IF(BN33="РНВ",$E33,IF(BO33="РНВ",$E33,IF(BP33="РНВ",$E33,IF(BQ33="РНВ",$E33,IF(BR33="РНВ",$E33,IF(BS33="РНВ",$E33,IF(BT33="РНВ",$E33,IF(BU33="РНВ",$E33,IF(BV33="РНВ",$E33,0)))))))))))) -> 5652.62 | CJ33: =IF(BX33="РНВ",$E33,IF(BY33="РНВ",$E33,IF(BZ33="РНВ",$E33,IF(CA33="РНВ",$E33,IF(CB33="РНВ",$E33,IF(CC33="РНВ",$E33,IF(CD33="РНВ",$E33,IF(CE33="РНВ",$E33,IF(CF33="РНВ",$E33,IF(CG33="РНВ",$E33,IF(CH33="РНВ",$E33,IF(CI33="РНВ",$E33,0)))))))))))) -> 0
AK34: =IF(AK33>0,$E33/$F33,0) -> 0 | AL34: =IF(AL33>0,$E33/$F33,0) -> 0 | AM34: =IF(AM33>0,$E33/$F33,0) -> 0 | AN34: =IF(AN33>0,$E33/$F33,0) -> 0 | AO34: =IF(AO33>0,$E33/$F33,0) -> 0 | AP34: =IF(AP33>0,$E33/$F33,0) -> 0 | AQ34: =IF(AQ33>0,$E33/$F33,0) -> 0 | AR34: =IF(AR33>0,$E33/$F33,0) -> 0 | ... AV34: =IF(AV33>0,$E33/$F33,0) -> 314.03444 | AX34: =IF(AX33>0,$E33/$F33,0) -> 314.03444 | AY34: =IF(AY33>0,$E33/$F33,0) -> 314.03444 | AZ34: =IF(AZ33>0,$E33/$F33,0) -> 314.03444 | BA34: =IF(BA33>0,$E33/$F33,0) -> 314.03444 | BB34: =IF(BB33>0,$E33/$F33,0) -> 314.03444 | BC34: =IF(BC33>0,$E33/$F33,0) -> 314.03444 | BD34: =IF(BD33>0,$E33/$F33,0) -> 314.03444 | BE34: =IF(BE33>0,$E33/$F33,0) -> 314.03444 | ... BI34: =IF(BI33>0,$E33/$F33,0) -> 314.03444 | BK34: =IF(BK33>0,$E33/$F33,0) -> 314.03444 | BL34: =IF(BL33>0,$E33/$F33,0) -> 314.03444 | BM34: =IF(BM33>0,$E33/$F33,0) -> 314.03444 | BN34: =IF(BN33>0,$E33/$F33,0) -> 0 | BO34: =IF(BO33>0,$E33/$F33,0) -> 0 | BP34: =IF(BP33>0,$E33/$F33,0) -> 0 | BQ34: =IF(BQ33>0,$E33/$F33,0) -> 0 | BR34: =IF(BR33>0,$E33/$F33,0) -> 0 | ... BV34: =IF(BV33>0,$E33/$F33,0) -> 0 | BX34: =IF(BX33>0,$E33/$F33,0) -> 0 | BY34: =IF(BY33>0,$E33/$F33,0) -> 0 | BZ34: =IF(BZ33>0,$E33/$F33,0) -> 0 | CA34: =IF(CA33>0,$E33/$F33,0) -> 0 | CB34: =IF(CB33>0,$E33/$F33,0) -> 0 | CC34: =IF(CC33>0,$E33/$F33,0) -> 0 | CD34: =IF(CD33>0,$E33/$F33,0) -> 0 | CE34: =IF(CE33>0,$E33/$F33,0) -> 0 | ... CI34: =IF(CI33>0,$E33/$F33,0) -> 0
A35: 15 | B35: Узловая (озеро) | C35: Строительство | D35: 3 | E35: 8564.36 | F35: =COUNTA(K35:V35,X35:AI35,AK35:AV35,AX35:BI35,BK35:BV35,BX35:CI35) -> 30 | W35: =IF(K35="РНВ",$E35,IF(L35="РНВ",$E35,IF(M35="РНВ",$E35,IF(N35="РНВ",$E35,IF(O35="РНВ",$E35,IF(P35="РНВ",$E35,IF(Q35="РНВ",$E35,IF(R35="РНВ",$E35,IF(S35="РНВ",$E35,IF(T35="РНВ",$E35,IF(U35="РНВ",$E35,IF(V35="РНВ",$E35,0)))))))))))) -> 0 | AC35: 1 | AD35: 1 | AE35: 1 | AF35: 1 | AG35: 1 | AH35: 1 | AI35: 1 | AJ35: =IF(X35="РНВ",$E35,IF(Y35="РНВ",$E35,IF(Z35="РНВ",$E35,IF(AA35="РНВ",$E35,IF(AB35="РНВ",$E35,IF(AC35="РНВ",$E35,IF(AD35="РНВ",$E35,IF(AE35="РНВ",$E35,IF(AF35="РНВ",$E35,IF(AG35="РНВ",$E35,IF(AH35="РНВ",$E35,IF(AI35="РНВ",$E35,0)))))))))))) -> 0 | AK35: 1 | AL35: 1 | AM35: 1 | AN35: 1 | AO35: 1 | AP35: 1 | AQ35: 1 | AR35: 1 | AS35: 1 | AT35: 1 | AU35: 1 | AV35: 1 | AW35: =IF(AK35="РНВ",$E35,IF(AL35="РНВ",$E35,IF(AM35="РНВ",$E35,IF(AN35="РНВ",$E35,IF(AO35="РНВ",$E35,IF(AP35="РНВ",$E35,IF(AQ35="РНВ",$E35,IF(AR35="РНВ",$E35,IF(AS35="РНВ",$E35,IF(AT35="РНВ",$E35,IF(AU35="РНВ",$E35,IF(AV35="РНВ",$E35,0)))))))))))) -> 0 | AX35: 1 | AY35: 1 | AZ35: 1 | BA35: 1 | BB35: 1 | BC35: 1 | BD35: 1 | BE35: 1 | BF35: 1 | BG35: 1 | BH35: РНВ | BJ35: =IF(AX35="РНВ",$E35,IF(AY35="РНВ",$E35,IF(AZ35="РНВ",$E35,IF(BA35="РНВ",$E35,IF(BB35="РНВ",$E35,IF(BC35="РНВ",$E35,IF(BD35="РНВ",$E35,IF(BE35="РНВ",$E35,IF(BF35="РНВ",$E35,IF(BG35="РНВ",$E35,IF(BH35="РНВ",$E35,IF(BI35="РНВ",$E35,0)))))))))))) -> 8564.36 | BW35: =IF(BK35="РНВ",$E35,IF(BL35="РНВ",$E35,IF(BM35="РНВ",$E35,IF(BN35="РНВ",$E35,IF(BO35="РНВ",$E35,IF(BP35="РНВ",$E35,IF(BQ35="РНВ",$E35,IF(BR35="РНВ",$E35,IF(BS35="РНВ",$E35,IF(BT35="РНВ",$E35,IF(BU35="РНВ",$E35,IF(BV35="РНВ",$E35,0)))))))))))) -> 0 | CJ35: =IF(BX35="РНВ",$E35,IF(BY35="РНВ",$E35,IF(BZ35="РНВ",$E35,IF(CA35="РНВ",$E35,IF(CB35="РНВ",$E35,IF(CC35="РНВ",$E35,IF(CD35="РНВ",$E35,IF(CE35="РНВ",$E35,IF(CF35="РНВ",$E35,IF(CG35="РНВ",$E35,IF(CH35="РНВ",$E35,IF(CI35="РНВ",$E35,0)))))))))))) -> 0
V36: 647082 | AK36: =IF(AK35>0,$E35/$F35,0) -> 285.47867 | AL36: =IF(AL35>0,$E35/$F35,0) -> 285.47867 | AM36: =IF(AM35>0,$E35/$F35,0) -> 285.47867 | AN36: =IF(AN35>0,$E35/$F35,0) -> 285.47867 | AO36: =IF(AO35>0,$E35/$F35,0) -> 285.47867 | AP36: =IF(AP35>0,$E35/$F35,0) -> 285.47867 | AQ36: =IF(AQ35>0,$E35/$F35,0) -> 285.47867 | AR36: =IF(AR35>0,$E35/$F35,0) -> 285.47867 | ... AV36: =IF(AV35>0,$E35/$F35,0) -> 285.47867 | AX36: =IF(AX35>0,$E35/$F35,0) -> 285.47867 | AY36: =IF(AY35>0,$E35/$F35,0) -> 285.47867 | AZ36: =IF(AZ35>0,$E35/$F35,0) -> 285.47867 | BA36: =IF(BA35>0,$E35/$F35,0) -> 285.47867 | BB36: =IF(BB35>0,$E35/$F35,0) -> 285.47867 | BC36: =IF(BC35>0,$E35/$F35,0) -> 285.47867 | BD36: =IF(BD35>0,$E35/$F35,0) -> 285.47867 | BE36: =IF(BE35>0,$E35/$F35,0) -> 285.47867 | ... BI36: =IF(BI35>0,$E35/$F35,0) -> 0 | BK36: =IF(BK35>0,$E35/$F35,0) -> 0 | BL36: =IF(BL35>0,$E35/$F35,0) -> 0 | BM36: =IF(BM35>0,$E35/$F35,0) -> 0 | BN36: =IF(BN35>0,$E35/$F35,0) -> 0 | BO36: =IF(BO35>0,$E35/$F35,0) -> 0 | BP36: =IF(BP35>0,$E35/$F35,0) -> 0 | BQ36: =IF(BQ35>0,$E35/$F35,0) -> 0 | BR36: =IF(BR35>0,$E35/$F35,0) -> 0 | ... BV36: =IF(BV35>0,$E35/$F35,0) -> 0 | BX36: =IF(BX35>0,$E35/$F35,0) -> 0 | BY36: =IF(BY35>0,$E35/$F35,0) -> 0 | BZ36: =IF(BZ35>0,$E35/$F35,0) -> 0 | CA36: =IF(CA35>0,$E35/$F35,0) -> 0 | CB36: =IF(CB35>0,$E35/$F35,0) -> 0 | CC36: =IF(CC35>0,$E35/$F35,0) -> 0 | CD36: =IF(CD35>0,$E35/$F35,0) -> 0 | CE36: =IF(CE35>0,$E35/$F35,0) -> 0 | ... CI36: =IF(CI35>0,$E35/$F35,0) -> 0
A37: 16 | B37: Узловая 1 очередь | C37: Проектирование, экспертиза, получение РНС | D37: 2 | E37: 5635 | F37: =COUNTA(K37:V37,X37:AI37,AK37:AV37,AX37:BI37,BK37:BV37,BX37:CI37) -> 24 | W37: =IF(K37="РНВ",$E37,IF(L37="РНВ",$E37,IF(M37="РНВ",$E37,IF(N37="РНВ",$E37,IF(O37="РНВ",$E37,IF(P37="РНВ",$E37,IF(Q37="РНВ",$E37,IF(R37="РНВ",$E37,IF(S37="РНВ",$E37,IF(T37="РНВ",$E37,IF(U37="РНВ",$E37,IF(V37="РНВ",$E37,0)))))))))))) -> 0 | AJ37: =IF(X37="РНВ",$E37,IF(Y37="РНВ",$E37,IF(Z37="РНВ",$E37,IF(AA37="РНВ",$E37,IF(AB37="РНВ",$E37,IF(AC37="РНВ",$E37,IF(AD37="РНВ",$E37,IF(AE37="РНВ",$E37,IF(AF37="РНВ",$E37,IF(AG37="РНВ",$E37,IF(AH37="РНВ",$E37,IF(AI37="РНВ",$E37,0)))))))))))) -> 0 | AK37: 1 | AL37: 1 | AM37: 1 | AN37: 1 | AO37: 1 | AP37: 1 | AQ37: 1 | AR37: 1 | AS37: 1 | AT37: 1 | AU37: 1 | AV37: 1 | AW37: =IF(AK37="РНВ",$E37,IF(AL37="РНВ",$E37,IF(AM37="РНВ",$E37,IF(AN37="РНВ",$E37,IF(AO37="РНВ",$E37,IF(AP37="РНВ",$E37,IF(AQ37="РНВ",$E37,IF(AR37="РНВ",$E37,IF(AS37="РНВ",$E37,IF(AT37="РНВ",$E37,IF(AU37="РНВ",$E37,IF(AV37="РНВ",$E37,0)))))))))))) -> 0 | AX37: 1 | AY37: 1 | AZ37: 1 | BA37: 1 | BB37: 1 | BC37: 1 | BD37: 1 | BE37: 1 | BF37: 1 | BG37: 1 | BH37: 1 | BI37: РНВ | BJ37: =IF(AX37="РНВ",$E37,IF(AY37="РНВ",$E37,IF(AZ37="РНВ",$E37,IF(BA37="РНВ",$E37,IF(BB37="РНВ",$E37,IF(BI37="РНВ",$E37,IF(BD37="РНВ",$E37,IF(BE37="РНВ",$E37,IF(#REF!="РНВ",$E37,IF(#REF!="РНВ",$E37,IF(BH37="РНВ",$E37,IF(#REF!="РНВ",$E37,0)))))))))))) -> 5635 | BW37: =IF(BK37="РНВ",$E37,IF(BL37="РНВ",$E37,IF(BM37="РНВ",$E37,IF(BN37="РНВ",$E37,IF(BO37="РНВ",$E37,IF(BP37="РНВ",$E37,IF(BQ37="РНВ",$E37,IF(BR37="РНВ",$E37,IF(BS37="РНВ",$E37,IF(BT37="РНВ",$E37,IF(BU37="РНВ",$E37,IF(BV37="РНВ",$E37,0)))))))))))) -> 0 | CJ37: =IF(BX37="РНВ",$E37,IF(BY37="РНВ",$E37,IF(BZ37="РНВ",$E37,IF(CA37="РНВ",$E37,IF(CB37="РНВ",$E37,IF(CC37="РНВ",$E37,IF(CD37="РНВ",$E37,IF(CE37="РНВ",$E37,IF(CF37="РНВ",$E37,IF(CG37="РНВ",$E37,IF(CH37="РНВ",$E37,IF(CI37="РНВ",$E37,0)))))))))))) -> 0
V38: =447755*E37/SUM($E$37:$E$44) -> 59287.53 | AK38: =IF(AK37>0,$E37/$F37,0) -> 234.79167 | AL38: =IF(AL37>0,$E37/$F37,0) -> 234.79167 | AM38: =IF(AM37>0,$E37/$F37,0) -> 234.79167 | AN38: =IF(AN37>0,$E37/$F37,0) -> 234.79167 | AO38: =IF(AO37>0,$E37/$F37,0) -> 234.79167 | AP38: =IF(AP37>0,$E37/$F37,0) -> 234.79167 | AQ38: =IF(AQ37>0,$E37/$F37,0) -> 234.79167 | AR38: =IF(AR37>0,$E37/$F37,0) -> 234.79167 | ... AV38: =IF(AV37>0,$E37/$F37,0) -> 234.79167 | AX38: =IF(AX37>0,$E37/$F37,0) -> 234.79167 | AY38: =IF(AY37>0,$E37/$F37,0) -> 234.79167 | AZ38: =IF(AZ37>0,$E37/$F37,0) -> 234.79167 | BA38: =IF(BA37>0,$E37/$F37,0) -> 234.79167 | BB38: =IF(BB37>0,$E37/$F37,0) -> 234.79167 | BC38: =IF(BI37>0,$E37/$F37,0) -> 234.79167 | BD38: =IF(BD37>0,$E37/$F37,0) -> 234.79167 | BE38: =IF(BE37>0,$E37/$F37,0) -> 234.79167 | BF38: =IF(BF37>0,$E37/$F37,0) -> 234.79167 | BG38: =IF(BG37>0,$E37/$F37,0) -> 234.79167 | BH38: =IF(BH37>0,$E37/$F37,0) -> 234.79167 | BI38: =IF(BI37>0,$E37/$F37,0) -> 234.79167 | BK38: =IF(BK37>0,$E37/$F37,0) -> 0 | BL38: =IF(BL37>0,$E37/$F37,0) -> 0 | BM38: =IF(BM37>0,$E37/$F37,0) -> 0 | BN38: =IF(BN37>0,$E37/$F37,0) -> 0 | BO38: =IF(BO37>0,$E37/$F37,0) -> 0 | BP38: =IF(BP37>0,$E37/$F37,0) -> 0 | BQ38: =IF(BQ37>0,$E37/$F37,0) -> 0 | BR38: =IF(BR37>0,$E37/$F37,0) -> 0 | ... BV38: =IF(BV37>0,$E37/$F37,0) -> 0 | BX38: =IF(BX37>0,$E37/$F37,0) -> 0 | BY38: =IF(BY37>0,$E37/$F37,0) -> 0 | BZ38: =IF(BZ37>0,$E37/$F37,0) -> 0 | CA38: =IF(CA37>0,$E37/$F37,0) -> 0 | CB38: =IF(CB37>0,$E37/$F37,0) -> 0 | CC38: =IF(CC37>0,$E37/$F37,0) -> 0 | CD38: =IF(CD37>0,$E37/$F37,0) -> 0 | CE38: =IF(CE37>0,$E37/$F37,0) -> 0 | ... CI38: =IF(CI37>0,$E37/$F37,0) -> 0
A39: 17 | B39: Узловая 2 очередь | C39: Есть право на зу, ждет реализации | D39: 4 | E39: 11270 | F39: =COUNTA(K39:V39,X39:AI39,AK39:AV39,AX39:BI39,BK39:BV39,BX39:CI39) -> 21 | W39: =IF(K39="РНВ",$E39,IF(L39="РНВ",$E39,IF(M39="РНВ",$E39,IF(N39="РНВ",$E39,IF(O39="РНВ",$E39,IF(P39="РНВ",$E39,IF(Q39="РНВ",$E39,IF(R39="РНВ",$E39,IF(S39="РНВ",$E39,IF(T39="РНВ",$E39,IF(U39="РНВ",$E39,IF(V39="РНВ",$E39,0)))))))))))) -> 0 | AJ39: =IF(X39="РНВ",$E39,IF(Y39="РНВ",$E39,IF(Z39="РНВ",$E39,IF(AA39="РНВ",$E39,IF(AB39="РНВ",$E39,IF(AC39="РНВ",$E39,IF(AD39="РНВ",$E39,IF(AE39="РНВ",$E39,IF(AF39="РНВ",$E39,IF(AG39="РНВ",$E39,IF(AH39="РНВ",$E39,IF(AI39="РНВ",$E39,0)))))))))))) -> 0 | AS39: 1 | AT39: 1 | AU39: 1 | AV39: 1 | AW39: =IF(AK39="РНВ",$E39,IF(AL39="РНВ",$E39,IF(AM39="РНВ",$E39,IF(AN39="РНВ",$E39,IF(AO39="РНВ",$E39,IF(AP39="РНВ",$E39,IF(AQ39="РНВ",$E39,IF(AR39="РНВ",$E39,IF(AS39="РНВ",$E39,IF(AT39="РНВ",$E39,IF(AU39="РНВ",$E39,IF(AV39="РНВ",$E39,0)))))))))))) -> 0 | AX39: 1 | AY39: 1 | AZ39: 1 | BA39: 1 | BB39: 1 | BC39: 1 | BD39: 1 | BE39: 1 | BF39: 1 | BG39: 1 | BH39: 1 | BI39: 1 | BJ39: =IF(AX39="РНВ",$E39,IF(AY39="РНВ",$E39,IF(AZ39="РНВ",$E39,IF(BA39="РНВ",$E39,IF(BB39="РНВ",$E39,IF(BC39="РНВ",$E39,IF(BD39="РНВ",$E39,IF(BE39="РНВ",$E39,IF(BF39="РНВ",$E39,IF(BG39="РНВ",$E39,IF(BH39="РНВ",$E39,IF(BI39="РНВ",$E39,0)))))))))))) -> 0 | BK39: 1 | BL39: 1 | BM39: 1 | BN39: 1 | BO39: РНВ | BW39: =IF(BK39="РНВ",$E39,IF(BL39="РНВ",$E39,IF(BM39="РНВ",$E39,IF(BN39="РНВ",$E39,IF(BO39="РНВ",$E39,IF(BP39="РНВ",$E39,IF(BQ39="РНВ",$E39,IF(BR39="РНВ",$E39,IF(BS39="РНВ",$E39,IF(BT39="РНВ",$E39,IF(BU39="РНВ",$E39,IF(BV39="РНВ",$E39,0)))))))))))) -> 11270 | CJ39: =IF(BX39="РНВ",$E39,IF(BY39="РНВ",$E39,IF(BZ39="РНВ",$E39,IF(CA39="РНВ",$E39,IF(CB39="РНВ",$E39,IF(CC39="РНВ",$E39,IF(CD39="РНВ",$E39,IF(CE39="РНВ",$E39,IF(CF39="РНВ",$E39,IF(CG39="РНВ",$E39,IF(CH39="РНВ",$E39,IF(CI39="РНВ",$E39,0)))))))))))) -> 0
V40: =447755*E39/SUM($E$37:$E$44) -> 118575.06 | AK40: =IF(AK39>0,$E39/$F39,0) -> 0 | AL40: =IF(AL39>0,$E39/$F39,0) -> 0 | AM40: =IF(AM39>0,$E39/$F39,0) -> 0 | AN40: =IF(AN39>0,$E39/$F39,0) -> 0 | AO40: =IF(AO39>0,$E39/$F39,0) -> 0 | AP40: =IF(AP39>0,$E39/$F39,0) -> 0 | AQ40: =IF(AQ39>0,$E39/$F39,0) -> 0 | AR40: =IF(AR39>0,$E39/$F39,0) -> 0 | ... AV40: =IF(AV39>0,$E39/$F39,0) -> 536.66667 | AX40: =IF(AX39>0,$E39/$F39,0) -> 536.66667 | AY40: =IF(AY39>0,$E39/$F39,0) -> 536.66667 | AZ40: =IF(AZ39>0,$E39/$F39,0) -> 536.66667 | BA40: =IF(BA39>0,$E39/$F39,0) -> 536.66667 | BB40: =IF(BB39>0,$E39/$F39,0) -> 536.66667 | BC40: =IF(BC39>0,$E39/$F39,0) -> 536.66667 | BD40: =IF(BD39>0,$E39/$F39,0) -> 536.66667 | BE40: =IF(BE39>0,$E39/$F39,0) -> 536.66667 | ... BI40: =IF(BI39>0,$E39/$F39,0) -> 536.66667 | BK40: =IF(BK39>0,$E39/$F39,0) -> 536.66667 | BL40: =IF(BL39>0,$E39/$F39,0) -> 536.66667 | BM40: =IF(BM39>0,$E39/$F39,0) -> 536.66667 | BN40: =IF(BN39>0,$E39/$F39,0) -> 536.66667 | BO40: =IF(BO39>0,$E39/$F39,0) -> 536.66667 | BP40: =IF(BP39>0,$E39/$F39,0) -> 0 | BQ40: =IF(BQ39>0,$E39/$F39,0) -> 0 | BR40: =IF(BR39>0,$E39/$F39,0) -> 0 | ... BV40: =IF(BV39>0,$E39/$F39,0) -> 0 | BX40: =IF(BX39>0,$E39/$F39,0) -> 0 | BY40: =IF(BY39>0,$E39/$F39,0) -> 0 | BZ40: =IF(BZ39>0,$E39/$F39,0) -> 0 | CA40: =IF(CA39>0,$E39/$F39,0) -> 0 | CB40: =IF(CB39>0,$E39/$F39,0) -> 0 | CC40: =IF(CC39>0,$E39/$F39,0) -> 0 | CD40: =IF(CD39>0,$E39/$F39,0) -> 0 | CE40: =IF(CE39>0,$E39/$F39,0) -> 0 | ... CI40: =IF(CI39>0,$E39/$F39,0) -> 0
A41: 18 | B41: Узловая 3 очередь | C41: Есть право на зу, ждет реализации | D41: 5 | E41: 14382 | F41: =COUNTA(K41:V41,X41:AI41,AK41:AV41,AX41:BI41,BK41:BV41,BX41:CI41) -> 24 | W41: =IF(K41="РНВ",$E41,IF(L41="РНВ",$E41,IF(M41="РНВ",$E41,IF(N41="РНВ",$E41,IF(O41="РНВ",$E41,IF(P41="РНВ",$E41,IF(Q41="РНВ",$E41,IF(R41="РНВ",$E41,IF(S41="РНВ",$E41,IF(T41="РНВ",$E41,IF(U41="РНВ",$E41,IF(V41="РНВ",$E41,0)))))))))))) -> 0 | AJ41: =IF(X41="РНВ",$E41,IF(Y41="РНВ",$E41,IF(Z41="РНВ",$E41,IF(AA41="РНВ",$E41,IF(AB41="РНВ",$E41,IF(AC41="РНВ",$E41,IF(AD41="РНВ",$E41,IF(AE41="РНВ",$E41,IF(AF41="РНВ",$E41,IF(AG41="РНВ",$E41,IF(AH41="РНВ",$E41,IF(AI41="РНВ",$E41,0)))))))))))) -> 0 | AW41: =IF(AK41="РНВ",$E41,IF(AL41="РНВ",$E41,IF(AM41="РНВ",$E41,IF(AN41="РНВ",$E41,IF(AO41="РНВ",$E41,IF(AP41="РНВ",$E41,IF(AQ41="РНВ",$E41,IF(AR41="РНВ",$E41,IF(AS41="РНВ",$E41,IF(AT41="РНВ",$E41,IF(AU41="РНВ",$E41,IF(AV41="РНВ",$E41,0)))))))))))) -> 0 | BA41: 1 | BB41: 1 | BC41: 1 | BD41: 1 | BE41: 1 | BF41: 1 | BG41: 1 | BH41: 1 | BI41: 1 | BJ41: =IF(AX41="РНВ",$E41,IF(AY41="РНВ",$E41,IF(AZ41="РНВ",$E41,IF(BA41="РНВ",$E41,IF(BB41="РНВ",$E41,IF(BC41="РНВ",$E41,IF(BD41="РНВ",$E41,IF(BE41="РНВ",$E41,IF(BF41="РНВ",$E41,IF(BG41="РНВ",$E41,IF(BH41="РНВ",$E41,IF(BI41="РНВ",$E41,0)))))))))))) -> 0 | BK41: 1 | BL41: 1 | BM41: 1 | BN41: 1 | BO41: 1 | BP41: 1 | BQ41: 1 | BR41: 1 | BS41: 1 | BT41: 1 | BU41: 1 | BV41: 1 | BW41: =IF(BK41="РНВ",$E41,IF(BL41="РНВ",$E41,IF(BM41="РНВ",$E41,IF(BN41="РНВ",$E41,IF(BO41="РНВ",$E41,IF(BP41="РНВ",$E41,IF(BQ41="РНВ",$E41,IF(BR41="РНВ",$E41,IF(BS41="РНВ",$E41,IF(BT41="РНВ",$E41,IF(BU41="РНВ",$E41,IF(BV41="РНВ",$E41,0)))))))))))) -> 0 | BX41: 1 | BY41: 1 | BZ41: РНВ | CJ41: =IF(BX41="РНВ",$E41,IF(BY41="РНВ",$E41,IF(BZ41="РНВ",$E41,IF(CA41="РНВ",$E41,IF(CB41="РНВ",$E41,IF(CC41="РНВ",$E41,IF(CD41="РНВ",$E41,IF(CE41="РНВ",$E41,IF(CF41="РНВ",$E41,IF(CG41="РНВ",$E41,IF(CH41="РНВ",$E41,IF(CI41="РНВ",$E41,0)))))))))))) -> 14382
V42: =447755*E41/SUM($E$37:$E$44) -> 151317.35 | AK42: =IF(AK41>0,$E41/$F41,0) -> 0 | AL42: =IF(AL41>0,$E41/$F41,0) -> 0 | AM42: =IF(AM41>0,$E41/$F41,0) -> 0 | AN42: =IF(AN41>0,$E41/$F41,0) -> 0 | AO42: =IF(AO41>0,$E41/$F41,0) -> 0 | AP42: =IF(AP41>0,$E41/$F41,0) -> 0 | AQ42: =IF(AQ41>0,$E41/$F41,0) -> 0 | AR42: =IF(AR41>0,$E41/$F41,0) -> 0 | ... AV42: =IF(AV41>0,$E41/$F41,0) -> 0 | AX42: =IF(AX41>0,$E41/$F41,0) -> 0 | AY42: =IF(AY41>0,$E41/$F41,0) -> 0 | AZ42: =IF(AZ41>0,$E41/$F41,0) -> 0 | BA42: =IF(BA41>0,$E41/$F41,0) -> 599.25 | BB42: =IF(BB41>0,$E41/$F41,0) -> 599.25 | BC42: =IF(BC41>0,$E41/$F41,0) -> 599.25 | BD42: =IF(BD41>0,$E41/$F41,0) -> 599.25 | BE42: =IF(BE41>0,$E41/$F41,0) -> 599.25 | ... BI42: =IF(BI41>0,$E41/$F41,0) -> 599.25 | BK42: =IF(BK41>0,$E41/$F41,0) -> 599.25 | BL42: =IF(BL41>0,$E41/$F41,0) -> 599.25 | BM42: =IF(BM41>0,$E41/$F41,0) -> 599.25 | BN42: =IF(BN41>0,$E41/$F41,0) -> 599.25 | BO42: =IF(BO41>0,$E41/$F41,0) -> 599.25 | BP42: =IF(BP41>0,$E41/$F41,0) -> 599.25 | BQ42: =IF(BQ41>0,$E41/$F41,0) -> 599.25 | BR42: =IF(BR41>0,$E41/$F41,0) -> 599.25 | ... BV42: =IF(BV41>0,$E41/$F41,0) -> 599.25 | BX42: =IF(BX41>0,$E41/$F41,0) -> 599.25 | BY42: =IF(BY41>0,$E41/$F41,0) -> 599.25 | BZ42: =IF(BZ41>0,$E41/$F41,0) -> 599.25 | CA42: =IF(CA41>0,$E41/$F41,0) -> 0 | CB42: =IF(CB41>0,$E41/$F41,0) -> 0 | CC42: =IF(CC41>0,$E41/$F41,0) -> 0 | CD42: =IF(CD41>0,$E41/$F41,0) -> 0 | CE42: =IF(CE41>0,$E41/$F41,0) -> 0 | ... CI42: =IF(CI41>0,$E41/$F41,0) -> 0
A43: 19 | B43: Узловая 4 очередь | C43: Есть право на зу, ждет реализации | D43: 4 | E43: 11270 | F43: =COUNTA(K43:V43,X43:AI43,AK43:AV43,AX43:BI43,BK43:BV43,BX43:CI43) -> 21 | W43: =IF(K43="РНВ",$E43,IF(L43="РНВ",$E43,IF(M43="РНВ",$E43,IF(N43="РНВ",$E43,IF(O43="РНВ",$E43,IF(P43="РНВ",$E43,IF(Q43="РНВ",$E43,IF(R43="РНВ",$E43,IF(S43="РНВ",$E43,IF(T43="РНВ",$E43,IF(U43="РНВ",$E43,IF(V43="РНВ",$E43,0)))))))))))) -> 0 | AJ43: =IF(X43="РНВ",$E43,IF(Y43="РНВ",$E43,IF(Z43="РНВ",$E43,IF(AA43="РНВ",$E43,IF(AB43="РНВ",$E43,IF(AC43="РНВ",$E43,IF(AD43="РНВ",$E43,IF(AE43="РНВ",$E43,IF(AF43="РНВ",$E43,IF(AG43="РНВ",$E43,IF(AH43="РНВ",$E43,IF(AI43="РНВ",$E43,0)))))))))))) -> 0 | AW43: =IF(AK43="РНВ",$E43,IF(AL43="РНВ",$E43,IF(AM43="РНВ",$E43,IF(AN43="РНВ",$E43,IF(AO43="РНВ",$E43,IF(AP43="РНВ",$E43,IF(AQ43="РНВ",$E43,IF(AR43="РНВ",$E43,IF(AS43="РНВ",$E43,IF(AT43="РНВ",$E43,IF(AU43="РНВ",$E43,IF(AV43="РНВ",$E43,0)))))))))))) -> 0 | BF43: 1 | BG43: 1 | BH43: 1 | BI43: 1 | BJ43: =IF(AX43="РНВ",$E43,IF(AY43="РНВ",$E43,IF(AZ43="РНВ",$E43,IF(BA43="РНВ",$E43,IF(BB43="РНВ",$E43,IF(BC43="РНВ",$E43,IF(BD43="РНВ",$E43,IF(BE43="РНВ",$E43,IF(BF43="РНВ",$E43,IF(BG43="РНВ",$E43,IF(BH43="РНВ",$E43,IF(BI43="РНВ",$E43,0)))))))))))) -> 0 | BK43: 1 | BL43: 1 | BM43: 1 | BN43: 1 | BO43: 1 | BP43: 1 | BQ43: 1 | BR43: 1 | BS43: 1 | BT43: 1 | BU43: 1 | BV43: 1 | BW43: =IF(BK43="РНВ",$E43,IF(BL43="РНВ",$E43,IF(BM43="РНВ",$E43,IF(BN43="РНВ",$E43,IF(BO43="РНВ",$E43,IF(BP43="РНВ",$E43,IF(BQ43="РНВ",$E43,IF(BR43="РНВ",$E43,IF(BS43="РНВ",$E43,IF(BT43="РНВ",$E43,IF(BU43="РНВ",$E43,IF(BV43="РНВ",$E43,0)))))))))))) -> 0 | BX43: 1 | BY43: 1 | BZ43: 1 | CA43: 1 | CB43: РНВ | CJ43: =IF(BX43="РНВ",$E43,IF(BY43="РНВ",$E43,IF(BZ43="РНВ",$E43,IF(CA43="РНВ",$E43,IF(CB43="РНВ",$E43,IF(CC43="РНВ",$E43,IF(CD43="РНВ",$E43,IF(CE43="РНВ",$E43,IF(CF43="РНВ",$E43,IF(CG43="РНВ",$E43,IF(CH43="РНВ",$E43,IF(CI43="РНВ",$E43,0)))))))))))) -> 11270
V44: =447755*E43/SUM($E$37:$E$44) -> 118575.06 | AK44: =IF(AK43>0,$E43/$F43,0) -> 0 | AL44: =IF(AL43>0,$E43/$F43,0) -> 0 | AM44: =IF(AM43>0,$E43/$F43,0) -> 0 | AN44: =IF(AN43>0,$E43/$F43,0) -> 0 | AO44: =IF(AO43>0,$E43/$F43,0) -> 0 | AP44: =IF(AP43>0,$E43/$F43,0) -> 0 | AQ44: =IF(AQ43>0,$E43/$F43,0) -> 0 | AR44: =IF(AR43>0,$E43/$F43,0) -> 0 | ... AV44: =IF(AV43>0,$E43/$F43,0) -> 0 | AX44: =IF(AX43>0,$E43/$F43,0) -> 0 | AY44: =IF(AY43>0,$E43/$F43,0) -> 0 | AZ44: =IF(AZ43>0,$E43/$F43,0) -> 0 | BA44: =IF(BA43>0,$E43/$F43,0) -> 0 | BB44: =IF(BB43>0,$E43/$F43,0) -> 0 | BC44: =IF(BC43>0,$E43/$F43,0) -> 0 | BD44: =IF(BD43>0,$E43/$F43,0) -> 0 | BE44: =IF(BE43>0,$E43/$F43,0) -> 0 | ... BI44: =IF(BI43>0,$E43/$F43,0) -> 536.66667 | BK44: =IF(BK43>0,$E43/$F43,0) -> 536.66667 | BL44: =IF(BL43>0,$E43/$F43,0) -> 536.66667 | BM44: =IF(BM43>0,$E43/$F43,0) -> 536.66667 | BN44: =IF(BN43>0,$E43/$F43,0) -> 536.66667 | BO44: =IF(BO43>0,$E43/$F43,0) -> 536.66667 | BP44: =IF(BP43>0,$E43/$F43,0) -> 536.66667 | BQ44: =IF(BQ43>0,$E43/$F43,0) -> 536.66667 | BR44: =IF(BR43>0,$E43/$F43,0) -> 536.66667 | ... BV44: =IF(BV43>0,$E43/$F43,0) -> 536.66667 | BX44: =IF(BX43>0,$E43/$F43,0) -> 536.66667 | BY44: =IF(BY43>0,$E43/$F43,0) -> 536.66667 | BZ44: =IF(BZ43>0,$E43/$F43,0) -> 536.66667 | CA44: =IF(CA43>0,$E43/$F43,0) -> 536.66667 | CB44: =IF(CB43>0,$E43/$F43,0) -> 536.66667 | CC44: =IF(CC43>0,$E43/$F43,0) -> 0 | CD44: =IF(CD43>0,$E43/$F43,0) -> 0 | CE44: =IF(CE43>0,$E43/$F43,0) -> 0 | ... CI44: =IF(CI43>0,$E43/$F43,0) -> 0
A45: 20 | B45: Бобров 1 очередь 1 дом | C45: Строительство | D45: 5 | E45: 16789.14 | F45: =COUNTA(K45:V45,X45:AI45,AK45:AV45,AX45:BI45,BK45:BV45,BX45:CI45) -> 26 | W45: =IF(K45="РНВ",$E45,IF(L45="РНВ",$E45,IF(M45="РНВ",$E45,IF(N45="РНВ",$E45,IF(O45="РНВ",$E45,IF(P45="РНВ",$E45,IF(Q45="РНВ",$E45,IF(R45="РНВ",$E45,IF(S45="РНВ",$E45,IF(T45="РНВ",$E45,IF(U45="РНВ",$E45,IF(V45="РНВ",$E45,0)))))))))))) -> 0 | AG45: 1 | AH45: 1 | AI45: 1 | AJ45: =IF(X45="РНВ",$E45,IF(Y45="РНВ",$E45,IF(Z45="РНВ",$E45,IF(AA45="РНВ",$E45,IF(AB45="РНВ",$E45,IF(AC45="РНВ",$E45,IF(AD45="РНВ",$E45,IF(AE45="РНВ",$E45,IF(AF45="РНВ",$E45,IF(AG45="РНВ",$E45,IF(AH45="РНВ",$E45,IF(AI45="РНВ",$E45,0)))))))))))) -> 0 | AK45: 1 | AL45: 1 | AM45: 1 | AN45: 1 | AO45: 1 | AP45: 1 | AQ45: 1 | AR45: 1 | AS45: 1 | AT45: 1 | AU45: 1 | AV45: 1 | AW45: =IF(AK45="РНВ",$E45,IF(AL45="РНВ",$E45,IF(AM45="РНВ",$E45,IF(AN45="РНВ",$E45,IF(AO45="РНВ",$E45,IF(AP45="РНВ",$E45,IF(AQ45="РНВ",$E45,IF(AR45="РНВ",$E45,IF(AS45="РНВ",$E45,IF(AT45="РНВ",$E45,IF(AU45="РНВ",$E45,IF(AV45="РНВ",$E45,0)))))))))))) -> 0 | AX45: 1 | AY45: 1 | AZ45: 1 | BA45: 1 | BB45: 1 | BC45: 1 | BD45: 1 | BE45: 1 | BF45: 1 | BG45: 1 | BH45: РНВ | BJ45: =IF(AX45="РНВ",$E45,IF(AY45="РНВ",$E45,IF(AZ45="РНВ",$E45,IF(BA45="РНВ",$E45,IF(BB45="РНВ",$E45,IF(BC45="РНВ",$E45,IF(BD45="РНВ",$E45,IF(BE45="РНВ",$E45,IF(BF45="РНВ",$E45,IF(BG45="РНВ",$E45,IF(BH45="РНВ",$E45,IF(BI45="РНВ",$E45,0)))))))))))) -> 16789.14 | BW45: =IF(BK45="РНВ",$E45,IF(BL45="РНВ",$E45,IF(BM45="РНВ",$E45,IF(BN45="РНВ",$E45,IF(BO45="РНВ",$E45,IF(BP45="РНВ",$E45,IF(BQ45="РНВ",$E45,IF(BR45="РНВ",$E45,IF(BS45="РНВ",$E45,IF(BT45="РНВ",$E45,IF(BU45="РНВ",$E45,IF(BV45="РНВ",$E45,0)))))))))))) -> 0 | CJ45: =IF(BX45="РНВ",$E45,IF(BY45="РНВ",$E45,IF(BZ45="РНВ",$E45,IF(CA45="РНВ",$E45,IF(CB45="РНВ",$E45,IF(CC45="РНВ",$E45,IF(CD45="РНВ",$E45,IF(CE45="РНВ",$E45,IF(CF45="РНВ",$E45,IF(CG45="РНВ",$E45,IF(CH45="РНВ",$E45,IF(CI45="РНВ",$E45,0)))))))))))) -> 0
AK46: =IF(AK45>0,$E45/$F45,0) -> 645.73615 | AL46: =IF(AL45>0,$E45/$F45,0) -> 645.73615 | AM46: =IF(AM45>0,$E45/$F45,0) -> 645.73615 | AN46: =IF(AN45>0,$E45/$F45,0) -> 645.73615 | AO46: =IF(AO45>0,$E45/$F45,0) -> 645.73615 | AP46: =IF(AP45>0,$E45/$F45,0) -> 645.73615 | AQ46: =IF(AQ45>0,$E45/$F45,0) -> 645.73615 | AR46: =IF(AR45>0,$E45/$F45,0) -> 645.73615 | ... AV46: =IF(AV45>0,$E45/$F45,0) -> 645.73615 | AX46: =IF(AX45>0,$E45/$F45,0) -> 645.73615 | AY46: =IF(AY45>0,$E45/$F45,0) -> 645.73615 | AZ46: =IF(AZ45>0,$E45/$F45,0) -> 645.73615 | BA46: =IF(BA45>0,$E45/$F45,0) -> 645.73615 | BB46: =IF(BB45>0,$E45/$F45,0) -> 645.73615 | BC46: =IF(BC45>0,$E45/$F45,0) -> 645.73615 | BD46: =IF(BD45>0,$E45/$F45,0) -> 645.73615 | BE46: =IF(BE45>0,$E45/$F45,0) -> 645.73615 | ... BI46: =IF(BI45>0,$E45/$F45,0) -> 0 | BK46: =IF(BK45>0,$E45/$F45,0) -> 0 | BL46: =IF(BL45>0,$E45/$F45,0) -> 0 | BM46: =IF(BM45>0,$E45/$F45,0) -> 0 | BN46: =IF(BN45>0,$E45/$F45,0) -> 0 | BO46: =IF(BO45>0,$E45/$F45,0) -> 0 | BP46: =IF(BP45>0,$E45/$F45,0) -> 0 | BQ46: =IF(BQ45>0,$E45/$F45,0) -> 0 | BR46: =IF(BR45>0,$E45/$F45,0) -> 0 | ... BV46: =IF(BV45>0,$E45/$F45,0) -> 0
A47: 21 | B47: Бобров 1 очередь 2 дом | C47: Есть право на зу, ждет реализации | D47: 3 | E47: 10997 | F47: =COUNTA(K47:V47,X47:AI47,AK47:AV47,AX47:BI47,BK47:BV47,BX47:CI47) -> 24 | W47: =IF(K47="РНВ",$E47,IF(L47="РНВ",$E47,IF(M47="РНВ",$E47,IF(N47="РНВ",$E47,IF(O47="РНВ",$E47,IF(P47="РНВ",$E47,IF(Q47="РНВ",$E47,IF(R47="РНВ",$E47,IF(S47="РНВ",$E47,IF(T47="РНВ",$E47,IF(U47="РНВ",$E47,IF(V47="РНВ",$E47,0)))))))))))) -> 0 | AJ47: =IF(X47="РНВ",$E47,IF(Y47="РНВ",$E47,IF(Z47="РНВ",$E47,IF(AA47="РНВ",$E47,IF(AB47="РНВ",$E47,IF(AC47="РНВ",$E47,IF(AD47="РНВ",$E47,IF(AE47="РНВ",$E47,IF(AF47="РНВ",$E47,IF(AG47="РНВ",$E47,IF(AH47="РНВ",$E47,IF(AI47="РНВ",$E47,0)))))))))))) -> 0 | AV47: 1 | AW47: =IF(AK47="РНВ",$E47,IF(AL47="РНВ",$E47,IF(AM47="РНВ",$E47,IF(AN47="РНВ",$E47,IF(AO47="РНВ",$E47,IF(AP47="РНВ",$E47,IF(AQ47="РНВ",$E47,IF(AR47="РНВ",$E47,IF(AS47="РНВ",$E47,IF(AT47="РНВ",$E47,IF(AU47="РНВ",$E47,IF(AV47="РНВ",$E47,0)))))))))))) -> 0 | AX47: 1 | AY47: 1 | AZ47: 1 | BA47: 1 | BB47: 1 | BC47: 1 | BD47: 1 | BE47: 1 | BF47: 1 | BG47: 1 | BH47: 1 | BI47: 1 | BJ47: =IF(AX47="РНВ",$E47,IF(AY47="РНВ",$E47,IF(AZ47="РНВ",$E47,IF(BA47="РНВ",$E47,IF(BB47="РНВ",$E47,IF(BC47="РНВ",$E47,IF(BD47="РНВ",$E47,IF(BE47="РНВ",$E47,IF(BF47="РНВ",$E47,IF(BG47="РНВ",$E47,IF(BH47="РНВ",$E47,IF(BI47="РНВ",$E47,0)))))))))))) -> 0 | BK47: 1 | BL47: 1 | BM47: 1 | BN47: 1 | BO47: 1 | BP47: 1 | BQ47: 1 | BR47: 1 | BS47: 1 | BT47: 1 | BU47: РНВ | BW47: =IF(BK47="РНВ",$E47,IF(BL47="РНВ",$E47,IF(BM47="РНВ",$E47,IF(BN47="РНВ",$E47,IF(BO47="РНВ",$E47,IF(BP47="РНВ",$E47,IF(BQ47="РНВ",$E47,IF(BR47="РНВ",$E47,IF(BS47="РНВ",$E47,IF(BT47="РНВ",$E47,IF(BU47="РНВ",$E47,IF(BV47="РНВ",$E47,0)))))))))))) -> 10997 | CJ47: =IF(BX47="РНВ",$E47,IF(BY47="РНВ",$E47,IF(BZ47="РНВ",$E47,IF(CA47="РНВ",$E47,IF(CB47="РНВ",$E47,IF(CC47="РНВ",$E47,IF(CD47="РНВ",$E47,IF(CE47="РНВ",$E47,IF(CF47="РНВ",$E47,IF(CG47="РНВ",$E47,IF(CH47="РНВ",$E47,IF(CI47="РНВ",$E47,0)))))))))))) -> 0
AK48: =IF(AK47>0,$E47/$F47,0) -> 0 | AL48: =IF(AL47>0,$E47/$F47,0) -> 0 | AM48: =IF(AM47>0,$E47/$F47,0) -> 0 | AN48: =IF(AN47>0,$E47/$F47,0) -> 0 | AO48: =IF(AO47>0,$E47/$F47,0) -> 0 | AP48: =IF(AP47>0,$E47/$F47,0) -> 0 | AQ48: =IF(AQ47>0,$E47/$F47,0) -> 0 | AR48: =IF(AR47>0,$E47/$F47,0) -> 0 | ... AV48: =IF(AV47>0,$E47/$F47,0) -> 458.20833 | AX48: =IF(AX47>0,$E47/$F47,0) -> 458.20833 | AY48: =IF(AY47>0,$E47/$F47,0) -> 458.20833 | AZ48: =IF(AZ47>0,$E47/$F47,0) -> 458.20833 | BA48: =IF(BA47>0,$E47/$F47,0) -> 458.20833 | BB48: =IF(BB47>0,$E47/$F47,0) -> 458.20833 | BC48: =IF(BC47>0,$E47/$F47,0) -> 458.20833 | BD48: =IF(BD47>0,$E47/$F47,0) -> 458.20833 | BE48: =IF(BE47>0,$E47/$F47,0) -> 458.20833 | ... BI48: =IF(BI47>0,$E47/$F47,0) -> 458.20833 | BK48: =IF(BK47>0,$E47/$F47,0) -> 458.20833 | BL48: =IF(BL47>0,$E47/$F47,0) -> 458.20833 | BM48: =IF(BM47>0,$E47/$F47,0) -> 458.20833 | BN48: =IF(BN47>0,$E47/$F47,0) -> 458.20833 | BO48: =IF(BO47>0,$E47/$F47,0) -> 458.20833 | BP48: =IF(BP47>0,$E47/$F47,0) -> 458.20833 | BQ48: =IF(BQ47>0,$E47/$F47,0) -> 458.20833 | BR48: =IF(BR47>0,$E47/$F47,0) -> 458.20833 | ... BV48: =IF(BV47>0,$E47/$F47,0) -> 0 | BX48: =IF(BX47>0,$E47/$F47,0) -> 0 | BY48: =IF(BY47>0,$E47/$F47,0) -> 0 | BZ48: =IF(BZ47>0,$E47/$F47,0) -> 0 | CA48: =IF(CA47>0,$E47/$F47,0) -> 0 | CB48: =IF(CB47>0,$E47/$F47,0) -> 0 | CC48: =IF(CC47>0,$E47/$F47,0) -> 0 | CD48: =IF(CD47>0,$E47/$F47,0) -> 0 | CE48: =IF(CE47>0,$E47/$F47,0) -> 0 | ... CI48: =IF(CI47>0,$E47/$F47,0) -> 0
A49: 22 | B49: Бобров 2 очередь 1 дом | C49: Есть право на зу, ждет реализации | D49: 5 | E49: 16789.14 | F49: =COUNTA(K49:V49,X49:AI49,AK49:AV49,AX49:BI49,BK49:BV49,BX49:CI49) -> 24 | W49: =IF(K49="РНВ",$E49,IF(L49="РНВ",$E49,IF(M49="РНВ",$E49,IF(N49="РНВ",$E49,IF(O49="РНВ",$E49,IF(P49="РНВ",$E49,IF(Q49="РНВ",$E49,IF(R49="РНВ",$E49,IF(S49="РНВ",$E49,IF(T49="РНВ",$E49,IF(U49="РНВ",$E49,IF(V49="РНВ",$E49,0)))))))))))) -> 0 | AJ49: =IF(X49="РНВ",$E49,IF(Y49="РНВ",$E49,IF(Z49="РНВ",$E49,IF(AA49="РНВ",$E49,IF(AB49="РНВ",$E49,IF(AC49="РНВ",$E49,IF(AD49="РНВ",$E49,IF(AE49="РНВ",$E49,IF(AF49="РНВ",$E49,IF(AG49="РНВ",$E49,IF(AH49="РНВ",$E49,IF(AI49="РНВ",$E49,0)))))))))))) -> 0 | AW49: =IF(AK49="РНВ",$E49,IF(AL49="РНВ",$E49,IF(AM49="РНВ",$E49,IF(AN49="РНВ",$E49,IF(AO49="РНВ",$E49,IF(AP49="РНВ",$E49,IF(AQ49="РНВ",$E49,IF(AR49="РНВ",$E49,IF(AS49="РНВ",$E49,IF(AT49="РНВ",$E49,IF(AU49="РНВ",$E49,IF(AV49="РНВ",$E49,0)))))))))))) -> 0 | BJ49: =IF(AX49="РНВ",$E49,IF(AY49="РНВ",$E49,IF(AZ49="РНВ",$E49,IF(BA49="РНВ",$E49,IF(BB49="РНВ",$E49,IF(BC49="РНВ",$E49,IF(BD49="РНВ",$E49,IF(BE49="РНВ",$E49,IF(BF49="РНВ",$E49,IF(BG49="РНВ",$E49,IF(BH49="РНВ",$E49,IF(BI49="РНВ",$E49,0)))))))))))) -> 0 | BK49: 1 | BL49: 1 | BM49: 1 | BN49: 1 | BO49: 1 | BP49: 1 | BQ49: 1 | BR49: 1 | BS49: 1 | BT49: 1 | BU49: 1 | BV49: 1 | BW49: =IF(BK49="РНВ",$E49,IF(BL49="РНВ",$E49,IF(BM49="РНВ",$E49,IF(BN49="РНВ",$E49,IF(BO49="РНВ",$E49,IF(BP49="РНВ",$E49,IF(BQ49="РНВ",$E49,IF(BR49="РНВ",$E49,IF(BS49="РНВ",$E49,IF(BT49="РНВ",$E49,IF(BU49="РНВ",$E49,IF(BV49="РНВ",$E49,0)))))))))))) -> 0 | BX49: 1 | BY49: 1 | BZ49: 1 | CA49: 1 | CB49: 1 | CC49: 1 | CD49: 1 | CE49: 1 | CF49: 1 | CG49: 1 | CH49: 1 | CI49: 1 | CJ49: =IF(BX49="РНВ",$E49,IF(BY49="РНВ",$E49,IF(BZ49="РНВ",$E49,IF(CA49="РНВ",$E49,IF(CB49="РНВ",$E49,IF(CC49="РНВ",$E49,IF(CD49="РНВ",$E49,IF(CE49="РНВ",$E49,IF(CF49="РНВ",$E49,IF(CG49="РНВ",$E49,IF(CH49="РНВ",$E49,IF(CI49="РНВ",$E49,0)))))))))))) -> 0
AK50: =IF(AK49>0,$E49/$F49,0) -> 0 | AL50: =IF(AL49>0,$E49/$F49,0) -> 0 | AM50: =IF(AM49>0,$E49/$F49,0) -> 0 | AN50: =IF(AN49>0,$E49/$F49,0) -> 0 | AO50: =IF(AO49>0,$E49/$F49,0) -> 0 | AP50: =IF(AP49>0,$E49/$F49,0) -> 0 | AQ50: =IF(AQ49>0,$E49/$F49,0) -> 0 | AR50: =IF(AR49>0,$E49/$F49,0) -> 0 | ... AV50: =IF(AV49>0,$E49/$F49,0) -> 0 | AX50: =IF(AX49>0,$E49/$F49,0) -> 0 | AY50: =IF(AY49>0,$E49/$F49,0) -> 0 | AZ50: =IF(AZ49>0,$E49/$F49,0) -> 0 | BA50: =IF(BA49>0,$E49/$F49,0) -> 0 | BB50: =IF(BB49>0,$E49/$F49,0) -> 0 | BC50: =IF(BC49>0,$E49/$F49,0) -> 0 | BD50: =IF(BD49>0,$E49/$F49,0) -> 0 | BE50: =IF(BE49>0,$E49/$F49,0) -> 0 | ... BI50: =IF(BI49>0,$E49/$F49,0) -> 0 | BK50: =IF(BK49>0,$E49/$F49,0) -> 699.5475 | BL50: =IF(BL49>0,$E49/$F49,0) -> 699.5475 | BM50: =IF(BM49>0,$E49/$F49,0) -> 699.5475 | BN50: =IF(BN49>0,$E49/$F49,0) -> 699.5475 | BO50: =IF(BO49>0,$E49/$F49,0) -> 699.5475 | BP50: =IF(BP49>0,$E49/$F49,0) -> 699.5475 | BQ50: =IF(BQ49>0,$E49/$F49,0) -> 699.5475 | BR50: =IF(BR49>0,$E49/$F49,0) -> 699.5475 | ... BV50: =IF(BV49>0,$E49/$F49,0) -> 699.5475 | BX50: =IF(BX49>0,$E49/$F49,0) -> 699.5475 | BY50: =IF(BY49>0,$E49/$F49,0) -> 699.5475 | BZ50: =IF(BZ49>0,$E49/$F49,0) -> 699.5475 | CA50: =IF(CA49>0,$E49/$F49,0) -> 699.5475 | CB50: =IF(CB49>0,$E49/$F49,0) -> 699.5475 | CC50: =IF(CC49>0,$E49/$F49,0) -> 699.5475 | CD50: =IF(CD49>0,$E49/$F49,0) -> 699.5475 | CE50: =IF(CE49>0,$E49/$F49,0) -> 699.5475 | ... CI50: =IF(CI49>0,$E49/$F49,0) -> 699.5475
A51: 23 | B51: Бобров 2 очередь 2 дом | C51: Есть право на зу, ждет реализации | D51: 3 | E51: 10997 | F51: 21 | W51: =IF(K51="РНВ",$E51,IF(L51="РНВ",$E51,IF(M51="РНВ",$E51,IF(N51="РНВ",$E51,IF(O51="РНВ",$E51,IF(P51="РНВ",$E51,IF(Q51="РНВ",$E51,IF(R51="РНВ",$E51,IF(S51="РНВ",$E51,IF(T51="РНВ",$E51,IF(U51="РНВ",$E51,IF(V51="РНВ",$E51,0)))))))))))) -> 0 | AJ51: =IF(X51="РНВ",$E51,IF(Y51="РНВ",$E51,IF(Z51="РНВ",$E51,IF(AA51="РНВ",$E51,IF(AB51="РНВ",$E51,IF(AC51="РНВ",$E51,IF(AD51="РНВ",$E51,IF(AE51="РНВ",$E51,IF(AF51="РНВ",$E51,IF(AG51="РНВ",$E51,IF(AH51="РНВ",$E51,IF(AI51="РНВ",$E51,0)))))))))))) -> 0 | AW51: =IF(AK51="РНВ",$E51,IF(AL51="РНВ",$E51,IF(AM51="РНВ",$E51,IF(AN51="РНВ",$E51,IF(AO51="РНВ",$E51,IF(AP51="РНВ",$E51,IF(AQ51="РНВ",$E51,IF(AR51="РНВ",$E51,IF(AS51="РНВ",$E51,IF(AT51="РНВ",$E51,IF(AU51="РНВ",$E51,IF(AV51="РНВ",$E51,0)))))))))))) -> 0 | BJ51: =IF(AX51="РНВ",$E51,IF(AY51="РНВ",$E51,IF(AZ51="РНВ",$E51,IF(BA51="РНВ",$E51,IF(BB51="РНВ",$E51,IF(BC51="РНВ",$E51,IF(BD51="РНВ",$E51,IF(BE51="РНВ",$E51,IF(BF51="РНВ",$E51,IF(BG51="РНВ",$E51,IF(BH51="РНВ",$E51,IF(BI51="РНВ",$E51,0)))))))))))) -> 0 | BW51: =IF(BK51="РНВ",$E51,IF(BL51="РНВ",$E51,IF(BM51="РНВ",$E51,IF(BN51="РНВ",$E51,IF(BO51="РНВ",$E51,IF(BP51="РНВ",$E51,IF(BQ51="РНВ",$E51,IF(BR51="РНВ",$E51,IF(BS51="РНВ",$E51,IF(BT51="РНВ",$E51,IF(BU51="РНВ",$E51,IF(BV51="РНВ",$E51,0)))))))))))) -> 0 | BX51: 1 | BY51: 1 | BZ51: 1 | CA51: 1 | CB51: 1 | CC51: 1 | CD51: 1 | CE51: 1 | CF51: 1 | CG51: 1 | CH51: 1 | CI51: 1 | CJ51: =IF(BX51="РНВ",$E51,IF(BY51="РНВ",$E51,IF(BZ51="РНВ",$E51,IF(CA51="РНВ",$E51,IF(CB51="РНВ",$E51,IF(CC51="РНВ",$E51,IF(CD51="РНВ",$E51,IF(CE51="РНВ",$E51,IF(CF51="РНВ",$E51,IF(CG51="РНВ",$E51,IF(CH51="РНВ",$E51,IF(CI51="РНВ",$E51,0)))))))))))) -> 0
AK52: =IF(AK51>0,$E51/$F51,0) -> 0 | AL52: =IF(AL51>0,$E51/$F51,0) -> 0 | AM52: =IF(AM51>0,$E51/$F51,0) -> 0 | AN52: =IF(AN51>0,$E51/$F51,0) -> 0 | AO52: =IF(AO51>0,$E51/$F51,0) -> 0 | AP52: =IF(AP51>0,$E51/$F51,0) -> 0 | AQ52: =IF(AQ51>0,$E51/$F51,0) -> 0 | AR52: =IF(AR51>0,$E51/$F51,0) -> 0 | ... AV52: =IF(AV51>0,$E51/$F51,0) -> 0 | AX52: =IF(AX51>0,$E51/$F51,0) -> 0 | AY52: =IF(AY51>0,$E51/$F51,0) -> 0 | AZ52: =IF(AZ51>0,$E51/$F51,0) -> 0 | BA52: =IF(BA51>0,$E51/$F51,0) -> 0 | BB52: =IF(BB51>0,$E51/$F51,0) -> 0 | BC52: =IF(BC51>0,$E51/$F51,0) -> 0 | BD52: =IF(BD51>0,$E51/$F51,0) -> 0 | BE52: =IF(BE51>0,$E51/$F51,0) -> 0 | ... BI52: =IF(BI51>0,$E51/$F51,0) -> 0 | BK52: =IF(BK51>0,$E51/$F51,0) -> 0 | BL52: =IF(BL51>0,$E51/$F51,0) -> 0 | BM52: =IF(BM51>0,$E51/$F51,0) -> 0 | BN52: =IF(BN51>0,$E51/$F51,0) -> 0 | BO52: =IF(BO51>0,$E51/$F51,0) -> 0 | BP52: =IF(BP51>0,$E51/$F51,0) -> 0 | BQ52: =IF(BQ51>0,$E51/$F51,0) -> 0 | BR52: =IF(BR51>0,$E51/$F51,0) -> 0 | ... BV52: =IF(BV51>0,$E51/$F51,0) -> 0 | BX52: =IF(BX51>0,$E51/$F51,0) -> 523.66667 | BY52: =IF(BY51>0,$E51/$F51,0) -> 523.66667 | BZ52: =IF(BZ51>0,$E51/$F51,0) -> 523.66667 | CA52: =IF(CA51>0,$E51/$F51,0) -> 523.66667 | CB52: =IF(CB51>0,$E51/$F51,0) -> 523.66667 | CC52: =IF(CC51>0,$E51/$F51,0) -> 523.66667 | CD52: =IF(CD51>0,$E51/$F51,0) -> 523.66667 | CE52: =IF(CE51>0,$E51/$F51,0) -> 523.66667 | ... CI52: =IF(CI51>0,$E51/$F51,0) -> 523.66667
A53: 24 | B53: Бобров 3 очередь | C53: Приобретение прав на участок | D53: 8 | E53: 24698 | F53: =COUNTA(K53:V53,X53:AI53,AK53:AV53,AX53:BI53,BK53:BV53,BX53:CI53) -> 0 | W53: =IF(K53="РНВ",$E53,IF(L53="РНВ",$E53,IF(M53="РНВ",$E53,IF(N53="РНВ",$E53,IF(O53="РНВ",$E53,IF(P53="РНВ",$E53,IF(Q53="РНВ",$E53,IF(R53="РНВ",$E53,IF(S53="РНВ",$E53,IF(T53="РНВ",$E53,IF(U53="РНВ",$E53,IF(V53="РНВ",$E53,0)))))))))))) -> 0 | AJ53: =IF(X53="РНВ",$E53,IF(Y53="РНВ",$E53,IF(Z53="РНВ",$E53,IF(AA53="РНВ",$E53,IF(AB53="РНВ",$E53,IF(AC53="РНВ",$E53,IF(AD53="РНВ",$E53,IF(AE53="РНВ",$E53,IF(AF53="РНВ",$E53,IF(AG53="РНВ",$E53,IF(AH53="РНВ",$E53,IF(AI53="РНВ",$E53,0)))))))))))) -> 0 | AW53: =IF(AK53="РНВ",$E53,IF(AL53="РНВ",$E53,IF(AM53="РНВ",$E53,IF(AN53="РНВ",$E53,IF(AO53="РНВ",$E53,IF(AP53="РНВ",$E53,IF(AQ53="РНВ",$E53,IF(AR53="РНВ",$E53,IF(AS53="РНВ",$E53,IF(AT53="РНВ",$E53,IF(AU53="РНВ",$E53,IF(AV53="РНВ",$E53,0)))))))))))) -> 0 | BJ53: =IF(AX53="РНВ",$E53,IF(AY53="РНВ",$E53,IF(AZ53="РНВ",$E53,IF(BA53="РНВ",$E53,IF(BB53="РНВ",$E53,IF(BC53="РНВ",$E53,IF(BD53="РНВ",$E53,IF(BE53="РНВ",$E53,IF(BF53="РНВ",$E53,IF(BG53="РНВ",$E53,IF(BH53="РНВ",$E53,IF(BI53="РНВ",$E53,0)))))))))))) -> 0 | BW53: =IF(BK53="РНВ",$E53,IF(BL53="РНВ",$E53,IF(BM53="РНВ",$E53,IF(BN53="РНВ",$E53,IF(BO53="РНВ",$E53,IF(BP53="РНВ",$E53,IF(BQ53="РНВ",$E53,IF(BR53="РНВ",$E53,IF(BS53="РНВ",$E53,IF(BT53="РНВ",$E53,IF(BU53="РНВ",$E53,IF(BV53="РНВ",$E53,0)))))))))))) -> 0 | CJ53: =IF(BX53="РНВ",$E53,IF(BY53="РНВ",$E53,IF(BZ53="РНВ",$E53,IF(CA53="РНВ",$E53,IF(CB53="РНВ",$E53,IF(CC53="РНВ",$E53,IF(CD53="РНВ",$E53,IF(CE53="РНВ",$E53,IF(CF53="РНВ",$E53,IF(CG53="РНВ",$E53,IF(CH53="РНВ",$E53,IF(CI53="РНВ",$E53,0)))))))))))) -> 0
AK54: =IF(AK53>0,$E53/$F53,0) -> 0 | AL54: =IF(AL53>0,$E53/$F53,0) -> 0 | AM54: =IF(AM53>0,$E53/$F53,0) -> 0 | AN54: =IF(AN53>0,$E53/$F53,0) -> 0 | AO54: =IF(AO53>0,$E53/$F53,0) -> 0 | AP54: =IF(AP53>0,$E53/$F53,0) -> 0 | AQ54: =IF(AQ53>0,$E53/$F53,0) -> 0 | AR54: =IF(AR53>0,$E53/$F53,0) -> 0 | ... AV54: =IF(AV53>0,$E53/$F53,0) -> 0 | AX54: =IF(AX53>0,$E53/$F53,0) -> 0 | AY54: =IF(AY53>0,$E53/$F53,0) -> 0 | AZ54: =IF(AZ53>0,$E53/$F53,0) -> 0 | BA54: =IF(BA53>0,$E53/$F53,0) -> 0 | BB54: =IF(BB53>0,$E53/$F53,0) -> 0 | BC54: =IF(BC53>0,$E53/$F53,0) -> 0 | BD54: =IF(BD53>0,$E53/$F53,0) -> 0 | BE54: =IF(BE53>0,$E53/$F53,0) -> 0 | ... BI54: =IF(BI53>0,$E53/$F53,0) -> 0 | BK54: =IF(BK53>0,$E53/$F53,0) -> 0 | BL54: =IF(BL53>0,$E53/$F53,0) -> 0 | BM54: =IF(BM53>0,$E53/$F53,0) -> 0 | BN54: =IF(BN53>0,$E53/$F53,0) -> 0 | BO54: =IF(BO53>0,$E53/$F53,0) -> 0 | BP54: =IF(BP53>0,$E53/$F53,0) -> 0 | BQ54: =IF(BQ53>0,$E53/$F53,0) -> 0 | BR54: =IF(BR53>0,$E53/$F53,0) -> 0 | ... BV54: =IF(BV53>0,$E53/$F53,0) -> 0 | BX54: =IF(BX53>0,$E53/$F53,0) -> 0 | BY54: =IF(BY53>0,$E53/$F53,0) -> 0 | BZ54: =IF(BZ53>0,$E53/$F53,0) -> 0 | CA54: =IF(CA53>0,$E53/$F53,0) -> 0 | CB54: =IF(CB53>0,$E53/$F53,0) -> 0 | CC54: =IF(CC53>0,$E53/$F53,0) -> 0 | CD54: =IF(CD53>0,$E53/$F53,0) -> 0 | CE54: =IF(CE53>0,$E53/$F53,0) -> 0 | ... CI54: =IF(CI53>0,$E53/$F53,0) -> 0
A55: 25 | B55: Бобров 4 очередь | C55: Приобретение прав на участок | D55: 8 | E55: 24698 | F55: =COUNTA(K55:V55,X55:AI55,AK55:AV55,AX55:BI55,BK55:BV55,BX55:CI55) -> 0 | W55: =IF(K55="РНВ",$E55,IF(L55="РНВ",$E55,IF(M55="РНВ",$E55,IF(N55="РНВ",$E55,IF(O55="РНВ",$E55,IF(P55="РНВ",$E55,IF(Q55="РНВ",$E55,IF(R55="РНВ",$E55,IF(S55="РНВ",$E55,IF(T55="РНВ",$E55,IF(U55="РНВ",$E55,IF(V55="РНВ",$E55,0)))))))))))) -> 0 | AJ55: =IF(X55="РНВ",$E55,IF(Y55="РНВ",$E55,IF(Z55="РНВ",$E55,IF(AA55="РНВ",$E55,IF(AB55="РНВ",$E55,IF(AC55="РНВ",$E55,IF(AD55="РНВ",$E55,IF(AE55="РНВ",$E55,IF(AF55="РНВ",$E55,IF(AG55="РНВ",$E55,IF(AH55="РНВ",$E55,IF(AI55="РНВ",$E55,0)))))))))))) -> 0 | AW55: =IF(AK55="РНВ",$E55,IF(AL55="РНВ",$E55,IF(AM55="РНВ",$E55,IF(AN55="РНВ",$E55,IF(AO55="РНВ",$E55,IF(AP55="РНВ",$E55,IF(AQ55="РНВ",$E55,IF(AR55="РНВ",$E55,IF(AS55="РНВ",$E55,IF(AT55="РНВ",$E55,IF(AU55="РНВ",$E55,IF(AV55="РНВ",$E55,0)))))))))))) -> 0 | BJ55: =IF(AX55="РНВ",$E55,IF(AY55="РНВ",$E55,IF(AZ55="РНВ",$E55,IF(BA55="РНВ",$E55,IF(BB55="РНВ",$E55,IF(BC55="РНВ",$E55,IF(BD55="РНВ",$E55,IF(BE55="РНВ",$E55,IF(BF55="РНВ",$E55,IF(BG55="РНВ",$E55,IF(BH55="РНВ",$E55,IF(BI55="РНВ",$E55,0)))))))))))) -> 0 | BW55: =IF(BK55="РНВ",$E55,IF(BL55="РНВ",$E55,IF(BM55="РНВ",$E55,IF(BN55="РНВ",$E55,IF(BO55="РНВ",$E55,IF(BP55="РНВ",$E55,IF(BQ55="РНВ",$E55,IF(BR55="РНВ",$E55,IF(BS55="РНВ",$E55,IF(BT55="РНВ",$E55,IF(BU55="РНВ",$E55,IF(BV55="РНВ",$E55,0)))))))))))) -> 0 | CJ55: =IF(BX55="РНВ",$E55,IF(BY55="РНВ",$E55,IF(BZ55="РНВ",$E55,IF(CA55="РНВ",$E55,IF(CB55="РНВ",$E55,IF(CC55="РНВ",$E55,IF(CD55="РНВ",$E55,IF(CE55="РНВ",$E55,IF(CF55="РНВ",$E55,IF(CG55="РНВ",$E55,IF(CH55="РНВ",$E55,IF(CI55="РНВ",$E55,0)))))))))))) -> 0
AK56: =IF(AK55>0,$E55/$F55,0) -> 0 | AL56: =IF(AL55>0,$E55/$F55,0) -> 0 | AM56: =IF(AM55>0,$E55/$F55,0) -> 0 | AN56: =IF(AN55>0,$E55/$F55,0) -> 0 | AO56: =IF(AO55>0,$E55/$F55,0) -> 0 | AP56: =IF(AP55>0,$E55/$F55,0) -> 0 | AQ56: =IF(AQ55>0,$E55/$F55,0) -> 0 | AR56: =IF(AR55>0,$E55/$F55,0) -> 0 | ... AV56: =IF(AV55>0,$E55/$F55,0) -> 0 | AX56: =IF(AX55>0,$E55/$F55,0) -> 0 | AY56: =IF(AY55>0,$E55/$F55,0) -> 0 | AZ56: =IF(AZ55>0,$E55/$F55,0) -> 0 | BA56: =IF(BA55>0,$E55/$F55,0) -> 0 | BB56: =IF(BB55>0,$E55/$F55,0) -> 0 | BC56: =IF(BC55>0,$E55/$F55,0) -> 0 | BD56: =IF(BD55>0,$E55/$F55,0) -> 0 | BE56: =IF(BE55>0,$E55/$F55,0) -> 0 | ... BI56: =IF(BI55>0,$E55/$F55,0) -> 0 | BK56: =IF(BK55>0,$E55/$F55,0) -> 0 | BL56: =IF(BL55>0,$E55/$F55,0) -> 0 | BM56: =IF(BM55>0,$E55/$F55,0) -> 0 | BN56: =IF(BN55>0,$E55/$F55,0) -> 0 | BO56: =IF(BO55>0,$E55/$F55,0) -> 0 | BP56: =IF(BP55>0,$E55/$F55,0) -> 0 | BQ56: =IF(BQ55>0,$E55/$F55,0) -> 0 | BR56: =IF(BR55>0,$E55/$F55,0) -> 0 | ... BV56: =IF(BV55>0,$E55/$F55,0) -> 0 | BX56: =IF(BX55>0,$E55/$F55,0) -> 0 | BY56: =IF(BY55>0,$E55/$F55,0) -> 0 | BZ56: =IF(BZ55>0,$E55/$F55,0) -> 0 | CA56: =IF(CA55>0,$E55/$F55,0) -> 0 | CB56: =IF(CB55>0,$E55/$F55,0) -> 0 | CC56: =IF(CC55>0,$E55/$F55,0) -> 0 | CD56: =IF(CD55>0,$E55/$F55,0) -> 0 | CE56: =IF(CE55>0,$E55/$F55,0) -> 0 | ... CI56: =IF(CI55>0,$E55/$F55,0) -> 0
A57: 26 | B57: Бутурлиновка 1 очередь | C57: Есть право на зу, ждет реализации | D57: 4 | E57: 10824.5 | F57: =COUNTA(K57:V57,X57:AI57,AK57:AV57,AX57:BI57,BK57:BV57,BX57:CI57) -> 21 | W57: =IF(K57="РНВ",$E57,IF(L57="РНВ",$E57,IF(M57="РНВ",$E57,IF(N57="РНВ",$E57,IF(O57="РНВ",$E57,IF(P57="РНВ",$E57,IF(Q57="РНВ",$E57,IF(R57="РНВ",$E57,IF(S57="РНВ",$E57,IF(T57="РНВ",$E57,IF(U57="РНВ",$E57,IF(V57="РНВ",$E57,0)))))))))))) -> 0 | AJ57: =IF(X57="РНВ",$E57,IF(Y57="РНВ",$E57,IF(Z57="РНВ",$E57,IF(AA57="РНВ",$E57,IF(AB57="РНВ",$E57,IF(AC57="РНВ",$E57,IF(AD57="РНВ",$E57,IF(AE57="РНВ",$E57,IF(AF57="РНВ",$E57,IF(AG57="РНВ",$E57,IF(AH57="РНВ",$E57,IF(AI57="РНВ",$E57,0)))))))))))) -> 0 | AN57: 1 | AO57: 1 | AP57: 1 | AQ57: 1 | AR57: 1 | AS57: 1 | AT57: 1 | AU57: 1 | AV57: 1 | AW57: =IF(AK57="РНВ",$E57,IF(AL57="РНВ",$E57,IF(AM57="РНВ",$E57,IF(AN57="РНВ",$E57,IF(AO57="РНВ",$E57,IF(AP57="РНВ",$E57,IF(AQ57="РНВ",$E57,IF(AR57="РНВ",$E57,IF(AS57="РНВ",$E57,IF(AT57="РНВ",$E57,IF(AU57="РНВ",$E57,IF(AV57="РНВ",$E57,0)))))))))))) -> 0 | AX57: 1 | AY57: 1 | AZ57: 1 | BA57: 1 | BB57: 1 | BC57: 1 | BD57: 1 | BE57: 1 | BF57: 1 | BG57: 1 | BH57: 1 | BI57: РНВ | BJ57: =IF(AX57="РНВ",$E57,IF(AY57="РНВ",$E57,IF(AZ57="РНВ",$E57,IF(BA57="РНВ",$E57,IF(BB57="РНВ",$E57,IF(BC57="РНВ",$E57,IF(BD57="РНВ",$E57,IF(BE57="РНВ",$E57,IF(BF57="РНВ",$E57,IF(BG57="РНВ",$E57,IF(BH57="РНВ",$E57,IF(BI57="РНВ",$E57,0)))))))))))) -> 10824.5 | BW57: =IF(BK57="РНВ",$E57,IF(BL57="РНВ",$E57,IF(BM57="РНВ",$E57,IF(BN57="РНВ",$E57,IF(BO57="РНВ",$E57,IF(BP57="РНВ",$E57,IF(BQ57="РНВ",$E57,IF(BR57="РНВ",$E57,IF(BS57="РНВ",$E57,IF(BT57="РНВ",$E57,IF(BU57="РНВ",$E57,IF(BV57="РНВ",$E57,0)))))))))))) -> 0 | CJ57: =IF(BX57="РНВ",$E57,IF(BY57="РНВ",$E57,IF(BZ57="РНВ",$E57,IF(CA57="РНВ",$E57,IF(CB57="РНВ",$E57,IF(CC57="РНВ",$E57,IF(CD57="РНВ",$E57,IF(CE57="РНВ",$E57,IF(CF57="РНВ",$E57,IF(CG57="РНВ",$E57,IF(CH57="РНВ",$E57,IF(CI57="РНВ",$E57,0)))))))))))) -> 0
AK58: =IF(AK57>0,$E57/$F57,0) -> 0 | AL58: =IF(AL57>0,$E57/$F57,0) -> 0 | AM58: =IF(AM57>0,$E57/$F57,0) -> 0 | AN58: =IF(AN57>0,$E57/$F57,0) -> 515.45238 | AO58: =IF(AO57>0,$E57/$F57,0) -> 515.45238 | AP58: =IF(AP57>0,$E57/$F57,0) -> 515.45238 | AQ58: =IF(AQ57>0,$E57/$F57,0) -> 515.45238 | AR58: =IF(AR57>0,$E57/$F57,0) -> 515.45238 | ... AV58: =IF(AV57>0,$E57/$F57,0) -> 515.45238 | AX58: =IF(AX57>0,$E57/$F57,0) -> 515.45238 | AY58: =IF(AY57>0,$E57/$F57,0) -> 515.45238 | AZ58: =IF(AZ57>0,$E57/$F57,0) -> 515.45238 | BA58: =IF(BA57>0,$E57/$F57,0) -> 515.45238 | BB58: =IF(BB57>0,$E57/$F57,0) -> 515.45238 | BC58: =IF(BC57>0,$E57/$F57,0) -> 515.45238 | BD58: =IF(BD57>0,$E57/$F57,0) -> 515.45238 | BE58: =IF(BE57>0,$E57/$F57,0) -> 515.45238 | ... BI58: =IF(BI57>0,$E57/$F57,0) -> 515.45238 | BK58: =IF(BK57>0,$E57/$F57,0) -> 0 | BL58: =IF(BL57>0,$E57/$F57,0) -> 0 | BM58: =IF(BM57>0,$E57/$F57,0) -> 0 | BN58: =IF(BN57>0,$E57/$F57,0) -> 0 | BO58: =IF(BO57>0,$E57/$F57,0) -> 0 | BP58: =IF(BP57>0,$E57/$F57,0) -> 0 | BQ58: =IF(BQ57>0,$E57/$F57,0) -> 0 | BR58: =IF(BR57>0,$E57/$F57,0) -> 0 | ... BV58: =IF(BV57>0,$E57/$F57,0) -> 0 | BX58: =IF(BX57>0,$E57/$F57,0) -> 0 | BY58: =IF(BY57>0,$E57/$F57,0) -> 0 | BZ58: =IF(BZ57>0,$E57/$F57,0) -> 0 | CA58: =IF(CA57>0,$E57/$F57,0) -> 0 | CB58: =IF(CB57>0,$E57/$F57,0) -> 0 | CC58: =IF(CC57>0,$E57/$F57,0) -> 0 | CD58: =IF(CD57>0,$E57/$F57,0) -> 0 | CE58: =IF(CE57>0,$E57/$F57,0) -> 0 | ... CI58: =IF(CI57>0,$E57/$F57,0) -> 0
A59: 27 | B59: Бутурлиновка 2 очередь | C59: Есть право на зу, ждет реализации | D59: 4 | E59: 10824.5 | F59: =COUNTA(K59:V59,X59:AI59,AK59:AV59,AX59:BI59,BK59:BV59,BX59:CI59) -> 21 | W59: =IF(K59="РНВ",$E59,IF(L59="РНВ",$E59,IF(M59="РНВ",$E59,IF(N59="РНВ",$E59,IF(O59="РНВ",$E59,IF(P59="РНВ",$E59,IF(Q59="РНВ",$E59,IF(R59="РНВ",$E59,IF(S59="РНВ",$E59,IF(T59="РНВ",$E59,IF(U59="РНВ",$E59,IF(V59="РНВ",$E59,0)))))))))))) -> 0 | AJ59: =IF(X59="РНВ",$E59,IF(Y59="РНВ",$E59,IF(Z59="РНВ",$E59,IF(AA59="РНВ",$E59,IF(AB59="РНВ",$E59,IF(AC59="РНВ",$E59,IF(AD59="РНВ",$E59,IF(AE59="РНВ",$E59,IF(AF59="РНВ",$E59,IF(AG59="РНВ",$E59,IF(AH59="РНВ",$E59,IF(AI59="РНВ",$E59,0)))))))))))) -> 0 | AW59: =IF(AK59="РНВ",$E59,IF(AL59="РНВ",$E59,IF(AM59="РНВ",$E59,IF(AN59="РНВ",$E59,IF(AO59="РНВ",$E59,IF(AP59="РНВ",$E59,IF(AQ59="РНВ",$E59,IF(AR59="РНВ",$E59,IF(AS59="РНВ",$E59,IF(AT59="РНВ",$E59,IF(AU59="РНВ",$E59,IF(AV59="РНВ",$E59,0)))))))))))) -> 0 | AZ59: 1 | BA59: 1 | BB59: 1 | BC59: 1 | BD59: 1 | BE59: 1 | BF59: 1 | BG59: 1 | BH59: 1 | BI59: 1 | BJ59: =IF(AX59="РНВ",$E59,IF(AY59="РНВ",$E59,IF(AZ59="РНВ",$E59,IF(BA59="РНВ",$E59,IF(BB59="РНВ",$E59,IF(BC59="РНВ",$E59,IF(BD59="РНВ",$E59,IF(BE59="РНВ",$E59,IF(BF59="РНВ",$E59,IF(BG59="РНВ",$E59,IF(BH59="РНВ",$E59,IF(BI59="РНВ",$E59,0)))))))))))) -> 0 | BK59: 1 | BL59: 1 | BM59: 1 | BN59: 1 | BO59: 1 | BP59: 1 | BQ59: 1 | BR59: 1 | BS59: 1 | BT59: 1 | BU59: РНВ | BW59: =IF(BK59="РНВ",$E59,IF(BL59="РНВ",$E59,IF(BM59="РНВ",$E59,IF(BN59="РНВ",$E59,IF(BO59="РНВ",$E59,IF(BP59="РНВ",$E59,IF(BQ59="РНВ",$E59,IF(BR59="РНВ",$E59,IF(BS59="РНВ",$E59,IF(BT59="РНВ",$E59,IF(BU59="РНВ",$E59,IF(BV59="РНВ",$E59,0)))))))))))) -> 10824.5 | CJ59: =IF(BX59="РНВ",$E59,IF(BY59="РНВ",$E59,IF(BZ59="РНВ",$E59,IF(CA59="РНВ",$E59,IF(CB59="РНВ",$E59,IF(CC59="РНВ",$E59,IF(CD59="РНВ",$E59,IF(CE59="РНВ",$E59,IF(CF59="РНВ",$E59,IF(CG59="РНВ",$E59,IF(CH59="РНВ",$E59,IF(CI59="РНВ",$E59,0)))))))))))) -> 0
AK60: =IF(AK59>0,$E59/$F59,0) -> 0 | AL60: =IF(AL59>0,$E59/$F59,0) -> 0 | AM60: =IF(AM59>0,$E59/$F59,0) -> 0 | AN60: =IF(AN59>0,$E59/$F59,0) -> 0 | AO60: =IF(AO59>0,$E59/$F59,0) -> 0 | AP60: =IF(AP59>0,$E59/$F59,0) -> 0 | AQ60: =IF(AQ59>0,$E59/$F59,0) -> 0 | AR60: =IF(AR59>0,$E59/$F59,0) -> 0 | ... AV60: =IF(AV59>0,$E59/$F59,0) -> 0 | AX60: =IF(AX59>0,$E59/$F59,0) -> 0 | AY60: =IF(AY59>0,$E59/$F59,0) -> 0 | AZ60: =IF(AZ59>0,$E59/$F59,0) -> 515.45238 | BA60: =IF(BA59>0,$E59/$F59,0) -> 515.45238 | BB60: =IF(BB59>0,$E59/$F59,0) -> 515.45238 | BC60: =IF(BC59>0,$E59/$F59,0) -> 515.45238 | BD60: =IF(BD59>0,$E59/$F59,0) -> 515.45238 | BE60: =IF(BE59>0,$E59/$F59,0) -> 515.45238 | ... BI60: =IF(BI59>0,$E59/$F59,0) -> 515.45238 | BK60: =IF(BK59>0,$E59/$F59,0) -> 515.45238 | BL60: =IF(BL59>0,$E59/$F59,0) -> 515.45238 | BM60: =IF(BM59>0,$E59/$F59,0) -> 515.45238 | BN60: =IF(BN59>0,$E59/$F59,0) -> 515.45238 | BO60: =IF(BO59>0,$E59/$F59,0) -> 515.45238 | BP60: =IF(BP59>0,$E59/$F59,0) -> 515.45238 | BQ60: =IF(BQ59>0,$E59/$F59,0) -> 515.45238 | BR60: =IF(BR59>0,$E59/$F59,0) -> 515.45238 | ... BV60: =IF(BV59>0,$E59/$F59,0) -> 0 | BX60: =IF(BX59>0,$E59/$F59,0) -> 0 | BY60: =IF(BY59>0,$E59/$F59,0) -> 0 | BZ60: =IF(BZ59>0,$E59/$F59,0) -> 0 | CA60: =IF(CA59>0,$E59/$F59,0) -> 0 | CB60: =IF(CB59>0,$E59/$F59,0) -> 0 | CC60: =IF(CC59>0,$E59/$F59,0) -> 0 | CD60: =IF(CD59>0,$E59/$F59,0) -> 0 | CE60: =IF(CE59>0,$E59/$F59,0) -> 0 | ... CI60: =IF(CI59>0,$E59/$F59,0) -> 0
A61: 28 | B61: Бутрлиновка 3 очередь | C61: Есть право на зу, ждет реализации | D61: 1 | E61: 2700 | F61: =COUNTA(K61:V61,X61:AI61,AK61:AV61,AX61:BI61,BK61:BV61,BX61:CI61) -> 19 | W61: =IF(K61="РНВ",$E61,IF(L61="РНВ",$E61,IF(M61="РНВ",$E61,IF(N61="РНВ",$E61,IF(O61="РНВ",$E61,IF(P61="РНВ",$E61,IF(Q61="РНВ",$E61,IF(R61="РНВ",$E61,IF(S61="РНВ",$E61,IF(T61="РНВ",$E61,IF(U61="РНВ",$E61,IF(V61="РНВ",$E61,0)))))))))))) -> 0 | AJ61: =IF(X61="РНВ",$E61,IF(Y61="РНВ",$E61,IF(Z61="РНВ",$E61,IF(AA61="РНВ",$E61,IF(AB61="РНВ",$E61,IF(AC61="РНВ",$E61,IF(AD61="РНВ",$E61,IF(AE61="РНВ",$E61,IF(AF61="РНВ",$E61,IF(AG61="РНВ",$E61,IF(AH61="РНВ",$E61,IF(AI61="РНВ",$E61,0)))))))))))) -> 0 | AW61: =IF(AK61="РНВ",$E61,IF(AL61="РНВ",$E61,IF(AM61="РНВ",$E61,IF(AN61="РНВ",$E61,IF(AO61="РНВ",$E61,IF(AP61="РНВ",$E61,IF(AQ61="РНВ",$E61,IF(AR61="РНВ",$E61,IF(AS61="РНВ",$E61,IF(AT61="РНВ",$E61,IF(AU61="РНВ",$E61,IF(AV61="РНВ",$E61,0)))))))))))) -> 0 | BF61: 1 | BG61: 1 | BH61: 1 | BI61: 1 | BJ61: =IF(AX61="РНВ",$E61,IF(AY61="РНВ",$E61,IF(AZ61="РНВ",$E61,IF(BA61="РНВ",$E61,IF(BB61="РНВ",$E61,IF(BC61="РНВ",$E61,IF(BD61="РНВ",$E61,IF(BE61="РНВ",$E61,IF(BF61="РНВ",$E61,IF(BG61="РНВ",$E61,IF(BH61="РНВ",$E61,IF(BI61="РНВ",$E61,0)))))))))))) -> 0 | BK61: 1 | BL61: 1 | BM61: 1 | BN61: 1 | BO61: 1 | BP61: 1 | BQ61: 1 | BR61: 1 | BS61: 1 | BT61: 1 | BU61: 1 | BV61: 1 | BW61: =IF(BK61="РНВ",$E61,IF(BL61="РНВ",$E61,IF(BM61="РНВ",$E61,IF(BN61="РНВ",$E61,IF(BO61="РНВ",$E61,IF(BP61="РНВ",$E61,IF(BQ61="РНВ",$E61,IF(BR61="РНВ",$E61,IF(BS61="РНВ",$E61,IF(BT61="РНВ",$E61,IF(BU61="РНВ",$E61,IF(BV61="РНВ",$E61,0)))))))))))) -> 0 | BX61: 1 | BY61: 1 | BZ61: РНВ | CJ61: =IF(BX61="РНВ",$E61,IF(BY61="РНВ",$E61,IF(BZ61="РНВ",$E61,IF(CA61="РНВ",$E61,IF(CB61="РНВ",$E61,IF(CC61="РНВ",$E61,IF(CD61="РНВ",$E61,IF(CE61="РНВ",$E61,IF(CF61="РНВ",$E61,IF(CG61="РНВ",$E61,IF(CH61="РНВ",$E61,IF(CI61="РНВ",$E61,0)))))))))))) -> 2700
AK62: =IF(AK61>0,$E61/$F61,0) -> 0 | AL62: =IF(AL61>0,$E61/$F61,0) -> 0 | AM62: =IF(AM61>0,$E61/$F61,0) -> 0 | AN62: =IF(AN61>0,$E61/$F61,0) -> 0 | AO62: =IF(AO61>0,$E61/$F61,0) -> 0 | AP62: =IF(AP61>0,$E61/$F61,0) -> 0 | AQ62: =IF(AQ61>0,$E61/$F61,0) -> 0 | AR62: =IF(AR61>0,$E61/$F61,0) -> 0 | ... AV62: =IF(AV61>0,$E61/$F61,0) -> 0 | AX62: =IF(AX61>0,$E61/$F61,0) -> 0 | AY62: =IF(AY61>0,$E61/$F61,0) -> 0 | AZ62: =IF(AZ61>0,$E61/$F61,0) -> 0 | BA62: =IF(BA61>0,$E61/$F61,0) -> 0 | BB62: =IF(BB61>0,$E61/$F61,0) -> 0 | BC62: =IF(BC61>0,$E61/$F61,0) -> 0 | BD62: =IF(BD61>0,$E61/$F61,0) -> 0 | BE62: =IF(BE61>0,$E61/$F61,0) -> 0 | ... BI62: =IF(BI61>0,$E61/$F61,0) -> 142.10526 | BK62: =IF(BK61>0,$E61/$F61,0) -> 142.10526 | BL62: =IF(BL61>0,$E61/$F61,0) -> 142.10526 | BM62: =IF(BM61>0,$E61/$F61,0) -> 142.10526 | BN62: =IF(BN61>0,$E61/$F61,0) -> 142.10526 | BO62: =IF(BO61>0,$E61/$F61,0) -> 142.10526 | BP62: =IF(BP61>0,$E61/$F61,0) -> 142.10526 | BQ62: =IF(BQ61>0,$E61/$F61,0) -> 142.10526 | BR62: =IF(BR61>0,$E61/$F61,0) -> 142.10526 | ... BV62: =IF(BV61>0,$E61/$F61,0) -> 142.10526 | BX62: =IF(BX61>0,$E61/$F61,0) -> 142.10526 | BY62: =IF(BY61>0,$E61/$F61,0) -> 142.10526 | BZ62: =IF(BZ61>0,$E61/$F61,0) -> 142.10526 | CA62: =IF(CA61>0,$E61/$F61,0) -> 0 | CB62: =IF(CB61>0,$E61/$F61,0) -> 0 | CC62: =IF(CC61>0,$E61/$F61,0) -> 0 | CD62: =IF(CD61>0,$E61/$F61,0) -> 0 | CE62: =IF(CE61>0,$E61/$F61,0) -> 0 | ... CI62: =IF(CI61>0,$E61/$F61,0) -> 0
A63: 29 | B63: Бутурлиновка 4 очередь | C63: Есть право на зу, ждет реализации | D63: 1 | E63: 2700 | F63: =COUNTA(K63:V63,X63:AI63,AK63:AV63,AX63:BI63,BK63:BV63,BX63:CI63) -> 15 | W63: =IF(K63="РНВ",$E63,IF(L63="РНВ",$E63,IF(M63="РНВ",$E63,IF(N63="РНВ",$E63,IF(O63="РНВ",$E63,IF(P63="РНВ",$E63,IF(Q63="РНВ",$E63,IF(R63="РНВ",$E63,IF(S63="РНВ",$E63,IF(T63="РНВ",$E63,IF(U63="РНВ",$E63,IF(V63="РНВ",$E63,0)))))))))))) -> 0 | AJ63: =IF(X63="РНВ",$E63,IF(Y63="РНВ",$E63,IF(Z63="РНВ",$E63,IF(AA63="РНВ",$E63,IF(AB63="РНВ",$E63,IF(AC63="РНВ",$E63,IF(AD63="РНВ",$E63,IF(AE63="РНВ",$E63,IF(AF63="РНВ",$E63,IF(AG63="РНВ",$E63,IF(AH63="РНВ",$E63,IF(AI63="РНВ",$E63,0)))))))))))) -> 0 | AW63: =IF(AK63="РНВ",$E63,IF(AL63="РНВ",$E63,IF(AM63="РНВ",$E63,IF(AN63="РНВ",$E63,IF(AO63="РНВ",$E63,IF(AP63="РНВ",$E63,IF(AQ63="РНВ",$E63,IF(AR63="РНВ",$E63,IF(AS63="РНВ",$E63,IF(AT63="РНВ",$E63,IF(AU63="РНВ",$E63,IF(AV63="РНВ",$E63,0)))))))))))) -> 0 | BJ63: =IF(AX63="РНВ",$E63,IF(AY63="РНВ",$E63,IF(AZ63="РНВ",$E63,IF(BA63="РНВ",$E63,IF(BB63="РНВ",$E63,IF(BC63="РНВ",$E63,IF(BD63="РНВ",$E63,IF(BE63="РНВ",$E63,IF(BF63="РНВ",$E63,IF(BG63="РНВ",$E63,IF(BH63="РНВ",$E63,IF(BI63="РНВ",$E63,0)))))))))))) -> 0 | BM63: 1 | BN63: 1 | BO63: 1 | BP63: 1 | BQ63: 1 | BR63: 1 | BS63: 1 | BT63: 1 | BU63: 1 | BV63: 1 | BW63: =IF(BK63="РНВ",$E63,IF(BL63="РНВ",$E63,IF(BM63="РНВ",$E63,IF(BN63="РНВ",$E63,IF(BO63="РНВ",$E63,IF(BP63="РНВ",$E63,IF(BQ63="РНВ",$E63,IF(BR63="РНВ",$E63,IF(BS63="РНВ",$E63,IF(BT63="РНВ",$E63,IF(BU63="РНВ",$E63,IF(BV63="РНВ",$E63,0)))))))))))) -> 0 | BX63: 1 | BY63: 1 | BZ63: 1 | CA63: 1 | CB63: РНВ | CJ63: =IF(BX63="РНВ",$E63,IF(BY63="РНВ",$E63,IF(BZ63="РНВ",$E63,IF(CA63="РНВ",$E63,IF(CB63="РНВ",$E63,IF(CC63="РНВ",$E63,IF(CD63="РНВ",$E63,IF(CE63="РНВ",$E63,IF(CF63="РНВ",$E63,IF(CG63="РНВ",$E63,IF(CH63="РНВ",$E63,IF(CI63="РНВ",$E63,0)))))))))))) -> 2700
AK64: =IF(AK63>0,$E63/$F63,0) -> 0 | AL64: =IF(AL63>0,$E63/$F63,0) -> 0 | AM64: =IF(AM63>0,$E63/$F63,0) -> 0 | AN64: =IF(AN63>0,$E63/$F63,0) -> 0 | AO64: =IF(AO63>0,$E63/$F63,0) -> 0 | AP64: =IF(AP63>0,$E63/$F63,0) -> 0 | AQ64: =IF(AQ63>0,$E63/$F63,0) -> 0 | AR64: =IF(AR63>0,$E63/$F63,0) -> 0 | ... AV64: =IF(AV63>0,$E63/$F63,0) -> 0 | AX64: =IF(AX63>0,$E63/$F63,0) -> 0 | AY64: =IF(AY63>0,$E63/$F63,0) -> 0 | AZ64: =IF(AZ63>0,$E63/$F63,0) -> 0 | BA64: =IF(BA63>0,$E63/$F63,0) -> 0 | BB64: =IF(BB63>0,$E63/$F63,0) -> 0 | BC64: =IF(BC63>0,$E63/$F63,0) -> 0 | BD64: =IF(BD63>0,$E63/$F63,0) -> 0 | BE64: =IF(BE63>0,$E63/$F63,0) -> 0 | ... BI64: =IF(BI63>0,$E63/$F63,0) -> 0 | BK64: =IF(BK63>0,$E63/$F63,0) -> 0 | BL64: =IF(BL63>0,$E63/$F63,0) -> 0 | BM64: =IF(BM63>0,$E63/$F63,0) -> 180 | BN64: =IF(BN63>0,$E63/$F63,0) -> 180 | BO64: =IF(BO63>0,$E63/$F63,0) -> 180 | BP64: =IF(BP63>0,$E63/$F63,0) -> 180 | BQ64: =IF(BQ63>0,$E63/$F63,0) -> 180 | BR64: =IF(BR63>0,$E63/$F63,0) -> 180 | ... BV64: =IF(BV63>0,$E63/$F63,0) -> 180 | BX64: =IF(BX63>0,$E63/$F63,0) -> 180 | BY64: =IF(BY63>0,$E63/$F63,0) -> 180 | BZ64: =IF(BZ63>0,$E63/$F63,0) -> 180 | CA64: =IF(CA63>0,$E63/$F63,0) -> 180 | CB64: =IF(CB63>0,$E63/$F63,0) -> 180 | CC64: =IF(CC63>0,$E63/$F63,0) -> 0 | CD64: =IF(CD63>0,$E63/$F63,0) -> 0 | CE64: =IF(CE63>0,$E63/$F63,0) -> 0 | ... CI64: =IF(CI63>0,$E63/$F63,0) -> 0
A65: 30 | B65: Бутурлиновка 5 очередь | C65: Есть право на зу, ждет реализации | D65: 1 | E65: 2700 | F65: =COUNTA(K65:V65,X65:AI65,AK65:AV65,AX65:BI65,BK65:BV65,BX65:CI65) -> 15 | W65: =IF(K65="РНВ",$E65,IF(L65="РНВ",$E65,IF(M65="РНВ",$E65,IF(N65="РНВ",$E65,IF(O65="РНВ",$E65,IF(P65="РНВ",$E65,IF(Q65="РНВ",$E65,IF(R65="РНВ",$E65,IF(S65="РНВ",$E65,IF(T65="РНВ",$E65,IF(U65="РНВ",$E65,IF(V65="РНВ",$E65,0)))))))))))) -> 0 | AJ65: =IF(X65="РНВ",$E65,IF(Y65="РНВ",$E65,IF(Z65="РНВ",$E65,IF(AA65="РНВ",$E65,IF(AB65="РНВ",$E65,IF(AC65="РНВ",$E65,IF(AD65="РНВ",$E65,IF(AE65="РНВ",$E65,IF(AF65="РНВ",$E65,IF(AG65="РНВ",$E65,IF(AH65="РНВ",$E65,IF(AI65="РНВ",$E65,0)))))))))))) -> 0 | AW65: =IF(AK65="РНВ",$E65,IF(AL65="РНВ",$E65,IF(AM65="РНВ",$E65,IF(AN65="РНВ",$E65,IF(AO65="РНВ",$E65,IF(AP65="РНВ",$E65,IF(AQ65="РНВ",$E65,IF(AR65="РНВ",$E65,IF(AS65="РНВ",$E65,IF(AT65="РНВ",$E65,IF(AU65="РНВ",$E65,IF(AV65="РНВ",$E65,0)))))))))))) -> 0 | BJ65: =IF(AX65="РНВ",$E65,IF(AY65="РНВ",$E65,IF(AZ65="РНВ",$E65,IF(BA65="РНВ",$E65,IF(BB65="РНВ",$E65,IF(BC65="РНВ",$E65,IF(BD65="РНВ",$E65,IF(BE65="РНВ",$E65,IF(BF65="РНВ",$E65,IF(BG65="РНВ",$E65,IF(BH65="РНВ",$E65,IF(BI65="РНВ",$E65,0)))))))))))) -> 0 | BT65: 1 | BU65: 1 | BV65: 1 | BW65: =IF(BK65="РНВ",$E65,IF(BL65="РНВ",$E65,IF(BM65="РНВ",$E65,IF(BN65="РНВ",$E65,IF(BO65="РНВ",$E65,IF(BP65="РНВ",$E65,IF(BQ65="РНВ",$E65,IF(BR65="РНВ",$E65,IF(BS65="РНВ",$E65,IF(BT65="РНВ",$E65,IF(BU65="РНВ",$E65,IF(BV65="РНВ",$E65,0)))))))))))) -> 0 | BX65: 1 | BY65: 1 | BZ65: 1 | CA65: 1 | CB65: 1 | CC65: 1 | CD65: 1 | CE65: 1 | CF65: 1 | CG65: 1 | CH65: 1 | CI65: РНВ | CJ65: =IF(BX65="РНВ",$E65,IF(BY65="РНВ",$E65,IF(BZ65="РНВ",$E65,IF(CA65="РНВ",$E65,IF(CB65="РНВ",$E65,IF(CC65="РНВ",$E65,IF(CD65="РНВ",$E65,IF(CE65="РНВ",$E65,IF(CF65="РНВ",$E65,IF(CG65="РНВ",$E65,IF(CH65="РНВ",$E65,IF(CI65="РНВ",$E65,0)))))))))))) -> 2700
AK66: =IF(AK65>0,$E65/$F65,0) -> 0 | AL66: =IF(AL65>0,$E65/$F65,0) -> 0 | AM66: =IF(AM65>0,$E65/$F65,0) -> 0 | AN66: =IF(AN65>0,$E65/$F65,0) -> 0 | AO66: =IF(AO65>0,$E65/$F65,0) -> 0 | AP66: =IF(AP65>0,$E65/$F65,0) -> 0 | AQ66: =IF(AQ65>0,$E65/$F65,0) -> 0 | AR66: =IF(AR65>0,$E65/$F65,0) -> 0 | ... AV66: =IF(AV65>0,$E65/$F65,0) -> 0 | AX66: =IF(AX65>0,$E65/$F65,0) -> 0 | AY66: =IF(AY65>0,$E65/$F65,0) -> 0 | AZ66: =IF(AZ65>0,$E65/$F65,0) -> 0 | BA66: =IF(BA65>0,$E65/$F65,0) -> 0 | BB66: =IF(BB65>0,$E65/$F65,0) -> 0 | BC66: =IF(BC65>0,$E65/$F65,0) -> 0 | BD66: =IF(BD65>0,$E65/$F65,0) -> 0 | BE66: =IF(BE65>0,$E65/$F65,0) -> 0 | ... BI66: =IF(BI65>0,$E65/$F65,0) -> 0 | BK66: =IF(BK65>0,$E65/$F65,0) -> 0 | BL66: =IF(BL65>0,$E65/$F65,0) -> 0 | BM66: =IF(BM65>0,$E65/$F65,0) -> 0 | BN66: =IF(BN65>0,$E65/$F65,0) -> 0 | BO66: =IF(BO65>0,$E65/$F65,0) -> 0 | BP66: =IF(BP65>0,$E65/$F65,0) -> 0 | BQ66: =IF(BQ65>0,$E65/$F65,0) -> 0 | BR66: =IF(BR65>0,$E65/$F65,0) -> 0 | ... BV66: =IF(BV65>0,$E65/$F65,0) -> 180 | BX66: =IF(BX65>0,$E65/$F65,0) -> 180 | BY66: =IF(BY65>0,$E65/$F65,0) -> 180 | BZ66: =IF(BZ65>0,$E65/$F65,0) -> 180 | CA66: =IF(CA65>0,$E65/$F65,0) -> 180 | CB66: =IF(CB65>0,$E65/$F65,0) -> 180 | CC66: =IF(CC65>0,$E65/$F65,0) -> 180 | CD66: =IF(CD65>0,$E65/$F65,0) -> 180 | CE66: =IF(CE65>0,$E65/$F65,0) -> 180 | ... CI66: =IF(CI65>0,$E65/$F65,0) -> 180
A67: 31 | B67: Алексин КРТ1 1 очередь | C67: Проектирование, экспертиза, получение РНС | D67: 6 | E67: 19380 | F67: =COUNTA(K67:V67,X67:AI67,AK67:AV67,AX67:BI67,BK67:BV67,BX67:CI67) -> 27 | W67: =IF(K67="РНВ",$E67,IF(L67="РНВ",$E67,IF(M67="РНВ",$E67,IF(N67="РНВ",$E67,IF(O67="РНВ",$E67,IF(P67="РНВ",$E67,IF(Q67="РНВ",$E67,IF(R67="РНВ",$E67,IF(S67="РНВ",$E67,IF(T67="РНВ",$E67,IF(U67="РНВ",$E67,IF(V67="РНВ",$E67,0)))))))))))) -> 0 | AJ67: =IF(X67="РНВ",$E67,IF(Y67="РНВ",$E67,IF(Z67="РНВ",$E67,IF(AA67="РНВ",$E67,IF(AB67="РНВ",$E67,IF(AC67="РНВ",$E67,IF(AD67="РНВ",$E67,IF(AE67="РНВ",$E67,IF(AF67="РНВ",$E67,IF(AG67="РНВ",$E67,IF(AH67="РНВ",$E67,IF(AI67="РНВ",$E67,0)))))))))))) -> 0 | AM67: 1 | AN67: 1 | AO67: 1 | AP67: 1 | AQ67: 1 | AR67: 1 | AS67: 1 | AT67: 1 | AU67: 1 | AV67: 1 | AW67: =IF(AK67="РНВ",$E67,IF(AL67="РНВ",$E67,IF(AM67="РНВ",$E67,IF(AN67="РНВ",$E67,IF(AO67="РНВ",$E67,IF(AP67="РНВ",$E67,IF(AQ67="РНВ",$E67,IF(AR67="РНВ",$E67,IF(AS67="РНВ",$E67,IF(AT67="РНВ",$E67,IF(AU67="РНВ",$E67,IF(AV67="РНВ",$E67,0)))))))))))) -> 0 | AX67: 1 | AY67: 1 | AZ67: 1 | BA67: 1 | BB67: 1 | BC67: 1 | BD67: 1 | BE67: 1 | BF67: 1 | BG67: 1 | BH67: 1 | BI67: 1 | BJ67: =IF(AX67="РНВ",$E67,IF(AY67="РНВ",$E67,IF(AZ67="РНВ",$E67,IF(BA67="РНВ",$E67,IF(BB67="РНВ",$E67,IF(BC67="РНВ",$E67,IF(BD67="РНВ",$E67,IF(BE67="РНВ",$E67,IF(BF67="РНВ",$E67,IF(BG67="РНВ",$E67,IF(BH67="РНВ",$E67,IF(BI67="РНВ",$E67,0)))))))))))) -> 0 | BK67: 1 | BL67: 1 | BM67: 1 | BN67: 1 | BO67: РНВ | BW67: =IF(BK67="РНВ",$E67,IF(BL67="РНВ",$E67,IF(BM67="РНВ",$E67,IF(BN67="РНВ",$E67,IF(BO67="РНВ",$E67,IF(BP67="РНВ",$E67,IF(BQ67="РНВ",$E67,IF(BR67="РНВ",$E67,IF(BS67="РНВ",$E67,IF(BT67="РНВ",$E67,IF(BU67="РНВ",$E67,IF(BV67="РНВ",$E67,0)))))))))))) -> 19380 | CJ67: =IF(BX67="РНВ",$E67,IF(BY67="РНВ",$E67,IF(BZ67="РНВ",$E67,IF(CA67="РНВ",$E67,IF(CB67="РНВ",$E67,IF(CC67="РНВ",$E67,IF(CD67="РНВ",$E67,IF(CE67="РНВ",$E67,IF(CF67="РНВ",$E67,IF(CG67="РНВ",$E67,IF(CH67="РНВ",$E67,IF(CI67="РНВ",$E67,0)))))))))))) -> 0
AK68: =IF(AK67>0,$E67/$F67,0) -> 0 | AL68: =IF(AL67>0,$E67/$F67,0) -> 0 | AM68: =IF(AM67>0,$E67/$F67,0) -> 717.77778 | AN68: =IF(AN67>0,$E67/$F67,0) -> 717.77778 | AO68: =IF(AO67>0,$E67/$F67,0) -> 717.77778 | AP68: =IF(AP67>0,$E67/$F67,0) -> 717.77778 | AQ68: =IF(AQ67>0,$E67/$F67,0) -> 717.77778 | AR68: =IF(AR67>0,$E67/$F67,0) -> 717.77778 | ... AV68: =IF(AV67>0,$E67/$F67,0) -> 717.77778 | AX68: =IF(AX67>0,$E67/$F67,0) -> 717.77778 | AY68: =IF(AY67>0,$E67/$F67,0) -> 717.77778 | AZ68: =IF(AZ67>0,$E67/$F67,0) -> 717.77778 | BA68: =IF(BA67>0,$E67/$F67,0) -> 717.77778 | BB68: =IF(BB67>0,$E67/$F67,0) -> 717.77778 | BC68: =IF(BC67>0,$E67/$F67,0) -> 717.77778 | BD68: =IF(BD67>0,$E67/$F67,0) -> 717.77778 | BE68: =IF(BE67>0,$E67/$F67,0) -> 717.77778 | ... BI68: =IF(BI67>0,$E67/$F67,0) -> 717.77778 | BK68: =IF(BK67>0,$E67/$F67,0) -> 717.77778 | BL68: =IF(BL67>0,$E67/$F67,0) -> 717.77778 | BM68: =IF(BM67>0,$E67/$F67,0) -> 717.77778 | BN68: =IF(BN67>0,$E67/$F67,0) -> 717.77778 | BO68: =IF(BO67>0,$E67/$F67,0) -> 717.77778 | BP68: =IF(BP67>0,$E67/$F67,0) -> 0 | BQ68: =IF(BQ67>0,$E67/$F67,0) -> 0 | BR68: =IF(BR67>0,$E67/$F67,0) -> 0 | ... BV68: =IF(BV67>0,$E67/$F67,0) -> 0
A69: 32 | B69: Алексин КРТ1 2 очередь | C69: Есть право на зу, ждет реализации | D69: 2 | E69: 6683 | F69: =COUNTA(K69:V69,X69:AI69,AK69:AV69,AX69:BI69,BK69:BV69,BX69:CI69) -> 23 | W69: =IF(K69="РНВ",$E69,IF(L69="РНВ",$E69,IF(M69="РНВ",$E69,IF(N69="РНВ",$E69,IF(O69="РНВ",$E69,IF(P69="РНВ",$E69,IF(Q69="РНВ",$E69,IF(R69="РНВ",$E69,IF(S69="РНВ",$E69,IF(T69="РНВ",$E69,IF(U69="РНВ",$E69,IF(V69="РНВ",$E69,0)))))))))))) -> 0 | AJ69: =IF(X69="РНВ",$E69,IF(Y69="РНВ",$E69,IF(Z69="РНВ",$E69,IF(AA69="РНВ",$E69,IF(AB69="РНВ",$E69,IF(AC69="РНВ",$E69,IF(AD69="РНВ",$E69,IF(AE69="РНВ",$E69,IF(AF69="РНВ",$E69,IF(AG69="РНВ",$E69,IF(AH69="РНВ",$E69,IF(AI69="РНВ",$E69,0)))))))))))) -> 0 | AW69: =IF(AK69="РНВ",$E69,IF(AL69="РНВ",$E69,IF(AM69="РНВ",$E69,IF(AN69="РНВ",$E69,IF(AO69="РНВ",$E69,IF(AP69="РНВ",$E69,IF(AQ69="РНВ",$E69,IF(AR69="РНВ",$E69,IF(AS69="РНВ",$E69,IF(AT69="РНВ",$E69,IF(AU69="РНВ",$E69,IF(AV69="РНВ",$E69,0)))))))))))) -> 0 | BC69: 1 | BD69: 1 | BE69: 1 | BF69: 1 | BG69: 1 | BH69: 1 | BI69: 1 | BJ69: =IF(AX69="РНВ",$E69,IF(AY69="РНВ",$E69,IF(AZ69="РНВ",$E69,IF(BA69="РНВ",$E69,IF(BB69="РНВ",$E69,IF(BC69="РНВ",$E69,IF(BD69="РНВ",$E69,IF(BE69="РНВ",$E69,IF(BF69="РНВ",$E69,IF(BG69="РНВ",$E69,IF(BH69="РНВ",$E69,IF(BI69="РНВ",$E69,0)))))))))))) -> 0 | BK69: 1 | BL69: 1 | BM69: 1 | BN69: 1 | BO69: 1 | BP69: 1 | BQ69: 1 | BR69: 1 | BS69: 1 | BT69: 1 | BU69: 1 | BV69: 1 | BW69: =IF(BK69="РНВ",$E69,IF(BL69="РНВ",$E69,IF(BM69="РНВ",$E69,IF(BN69="РНВ",$E69,IF(BO69="РНВ",$E69,IF(BP69="РНВ",$E69,IF(BQ69="РНВ",$E69,IF(BR69="РНВ",$E69,IF(BS69="РНВ",$E69,IF(BT69="РНВ",$E69,IF(BU69="РНВ",$E69,IF(BV69="РНВ",$E69,0)))))))))))) -> 0 | BX69: 1 | BY69: 1 | BZ69: 1 | CA69: РНВ | CJ69: =IF(BX69="РНВ",$E69,IF(BY69="РНВ",$E69,IF(BZ69="РНВ",$E69,IF(CA69="РНВ",$E69,IF(CB69="РНВ",$E69,IF(CC69="РНВ",$E69,IF(CD69="РНВ",$E69,IF(CE69="РНВ",$E69,IF(CF69="РНВ",$E69,IF(CG69="РНВ",$E69,IF(CH69="РНВ",$E69,IF(CI69="РНВ",$E69,0)))))))))))) -> 6683
AK70: =IF(AK69>0,$E69/$F69,0) -> 0 | AL70: =IF(AL69>0,$E69/$F69,0) -> 0 | AM70: =IF(AM69>0,$E69/$F69,0) -> 0 | AN70: =IF(AN69>0,$E69/$F69,0) -> 0 | AO70: =IF(AO69>0,$E69/$F69,0) -> 0 | AP70: =IF(AP69>0,$E69/$F69,0) -> 0 | AQ70: =IF(AQ69>0,$E69/$F69,0) -> 0 | AR70: =IF(AR69>0,$E69/$F69,0) -> 0 | ... AV70: =IF(AV69>0,$E69/$F69,0) -> 0 | AX70: =IF(AX69>0,$E69/$F69,0) -> 0 | AY70: =IF(AY69>0,$E69/$F69,0) -> 0 | AZ70: =IF(AZ69>0,$E69/$F69,0) -> 0 | BA70: =IF(BA69>0,$E69/$F69,0) -> 0 | BB70: =IF(BB69>0,$E69/$F69,0) -> 0 | BC70: =IF(BC69>0,$E69/$F69,0) -> 290.56522 | BD70: =IF(BD69>0,$E69/$F69,0) -> 290.56522 | BE70: =IF(BE69>0,$E69/$F69,0) -> 290.56522 | ... BI70: =IF(BI69>0,$E69/$F69,0) -> 290.56522 | BK70: =IF(BK69>0,$E69/$F69,0) -> 290.56522 | BL70: =IF(BL69>0,$E69/$F69,0) -> 290.56522 | BM70: =IF(BM69>0,$E69/$F69,0) -> 290.56522 | BN70: =IF(BN69>0,$E69/$F69,0) -> 290.56522 | BO70: =IF(BO69>0,$E69/$F69,0) -> 290.56522 | BP70: =IF(BP69>0,$E69/$F69,0) -> 290.56522 | BQ70: =IF(BQ69>0,$E69/$F69,0) -> 290.56522 | BR70: =IF(BR69>0,$E69/$F69,0) -> 290.56522 | ... BV70: =IF(BV69>0,$E69/$F69,0) -> 290.56522 | BX70: =IF(BX69>0,$E69/$F69,0) -> 290.56522 | BY70: =IF(BY69>0,$E69/$F69,0) -> 290.56522 | BZ70: =IF(BZ69>0,$E69/$F69,0) -> 290.56522 | CA70: =IF(CA69>0,$E69/$F69,0) -> 290.56522 | CB70: =IF(CB69>0,$E69/$F69,0) -> 0 | CC70: =IF(CC69>0,$E69/$F69,0) -> 0 | CD70: =IF(CD69>0,$E69/$F69,0) -> 0 | CE70: =IF(CE69>0,$E69/$F69,0) -> 0 | ... CI70: =IF(CI69>0,$E69/$F69,0) -> 0
A71: 33 | B71: Алексин КРТ2 1 очередь | C71: Приобретение прав на участок | D71: 4 | E71: 13135 | F71: 21 | W71: =IF(K71="РНВ",$E71,IF(L71="РНВ",$E71,IF(M71="РНВ",$E71,IF(N71="РНВ",$E71,IF(O71="РНВ",$E71,IF(P71="РНВ",$E71,IF(Q71="РНВ",$E71,IF(R71="РНВ",$E71,IF(S71="РНВ",$E71,IF(T71="РНВ",$E71,IF(U71="РНВ",$E71,IF(V71="РНВ",$E71,0)))))))))))) -> 0 | AJ71: =IF(X71="РНВ",$E71,IF(Y71="РНВ",$E71,IF(Z71="РНВ",$E71,IF(AA71="РНВ",$E71,IF(AB71="РНВ",$E71,IF(AC71="РНВ",$E71,IF(AD71="РНВ",$E71,IF(AE71="РНВ",$E71,IF(AF71="РНВ",$E71,IF(AG71="РНВ",$E71,IF(AH71="РНВ",$E71,IF(AI71="РНВ",$E71,0)))))))))))) -> 0 | AW71: =IF(AK71="РНВ",$E71,IF(AL71="РНВ",$E71,IF(AM71="РНВ",$E71,IF(AN71="РНВ",$E71,IF(AO71="РНВ",$E71,IF(AP71="РНВ",$E71,IF(AQ71="РНВ",$E71,IF(AR71="РНВ",$E71,IF(AS71="РНВ",$E71,IF(AT71="РНВ",$E71,IF(AU71="РНВ",$E71,IF(AV71="РНВ",$E71,0)))))))))))) -> 0 | BJ71: =IF(AX71="РНВ",$E71,IF(AY71="РНВ",$E71,IF(AZ71="РНВ",$E71,IF(BA71="РНВ",$E71,IF(BB71="РНВ",$E71,IF(BC71="РНВ",$E71,IF(BD71="РНВ",$E71,IF(BE71="РНВ",$E71,IF(BF71="РНВ",$E71,IF(BG71="РНВ",$E71,IF(BH71="РНВ",$E71,IF(BI71="РНВ",$E71,0)))))))))))) -> 0 | BW71: =IF(BK71="РНВ",$E71,IF(BL71="РНВ",$E71,IF(BM71="РНВ",$E71,IF(BN71="РНВ",$E71,IF(BO71="РНВ",$E71,IF(BP71="РНВ",$E71,IF(BQ71="РНВ",$E71,IF(BR71="РНВ",$E71,IF(BS71="РНВ",$E71,IF(BT71="РНВ",$E71,IF(BU71="РНВ",$E71,IF(BV71="РНВ",$E71,0)))))))))))) -> 0 | CA71: 1 | CB71: 1 | CC71: 1 | CD71: 1 | CE71: 1 | CF71: 1 | CG71: 1 | CH71: 1 | CI71: 1 | CJ71: =IF(BX71="РНВ",$E71,IF(BY71="РНВ",$E71,IF(BZ71="РНВ",$E71,IF(CA71="РНВ",$E71,IF(CB71="РНВ",$E71,IF(CC71="РНВ",$E71,IF(CD71="РНВ",$E71,IF(CE71="РНВ",$E71,IF(CF71="РНВ",$E71,IF(CG71="РНВ",$E71,IF(CH71="РНВ",$E71,IF(CI71="РНВ",$E71,0)))))))))))) -> 0
AK72: =IF(AK71>0,$E71/$F71,0) -> 0 | AL72: =IF(AL71>0,$E71/$F71,0) -> 0 | AM72: =IF(AM71>0,$E71/$F71,0) -> 0 | AN72: =IF(AN71>0,$E71/$F71,0) -> 0 | AO72: =IF(AO71>0,$E71/$F71,0) -> 0 | AP72: =IF(AP71>0,$E71/$F71,0) -> 0 | AQ72: =IF(AQ71>0,$E71/$F71,0) -> 0 | AR72: =IF(AR71>0,$E71/$F71,0) -> 0 | ... AV72: =IF(AV71>0,$E71/$F71,0) -> 0 | AX72: =IF(AX71>0,$E71/$F71,0) -> 0 | AY72: =IF(AY71>0,$E71/$F71,0) -> 0 | AZ72: =IF(AZ71>0,$E71/$F71,0) -> 0 | BA72: =IF(BA71>0,$E71/$F71,0) -> 0 | BB72: =IF(BB71>0,$E71/$F71,0) -> 0 | BC72: =IF(BC71>0,$E71/$F71,0) -> 0 | BD72: =IF(BD71>0,$E71/$F71,0) -> 0 | BE72: =IF(BE71>0,$E71/$F71,0) -> 0 | ... BI72: =IF(BI71>0,$E71/$F71,0) -> 0 | BK72: =IF(BK71>0,$E71/$F71,0) -> 0 | BL72: =IF(BL71>0,$E71/$F71,0) -> 0 | BM72: =IF(BM71>0,$E71/$F71,0) -> 0 | BN72: =IF(BN71>0,$E71/$F71,0) -> 0 | BO72: =IF(BO71>0,$E71/$F71,0) -> 0 | BP72: =IF(BP71>0,$E71/$F71,0) -> 0 | BQ72: =IF(BQ71>0,$E71/$F71,0) -> 0 | BR72: =IF(BR71>0,$E71/$F71,0) -> 0 | ... BV72: =IF(BV71>0,$E71/$F71,0) -> 0 | BX72: =IF(BX71>0,$E71/$F71,0) -> 0 | BY72: =IF(BY71>0,$E71/$F71,0) -> 0 | BZ72: =IF(BZ71>0,$E71/$F71,0) -> 0 | CA72: =IF(CA71>0,$E71/$F71,0) -> 625.47619 | CB72: =IF(CB71>0,$E71/$F71,0) -> 625.47619 | CC72: =IF(CC71>0,$E71/$F71,0) -> 625.47619 | CD72: =IF(CD71>0,$E71/$F71,0) -> 625.47619 | CE72: =IF(CE71>0,$E71/$F71,0) -> 625.47619 | ... CI72: =IF(CI71>0,$E71/$F71,0) -> 625.47619
A73: 34 | B73: Алексин КРТ2 2 очередь | C73: Приобретение прав на участок | D73: 4 | E73: 12714 | F73: =COUNTA(K73:V73,X73:AI73,AK73:AV73,AX73:BI73,BK73:BV73,BX73:CI73) -> 0 | W73: =IF(K73="РНВ",$E73,IF(L73="РНВ",$E73,IF(M73="РНВ",$E73,IF(N73="РНВ",$E73,IF(O73="РНВ",$E73,IF(P73="РНВ",$E73,IF(Q73="РНВ",$E73,IF(R73="РНВ",$E73,IF(S73="РНВ",$E73,IF(T73="РНВ",$E73,IF(U73="РНВ",$E73,IF(V73="РНВ",$E73,0)))))))))))) -> 0 | AJ73: =IF(X73="РНВ",$E73,IF(Y73="РНВ",$E73,IF(Z73="РНВ",$E73,IF(AA73="РНВ",$E73,IF(AB73="РНВ",$E73,IF(AC73="РНВ",$E73,IF(AD73="РНВ",$E73,IF(AE73="РНВ",$E73,IF(AF73="РНВ",$E73,IF(AG73="РНВ",$E73,IF(AH73="РНВ",$E73,IF(AI73="РНВ",$E73,0)))))))))))) -> 0 | AW73: =IF(AK73="РНВ",$E73,IF(AL73="РНВ",$E73,IF(AM73="РНВ",$E73,IF(AN73="РНВ",$E73,IF(AO73="РНВ",$E73,IF(AP73="РНВ",$E73,IF(AQ73="РНВ",$E73,IF(AR73="РНВ",$E73,IF(AS73="РНВ",$E73,IF(AT73="РНВ",$E73,IF(AU73="РНВ",$E73,IF(AV73="РНВ",$E73,0)))))))))))) -> 0 | BJ73: =IF(AX73="РНВ",$E73,IF(AY73="РНВ",$E73,IF(AZ73="РНВ",$E73,IF(BA73="РНВ",$E73,IF(BB73="РНВ",$E73,IF(BC73="РНВ",$E73,IF(BD73="РНВ",$E73,IF(BE73="РНВ",$E73,IF(BF73="РНВ",$E73,IF(BG73="РНВ",$E73,IF(BH73="РНВ",$E73,IF(BI73="РНВ",$E73,0)))))))))))) -> 0 | BW73: =IF(BK73="РНВ",$E73,IF(BL73="РНВ",$E73,IF(BM73="РНВ",$E73,IF(BN73="РНВ",$E73,IF(BO73="РНВ",$E73,IF(BP73="РНВ",$E73,IF(BQ73="РНВ",$E73,IF(BR73="РНВ",$E73,IF(BS73="РНВ",$E73,IF(BT73="РНВ",$E73,IF(BU73="РНВ",$E73,IF(BV73="РНВ",$E73,0)))))))))))) -> 0 | CJ73: =IF(BX73="РНВ",$E73,IF(BY73="РНВ",$E73,IF(BZ73="РНВ",$E73,IF(CA73="РНВ",$E73,IF(CB73="РНВ",$E73,IF(CC73="РНВ",$E73,IF(CD73="РНВ",$E73,IF(CE73="РНВ",$E73,IF(CF73="РНВ",$E73,IF(CG73="РНВ",$E73,IF(CH73="РНВ",$E73,IF(CI73="РНВ",$E73,0)))))))))))) -> 0
AK74: =IF(AK73>0,$E73/$F73,0) -> 0 | AL74: =IF(AL73>0,$E73/$F73,0) -> 0 | AM74: =IF(AM73>0,$E73/$F73,0) -> 0 | AN74: =IF(AN73>0,$E73/$F73,0) -> 0 | AO74: =IF(AO73>0,$E73/$F73,0) -> 0 | AP74: =IF(AP73>0,$E73/$F73,0) -> 0 | AQ74: =IF(AQ73>0,$E73/$F73,0) -> 0 | AR74: =IF(AR73>0,$E73/$F73,0) -> 0 | ... AV74: =IF(AV73>0,$E73/$F73,0) -> 0 | AX74: =IF(AX73>0,$E73/$F73,0) -> 0 | AY74: =IF(AY73>0,$E73/$F73,0) -> 0 | AZ74: =IF(AZ73>0,$E73/$F73,0) -> 0 | BA74: =IF(BA73>0,$E73/$F73,0) -> 0 | BB74: =IF(BB73>0,$E73/$F73,0) -> 0 | BC74: =IF(BC73>0,$E73/$F73,0) -> 0 | BD74: =IF(BD73>0,$E73/$F73,0) -> 0 | BE74: =IF(BE73>0,$E73/$F73,0) -> 0 | ... BI74: =IF(BI73>0,$E73/$F73,0) -> 0 | BK74: =IF(BK73>0,$E73/$F73,0) -> 0 | BL74: =IF(BL73>0,$E73/$F73,0) -> 0 | BM74: =IF(BM73>0,$E73/$F73,0) -> 0 | BN74: =IF(BN73>0,$E73/$F73,0) -> 0 | BO74: =IF(BO73>0,$E73/$F73,0) -> 0 | BP74: =IF(BP73>0,$E73/$F73,0) -> 0 | BQ74: =IF(BQ73>0,$E73/$F73,0) -> 0 | BR74: =IF(BR73>0,$E73/$F73,0) -> 0 | ... BV74: =IF(BV73>0,$E73/$F73,0) -> 0 | BX74: =IF(BX73>0,$E73/$F73,0) -> 0 | BY74: =IF(BY73>0,$E73/$F73,0) -> 0 | BZ74: =IF(BZ73>0,$E73/$F73,0) -> 0 | CA74: =IF(CA73>0,$E73/$F73,0) -> 0 | CB74: =IF(CB73>0,$E73/$F73,0) -> 0 | CC74: =IF(CC73>0,$E73/$F73,0) -> 0 | CD74: =IF(CD73>0,$E73/$F73,0) -> 0 | CE74: =IF(CE73>0,$E73/$F73,0) -> 0 | ... CI74: =IF(CI73>0,$E73/$F73,0) -> 0
A75: 35 | B75: Мичуринск, набережная 1 очередь | C75: Проектирование, экспертиза, получение РНС | D75: 5 | E75: 15836 | F75: =COUNTA(K75:V75,X75:AI75,AK75:AV75,AX75:BI75,BK75:BV75,BX75:CI75) -> 28 | W75: =IF(K75="РНВ",$E75,IF(L75="РНВ",$E75,IF(M75="РНВ",$E75,IF(N75="РНВ",$E75,IF(O75="РНВ",$E75,IF(P75="РНВ",$E75,IF(Q75="РНВ",$E75,IF(R75="РНВ",$E75,IF(S75="РНВ",$E75,IF(T75="РНВ",$E75,IF(U75="РНВ",$E75,IF(V75="РНВ",$E75,0)))))))))))) -> 0 | AI75: 1 | AJ75: =IF(X75="РНВ",$E75,IF(Y75="РНВ",$E75,IF(Z75="РНВ",$E75,IF(AA75="РНВ",$E75,IF(AB75="РНВ",$E75,IF(AC75="РНВ",$E75,IF(AD75="РНВ",$E75,IF(AE75="РНВ",$E75,IF(AF75="РНВ",$E75,IF(AG75="РНВ",$E75,IF(AH75="РНВ",$E75,IF(AI75="РНВ",$E75,0)))))))))))) -> 0 | AK75: 1 | AL75: 1 | AM75: 1 | AN75: 1 | AO75: 1 | AP75: 1 | AQ75: 1 | AR75: 1 | AS75: 1 | AT75: 1 | AU75: 1 | AV75: 1 | AW75: =IF(AK75="РНВ",$E75,IF(AL75="РНВ",$E75,IF(AM75="РНВ",$E75,IF(AN75="РНВ",$E75,IF(AO75="РНВ",$E75,IF(AP75="РНВ",$E75,IF(AQ75="РНВ",$E75,IF(AR75="РНВ",$E75,IF(AS75="РНВ",$E75,IF(AT75="РНВ",$E75,IF(AU75="РНВ",$E75,IF(AV75="РНВ",$E75,0)))))))))))) -> 0 | AX75: 1 | AY75: 1 | AZ75: 1 | BA75: 1 | BB75: 1 | BC75: 1 | BD75: 1 | BE75: 1 | BF75: 1 | BG75: 1 | BH75: 1 | BI75: 1 | BJ75: =IF(AX75="РНВ",$E75,IF(AY75="РНВ",$E75,IF(AZ75="РНВ",$E75,IF(BA75="РНВ",$E75,IF(BB75="РНВ",$E75,IF(BC75="РНВ",$E75,IF(BD75="РНВ",$E75,IF(BE75="РНВ",$E75,IF(BF75="РНВ",$E75,IF(BG75="РНВ",$E75,IF(BH75="РНВ",$E75,IF(BI75="РНВ",$E75,0)))))))))))) -> 0 | BK75: 1 | BL75: 1 | BM75: РНВ | BW75: =IF(BK75="РНВ",$E75,IF(BL75="РНВ",$E75,IF(BM75="РНВ",$E75,IF(BN75="РНВ",$E75,IF(BO75="РНВ",$E75,IF(BP75="РНВ",$E75,IF(BQ75="РНВ",$E75,IF(BR75="РНВ",$E75,IF(BS75="РНВ",$E75,IF(BT75="РНВ",$E75,IF(BU75="РНВ",$E75,IF(BV75="РНВ",$E75,0)))))))))))) -> 15836 | CJ75: =IF(BX75="РНВ",$E75,IF(BY75="РНВ",$E75,IF(BZ75="РНВ",$E75,IF(CA75="РНВ",$E75,IF(CB75="РНВ",$E75,IF(CC75="РНВ",$E75,IF(CD75="РНВ",$E75,IF(CE75="РНВ",$E75,IF(CF75="РНВ",$E75,IF(CG75="РНВ",$E75,IF(CH75="РНВ",$E75,IF(CI75="РНВ",$E75,0)))))))))))) -> 0
AK76: =IF(AK75>0,$E75/$F75,0) -> 565.57143 | AL76: =IF(AL75>0,$E75/$F75,0) -> 565.57143 | AM76: =IF(AM75>0,$E75/$F75,0) -> 565.57143 | AN76: =IF(AN75>0,$E75/$F75,0) -> 565.57143 | AO76: =IF(AO75>0,$E75/$F75,0) -> 565.57143 | AP76: =IF(AP75>0,$E75/$F75,0) -> 565.57143 | AQ76: =IF(AQ75>0,$E75/$F75,0) -> 565.57143 | AR76: =IF(AR75>0,$E75/$F75,0) -> 565.57143 | ... AV76: =IF(AV75>0,$E75/$F75,0) -> 565.57143 | AX76: =IF(AX75>0,$E75/$F75,0) -> 565.57143 | AY76: =IF(AY75>0,$E75/$F75,0) -> 565.57143 | AZ76: =IF(AZ75>0,$E75/$F75,0) -> 565.57143 | BA76: =IF(BA75>0,$E75/$F75,0) -> 565.57143 | BB76: =IF(BB75>0,$E75/$F75,0) -> 565.57143 | BC76: =IF(BC75>0,$E75/$F75,0) -> 565.57143 | BD76: =IF(BD75>0,$E75/$F75,0) -> 565.57143 | BE76: =IF(BE75>0,$E75/$F75,0) -> 565.57143 | ... BI76: =IF(BI75>0,$E75/$F75,0) -> 565.57143 | BK76: =IF(BK75>0,$E75/$F75,0) -> 565.57143 | BL76: =IF(BL75>0,$E75/$F75,0) -> 565.57143 | BM76: =IF(BM75>0,$E75/$F75,0) -> 565.57143 | BN76: =IF(BN75>0,$E75/$F75,0) -> 0 | BO76: =IF(BO75>0,$E75/$F75,0) -> 0 | BP76: =IF(BP75>0,$E75/$F75,0) -> 0 | BQ76: =IF(BQ75>0,$E75/$F75,0) -> 0 | BR76: =IF(BR75>0,$E75/$F75,0) -> 0 | ... BV76: =IF(BV75>0,$E75/$F75,0) -> 0 | BX76: =IF(BX75>0,$E75/$F75,0) -> 0 | BY76: =IF(BY75>0,$E75/$F75,0) -> 0 | BZ76: =IF(BZ75>0,$E75/$F75,0) -> 0 | CA76: =IF(CA75>0,$E75/$F75,0) -> 0 | CB76: =IF(CB75>0,$E75/$F75,0) -> 0 | CC76: =IF(CC75>0,$E75/$F75,0) -> 0 | CD76: =IF(CD75>0,$E75/$F75,0) -> 0 | CE76: =IF(CE75>0,$E75/$F75,0) -> 0 | ... CI76: =IF(CI75>0,$E75/$F75,0) -> 0
A77: 36 | B77: Мичуринск, набережная 2 очередь | C77: Приобретение прав на участок | D77: 3 | E77: 9155 | F77: =COUNTA(K77:V77,X77:AI77,AK77:AV77,AX77:BI77,BK77:BV77,BX77:CI77) -> 20 | W77: =IF(K77="РНВ",$E77,IF(L77="РНВ",$E77,IF(M77="РНВ",$E77,IF(N77="РНВ",$E77,IF(O77="РНВ",$E77,IF(P77="РНВ",$E77,IF(Q77="РНВ",$E77,IF(R77="РНВ",$E77,IF(S77="РНВ",$E77,IF(T77="РНВ",$E77,IF(U77="РНВ",$E77,IF(V77="РНВ",$E77,0)))))))))))) -> 0 | AJ77: =IF(X77="РНВ",$E77,IF(Y77="РНВ",$E77,IF(Z77="РНВ",$E77,IF(AA77="РНВ",$E77,IF(AB77="РНВ",$E77,IF(AC77="РНВ",$E77,IF(AD77="РНВ",$E77,IF(AE77="РНВ",$E77,IF(AF77="РНВ",$E77,IF(AG77="РНВ",$E77,IF(AH77="РНВ",$E77,IF(AI77="РНВ",$E77,0)))))))))))) -> 0 | AW77: =IF(AK77="РНВ",$E77,IF(AL77="РНВ",$E77,IF(AM77="РНВ",$E77,IF(AN77="РНВ",$E77,IF(AO77="РНВ",$E77,IF(AP77="РНВ",$E77,IF(AQ77="РНВ",$E77,IF(AR77="РНВ",$E77,IF(AS77="РНВ",$E77,IF(AT77="РНВ",$E77,IF(AU77="РНВ",$E77,IF(AV77="РНВ",$E77,0)))))))))))) -> 0 | AZ77: 1 | BA77: 1 | BB77: 1 | BC77: 1 | BD77: 1 | BE77: 1 | BF77: 1 | BG77: 1 | BH77: 1 | BI77: 1 | BJ77: =IF(AX77="РНВ",$E77,IF(AY77="РНВ",$E77,IF(AZ77="РНВ",$E77,IF(BA77="РНВ",$E77,IF(BB77="РНВ",$E77,IF(BC77="РНВ",$E77,IF(BD77="РНВ",$E77,IF(BE77="РНВ",$E77,IF(BF77="РНВ",$E77,IF(BG77="РНВ",$E77,IF(BH77="РНВ",$E77,IF(BI77="РНВ",$E77,0)))))))))))) -> 0 | BK77: 1 | BL77: 1 | BM77: 1 | BN77: 1 | BO77: 1 | BP77: 1 | BQ77: 1 | BR77: 1 | BS77: 1 | BT77: РНВ | BW77: =IF(BK77="РНВ",$E77,IF(BL77="РНВ",$E77,IF(BM77="РНВ",$E77,IF(BN77="РНВ",$E77,IF(BO77="РНВ",$E77,IF(BP77="РНВ",$E77,IF(BQ77="РНВ",$E77,IF(BR77="РНВ",$E77,IF(BS77="РНВ",$E77,IF(BT77="РНВ",$E77,IF(BU77="РНВ",$E77,IF(BV77="РНВ",$E77,0)))))))))))) -> 9155 | CJ77: =IF(BX77="РНВ",$E77,IF(BY77="РНВ",$E77,IF(BZ77="РНВ",$E77,IF(CA77="РНВ",$E77,IF(CB77="РНВ",$E77,IF(CC77="РНВ",$E77,IF(CD77="РНВ",$E77,IF(CE77="РНВ",$E77,IF(CF77="РНВ",$E77,IF(CG77="РНВ",$E77,IF(CH77="РНВ",$E77,IF(CI77="РНВ",$E77,0)))))))))))) -> 0
AK78: =IF(AK77>0,$E77/$F77,0) -> 0 | AL78: =IF(AL77>0,$E77/$F77,0) -> 0 | AM78: =IF(AM77>0,$E77/$F77,0) -> 0 | AN78: =IF(AN77>0,$E77/$F77,0) -> 0 | AO78: =IF(AO77>0,$E77/$F77,0) -> 0 | AP78: =IF(AP77>0,$E77/$F77,0) -> 0 | AQ78: =IF(AQ77>0,$E77/$F77,0) -> 0 | AR78: =IF(AR77>0,$E77/$F77,0) -> 0 | ... AV78: =IF(AV77>0,$E77/$F77,0) -> 0 | AX78: =IF(AX77>0,$E77/$F77,0) -> 0 | AY78: =IF(AY77>0,$E77/$F77,0) -> 0 | AZ78: =IF(AZ77>0,$E77/$F77,0) -> 457.75 | BA78: =IF(BA77>0,$E77/$F77,0) -> 457.75 | BB78: =IF(BB77>0,$E77/$F77,0) -> 457.75 | BC78: =IF(BC77>0,$E77/$F77,0) -> 457.75 | BD78: =IF(BD77>0,$E77/$F77,0) -> 457.75 | BE78: =IF(BE77>0,$E77/$F77,0) -> 457.75 | ... BI78: =IF(BI77>0,$E77/$F77,0) -> 457.75 | BK78: =IF(BK77>0,$E77/$F77,0) -> 457.75 | BL78: =IF(BL77>0,$E77/$F77,0) -> 457.75 | BM78: =IF(BM77>0,$E77/$F77,0) -> 457.75 | BN78: =IF(BN77>0,$E77/$F77,0) -> 457.75 | BO78: =IF(BO77>0,$E77/$F77,0) -> 457.75 | BP78: =IF(BP77>0,$E77/$F77,0) -> 457.75 | BQ78: =IF(BQ77>0,$E77/$F77,0) -> 457.75 | BR78: =IF(BR77>0,$E77/$F77,0) -> 457.75 | ... BV78: =IF(BV77>0,$E77/$F77,0) -> 0 | BX78: =IF(BX77>0,$E77/$F77,0) -> 0 | BY78: =IF(BY77>0,$E77/$F77,0) -> 0 | BZ78: =IF(BZ77>0,$E77/$F77,0) -> 0 | CA78: =IF(CA77>0,$E77/$F77,0) -> 0 | CB78: =IF(CB77>0,$E77/$F77,0) -> 0 | CC78: =IF(CC77>0,$E77/$F77,0) -> 0 | CD78: =IF(CD77>0,$E77/$F77,0) -> 0 | CE78: =IF(CE77>0,$E77/$F77,0) -> 0 | ... CI78: =IF(CI77>0,$E77/$F77,0) -> 0
A79: 37 | B79: Мичуринск, набережная 3 очередь | C79: Приобретение прав на участок | D79: 3 | E79: 9858 | F79: =COUNTA(K79:V79,X79:AI79,AK79:AV79,AX79:BI79,BK79:BV79,BX79:CI79) -> 24 | W79: =IF(K79="РНВ",$E79,IF(L79="РНВ",$E79,IF(M79="РНВ",$E79,IF(N79="РНВ",$E79,IF(O79="РНВ",$E79,IF(P79="РНВ",$E79,IF(Q79="РНВ",$E79,IF(R79="РНВ",$E79,IF(S79="РНВ",$E79,IF(T79="РНВ",$E79,IF(U79="РНВ",$E79,IF(V79="РНВ",$E79,0)))))))))))) -> 0 | AJ79: =IF(X79="РНВ",$E79,IF(Y79="РНВ",$E79,IF(Z79="РНВ",$E79,IF(AA79="РНВ",$E79,IF(AB79="РНВ",$E79,IF(AC79="РНВ",$E79,IF(AD79="РНВ",$E79,IF(AE79="РНВ",$E79,IF(AF79="РНВ",$E79,IF(AG79="РНВ",$E79,IF(AH79="РНВ",$E79,IF(AI79="РНВ",$E79,0)))))))))))) -> 0 | AW79: =IF(AK79="РНВ",$E79,IF(AL79="РНВ",$E79,IF(AM79="РНВ",$E79,IF(AN79="РНВ",$E79,IF(AO79="РНВ",$E79,IF(AP79="РНВ",$E79,IF(AQ79="РНВ",$E79,IF(AR79="РНВ",$E79,IF(AS79="РНВ",$E79,IF(AT79="РНВ",$E79,IF(AU79="РНВ",$E79,IF(AV79="РНВ",$E79,0)))))))))))) -> 0 | BE79: 1 | BF79: 1 | BG79: 1 | BH79: 1 | BI79: 1 | BJ79: =IF(AX79="РНВ",$E79,IF(AY79="РНВ",$E79,IF(AZ79="РНВ",$E79,IF(BA79="РНВ",$E79,IF(BB79="РНВ",$E79,IF(BC79="РНВ",$E79,IF(BD79="РНВ",$E79,IF(BE79="РНВ",$E79,IF(BF79="РНВ",$E79,IF(BG79="РНВ",$E79,IF(BH79="РНВ",$E79,IF(BI79="РНВ",$E79,0)))))))))))) -> 0 | BK79: 1 | BL79: 1 | BM79: 1 | BN79: 1 | BO79: 1 | BP79: 1 | BQ79: 1 | BR79: 1 | BS79: 1 | BT79: 1 | BU79: 1 | BV79: 1 | BW79: =IF(BK79="РНВ",$E79,IF(BL79="РНВ",$E79,IF(BM79="РНВ",$E79,IF(BN79="РНВ",$E79,IF(BO79="РНВ",$E79,IF(BP79="РНВ",$E79,IF(BQ79="РНВ",$E79,IF(BR79="РНВ",$E79,IF(BS79="РНВ",$E79,IF(BT79="РНВ",$E79,IF(BU79="РНВ",$E79,IF(BV79="РНВ",$E79,0)))))))))))) -> 0 | BX79: 1 | BY79: 1 | BZ79: 1 | CA79: 1 | CB79: 1 | CC79: 1 | CD79: РНВ | CJ79: =IF(BX79="РНВ",$E79,IF(BY79="РНВ",$E79,IF(BZ79="РНВ",$E79,IF(CA79="РНВ",$E79,IF(CB79="РНВ",$E79,IF(CC79="РНВ",$E79,IF(CD79="РНВ",$E79,IF(CE79="РНВ",$E79,IF(CF79="РНВ",$E79,IF(CG79="РНВ",$E79,IF(CH79="РНВ",$E79,IF(CI79="РНВ",$E79,0)))))))))))) -> 9858
AK80: =IF(AK79>0,$E79/$F79,0) -> 0 | AL80: =IF(AL79>0,$E79/$F79,0) -> 0 | AM80: =IF(AM79>0,$E79/$F79,0) -> 0 | AN80: =IF(AN79>0,$E79/$F79,0) -> 0 | AO80: =IF(AO79>0,$E79/$F79,0) -> 0 | AP80: =IF(AP79>0,$E79/$F79,0) -> 0 | AQ80: =IF(AQ79>0,$E79/$F79,0) -> 0 | AR80: =IF(AR79>0,$E79/$F79,0) -> 0 | ... AV80: =IF(AV79>0,$E79/$F79,0) -> 0 | AX80: =IF(AX79>0,$E79/$F79,0) -> 0 | AY80: =IF(AY79>0,$E79/$F79,0) -> 0 | AZ80: =IF(AZ79>0,$E79/$F79,0) -> 0 | BA80: =IF(BA79>0,$E79/$F79,0) -> 0 | BB80: =IF(BB79>0,$E79/$F79,0) -> 0 | BC80: =IF(BC79>0,$E79/$F79,0) -> 0 | BD80: =IF(BD79>0,$E79/$F79,0) -> 0 | BE80: =IF(BE79>0,$E79/$F79,0) -> 410.75 | ... BI80: =IF(BI79>0,$E79/$F79,0) -> 410.75 | BK80: =IF(BK79>0,$E79/$F79,0) -> 410.75 | BL80: =IF(BL79>0,$E79/$F79,0) -> 410.75 | BM80: =IF(BM79>0,$E79/$F79,0) -> 410.75 | BN80: =IF(BN79>0,$E79/$F79,0) -> 410.75 | BO80: =IF(BO79>0,$E79/$F79,0) -> 410.75 | BP80: =IF(BP79>0,$E79/$F79,0) -> 410.75 | BQ80: =IF(BQ79>0,$E79/$F79,0) -> 410.75 | BR80: =IF(BR79>0,$E79/$F79,0) -> 410.75 | ... BV80: =IF(BV79>0,$E79/$F79,0) -> 410.75 | BX80: =IF(BX79>0,$E79/$F79,0) -> 410.75 | BY80: =IF(BY79>0,$E79/$F79,0) -> 410.75 | BZ80: =IF(BZ79>0,$E79/$F79,0) -> 410.75 | CA80: =IF(CA79>0,$E79/$F79,0) -> 410.75 | CB80: =IF(CB79>0,$E79/$F79,0) -> 410.75 | CC80: =IF(CC79>0,$E79/$F79,0) -> 410.75 | CD80: =IF(CD79>0,$E79/$F79,0) -> 410.75 | CE80: =IF(CE79>0,$E79/$F79,0) -> 0 | ... CI80: =IF(CI79>0,$E79/$F79,0) -> 0
A81: 38 | B81: Мичуринск, набережная 4 очередь | C81: Есть право на зу, ждет реализации | D81: 3 | E81: 9523 | F81: =COUNTA(K81:V81,X81:AI81,AK81:AV81,AX81:BI81,BK81:BV81,BX81:CI81) -> 21 | W81: =IF(K81="РНВ",$E81,IF(L81="РНВ",$E81,IF(M81="РНВ",$E81,IF(N81="РНВ",$E81,IF(O81="РНВ",$E81,IF(P81="РНВ",$E81,IF(Q81="РНВ",$E81,IF(R81="РНВ",$E81,IF(S81="РНВ",$E81,IF(T81="РНВ",$E81,IF(U81="РНВ",$E81,IF(V81="РНВ",$E81,0)))))))))))) -> 0 | AJ81: =IF(X81="РНВ",$E81,IF(Y81="РНВ",$E81,IF(Z81="РНВ",$E81,IF(AA81="РНВ",$E81,IF(AB81="РНВ",$E81,IF(AC81="РНВ",$E81,IF(AD81="РНВ",$E81,IF(AE81="РНВ",$E81,IF(AF81="РНВ",$E81,IF(AG81="РНВ",$E81,IF(AH81="РНВ",$E81,IF(AI81="РНВ",$E81,0)))))))))))) -> 0 | AW81: =IF(AK81="РНВ",$E81,IF(AL81="РНВ",$E81,IF(AM81="РНВ",$E81,IF(AN81="РНВ",$E81,IF(AO81="РНВ",$E81,IF(AP81="РНВ",$E81,IF(AQ81="РНВ",$E81,IF(AR81="РНВ",$E81,IF(AS81="РНВ",$E81,IF(AT81="РНВ",$E81,IF(AU81="РНВ",$E81,IF(AV81="РНВ",$E81,0)))))))))))) -> 0 | BJ81: =IF(AX81="РНВ",$E81,IF(AY81="РНВ",$E81,IF(AZ81="РНВ",$E81,IF(BA81="РНВ",$E81,IF(BB81="РНВ",$E81,IF(BC81="РНВ",$E81,IF(BD81="РНВ",$E81,IF(BE81="РНВ",$E81,IF(BF81="РНВ",$E81,IF(BG81="РНВ",$E81,IF(BH81="РНВ",$E81,IF(BI81="РНВ",$E81,0)))))))))))) -> 0 | BM81: 1 | BN81: 1 | BO81: 1 | BP81: 1 | BQ81: 1 | BR81: 1 | BS81: 1 | BT81: 1 | BU81: 1 | BV81: 1 | BW81: =IF(BK81="РНВ",$E81,IF(BL81="РНВ",$E81,IF(BM81="РНВ",$E81,IF(BN81="РНВ",$E81,IF(BO81="РНВ",$E81,IF(BP81="РНВ",$E81,IF(BQ81="РНВ",$E81,IF(BR81="РНВ",$E81,IF(BS81="РНВ",$E81,IF(BT81="РНВ",$E81,IF(BU81="РНВ",$E81,IF(BV81="РНВ",$E81,0)))))))))))) -> 0 | BX81: 1 | BY81: 1 | BZ81: 1 | CA81: 1 | CB81: 1 | CC81: 1 | CD81: 1 | CE81: 1 | CF81: 1 | CG81: 1 | CH81: РНВ | CJ81: =IF(BX81="РНВ",$E81,IF(BY81="РНВ",$E81,IF(BZ81="РНВ",$E81,IF(CA81="РНВ",$E81,IF(CB81="РНВ",$E81,IF(CC81="РНВ",$E81,IF(CD81="РНВ",$E81,IF(CE81="РНВ",$E81,IF(CF81="РНВ",$E81,IF(CG81="РНВ",$E81,IF(CH81="РНВ",$E81,IF(CI81="РНВ",$E81,0)))))))))))) -> 9523
AK82: =IF(AK81>0,$E81/$F81,0) -> 0 | AL82: =IF(AL81>0,$E81/$F81,0) -> 0 | AM82: =IF(AM81>0,$E81/$F81,0) -> 0 | AN82: =IF(AN81>0,$E81/$F81,0) -> 0 | AO82: =IF(AO81>0,$E81/$F81,0) -> 0 | AP82: =IF(AP81>0,$E81/$F81,0) -> 0 | AQ82: =IF(AQ81>0,$E81/$F81,0) -> 0 | AR82: =IF(AR81>0,$E81/$F81,0) -> 0 | ... AV82: =IF(AV81>0,$E81/$F81,0) -> 0 | AX82: =IF(AX81>0,$E81/$F81,0) -> 0 | AY82: =IF(AY81>0,$E81/$F81,0) -> 0 | AZ82: =IF(AZ81>0,$E81/$F81,0) -> 0 | BA82: =IF(BA81>0,$E81/$F81,0) -> 0 | BB82: =IF(BB81>0,$E81/$F81,0) -> 0 | BC82: =IF(BC81>0,$E81/$F81,0) -> 0 | BD82: =IF(BD81>0,$E81/$F81,0) -> 0 | BE82: =IF(BE81>0,$E81/$F81,0) -> 0 | ... BI82: =IF(BI81>0,$E81/$F81,0) -> 0 | BK82: =IF(BK81>0,$E81/$F81,0) -> 0 | BL82: =IF(BL81>0,$E81/$F81,0) -> 0 | BM82: =IF(BM81>0,$E81/$F81,0) -> 453.47619 | BN82: =IF(BN81>0,$E81/$F81,0) -> 453.47619 | BO82: =IF(BO81>0,$E81/$F81,0) -> 453.47619 | BP82: =IF(BP81>0,$E81/$F81,0) -> 453.47619 | BQ82: =IF(BQ81>0,$E81/$F81,0) -> 453.47619 | BR82: =IF(BR81>0,$E81/$F81,0) -> 453.47619 | ... BV82: =IF(BV81>0,$E81/$F81,0) -> 453.47619 | BX82: =IF(BX81>0,$E81/$F81,0) -> 453.47619 | BY82: =IF(BY81>0,$E81/$F81,0) -> 453.47619 | BZ82: =IF(BZ81>0,$E81/$F81,0) -> 453.47619 | CA82: =IF(CA81>0,$E81/$F81,0) -> 453.47619 | CB82: =IF(CB81>0,$E81/$F81,0) -> 453.47619 | CC82: =IF(CC81>0,$E81/$F81,0) -> 453.47619 | CD82: =IF(CD81>0,$E81/$F81,0) -> 453.47619 | CE82: =IF(CE81>0,$E81/$F81,0) -> 453.47619 | ... CI82: =IF(CI81>0,$E81/$F81,0) -> 0
A83: 39 | B83: Борисоглебск, торги | C83: Приобретение прав на участок | D83: 6 | E83: 20241 | F83: =COUNTA(K83:V83,X83:AI83,AK83:AV83,AX83:BI83,BK83:BV83,BX83:CI83) -> 28 | W83: =IF(K83="РНВ",$E83,IF(L83="РНВ",$E83,IF(M83="РНВ",$E83,IF(N83="РНВ",$E83,IF(O83="РНВ",$E83,IF(P83="РНВ",$E83,IF(Q83="РНВ",$E83,IF(R83="РНВ",$E83,IF(S83="РНВ",$E83,IF(T83="РНВ",$E83,IF(U83="РНВ",$E83,IF(V83="РНВ",$E83,0)))))))))))) -> 0 | AJ83: =IF(X83="РНВ",$E83,IF(Y83="РНВ",$E83,IF(Z83="РНВ",$E83,IF(AA83="РНВ",$E83,IF(AB83="РНВ",$E83,IF(AC83="РНВ",$E83,IF(AD83="РНВ",$E83,IF(AE83="РНВ",$E83,IF(AF83="РНВ",$E83,IF(AG83="РНВ",$E83,IF(AH83="РНВ",$E83,IF(AI83="РНВ",$E83,0)))))))))))) -> 0 | AK83: 1 | AL83: 1 | AM83: 1 | AN83: 1 | AO83: 1 | AP83: 1 | AQ83: 1 | AR83: 1 | AS83: 1 | AT83: 1 | AU83: 1 | AV83: 1 | AW83: =IF(AK83="РНВ",$E83,IF(AL83="РНВ",$E83,IF(AM83="РНВ",$E83,IF(AN83="РНВ",$E83,IF(AO83="РНВ",$E83,IF(AP83="РНВ",$E83,IF(AQ83="РНВ",$E83,IF(AR83="РНВ",$E83,IF(AS83="РНВ",$E83,IF(AT83="РНВ",$E83,IF(AU83="РНВ",$E83,IF(AV83="РНВ",$E83,0)))))))))))) -> 0 | AX83: 1 | AY83: 1 | AZ83: 1 | BA83: 1 | BB83: 1 | BC83: 1 | BD83: 1 | BE83: 1 | BF83: 1 | BG83: 1 | BH83: 1 | BI83: 1 | BJ83: =IF(AX83="РНВ",$E83,IF(AY83="РНВ",$E83,IF(AZ83="РНВ",$E83,IF(BA83="РНВ",$E83,IF(BB83="РНВ",$E83,IF(BC83="РНВ",$E83,IF(BD83="РНВ",$E83,IF(BE83="РНВ",$E83,IF(BF83="РНВ",$E83,IF(BG83="РНВ",$E83,IF(BH83="РНВ",$E83,IF(BI83="РНВ",$E83,0)))))))))))) -> 0 | BK83: 1 | BL83: 1 | BM83: 1 | BN83: РНВ | BW83: =IF(BK83="РНВ",$E83,IF(BL83="РНВ",$E83,IF(BM83="РНВ",$E83,IF(BN83="РНВ",$E83,IF(BO83="РНВ",$E83,IF(BP83="РНВ",$E83,IF(BQ83="РНВ",$E83,IF(BR83="РНВ",$E83,IF(BS83="РНВ",$E83,IF(BT83="РНВ",$E83,IF(BU83="РНВ",$E83,IF(BV83="РНВ",$E83,0)))))))))))) -> 20241 | CJ83: =IF(BX83="РНВ",$E83,IF(BY83="РНВ",$E83,IF(BZ83="РНВ",$E83,IF(CA83="РНВ",$E83,IF(CB83="РНВ",$E83,IF(CC83="РНВ",$E83,IF(CD83="РНВ",$E83,IF(CE83="РНВ",$E83,IF(CF83="РНВ",$E83,IF(CG83="РНВ",$E83,IF(CH83="РНВ",$E83,IF(CI83="РНВ",$E83,0)))))))))))) -> 0
AK84: =IF(AK83>0,$E83/$F83,0) -> 722.89286 | AL84: =IF(AL83>0,$E83/$F83,0) -> 722.89286 | AM84: =IF(AM83>0,$E83/$F83,0) -> 722.89286 | AN84: =IF(AN83>0,$E83/$F83,0) -> 722.89286 | AO84: =IF(AO83>0,$E83/$F83,0) -> 722.89286 | AP84: =IF(AP83>0,$E83/$F83,0) -> 722.89286 | AQ84: =IF(AQ83>0,$E83/$F83,0) -> 722.89286 | AR84: =IF(AR83>0,$E83/$F83,0) -> 722.89286 | ... AV84: =IF(AV83>0,$E83/$F83,0) -> 722.89286 | AX84: =IF(AX83>0,$E83/$F83,0) -> 722.89286 | AY84: =IF(AY83>0,$E83/$F83,0) -> 722.89286 | AZ84: =IF(AZ83>0,$E83/$F83,0) -> 722.89286 | BA84: =IF(BA83>0,$E83/$F83,0) -> 722.89286 | BB84: =IF(BB83>0,$E83/$F83,0) -> 722.89286 | BC84: =IF(BC83>0,$E83/$F83,0) -> 722.89286 | BD84: =IF(BD83>0,$E83/$F83,0) -> 722.89286 | BE84: =IF(BE83>0,$E83/$F83,0) -> 722.89286 | ... BI84: =IF(BI83>0,$E83/$F83,0) -> 722.89286 | BK84: =IF(BK83>0,$E83/$F83,0) -> 722.89286 | BL84: =IF(BL83>0,$E83/$F83,0) -> 722.89286 | BM84: =IF(BM83>0,$E83/$F83,0) -> 722.89286 | BN84: =IF(BN83>0,$E83/$F83,0) -> 722.89286 | BO84: =IF(BO83>0,$E83/$F83,0) -> 0 | BP84: =IF(BP83>0,$E83/$F83,0) -> 0 | BQ84: =IF(BQ83>0,$E83/$F83,0) -> 0 | BR84: =IF(BR83>0,$E83/$F83,0) -> 0 | ... BV84: =IF(BV83>0,$E83/$F83,0) -> 0 | BX84: =IF(BX83>0,$E83/$F83,0) -> 0 | BY84: =IF(BY83>0,$E83/$F83,0) -> 0 | BZ84: =IF(BZ83>0,$E83/$F83,0) -> 0 | CA84: =IF(CA83>0,$E83/$F83,0) -> 0 | CB84: =IF(CB83>0,$E83/$F83,0) -> 0 | CC84: =IF(CC83>0,$E83/$F83,0) -> 0 | CD84: =IF(CD83>0,$E83/$F83,0) -> 0 | CE84: =IF(CE83>0,$E83/$F83,0) -> 0 | ... CI84: =IF(CI83>0,$E83/$F83,0) -> 0
A85: 40 | B85: Участки 2026 | C85: Поиск участка | E85: =E94-E88-E90-E91 -> 110307.79 | F85: =COUNTA(K85:V85,X85:AI85,AK85:AV85,AX85:BI85,BK85:BV85,BX85:CI85) -> 0 | W85: =IF(K85="РНВ",$E85,IF(L85="РНВ",$E85,IF(M85="РНВ",$E85,IF(N85="РНВ",$E85,IF(O85="РНВ",$E85,IF(P85="РНВ",$E85,IF(Q85="РНВ",$E85,IF(R85="РНВ",$E85,IF(S85="РНВ",$E85,IF(T85="РНВ",$E85,IF(U85="РНВ",$E85,IF(V85="РНВ",$E85,0)))))))))))) -> 0 | AJ85: =IF(X85="РНВ",$E85,IF(Y85="РНВ",$E85,IF(Z85="РНВ",$E85,IF(AA85="РНВ",$E85,IF(AB85="РНВ",$E85,IF(AC85="РНВ",$E85,IF(AD85="РНВ",$E85,IF(AE85="РНВ",$E85,IF(AF85="РНВ",$E85,IF(AG85="РНВ",$E85,IF(AH85="РНВ",$E85,IF(AI85="РНВ",$E85,0)))))))))))) -> 0 | AW85: =IF(AK85="РНВ",$E85,IF(AL85="РНВ",$E85,IF(AM85="РНВ",$E85,IF(AN85="РНВ",$E85,IF(AO85="РНВ",$E85,IF(AP85="РНВ",$E85,IF(AQ85="РНВ",$E85,IF(AR85="РНВ",$E85,IF(AS85="РНВ",$E85,IF(AT85="РНВ",$E85,IF(AU85="РНВ",$E85,IF(AV85="РНВ",$E85,0)))))))))))) -> 0 | BJ85: =IF(AX85="РНВ",$E85,IF(AY85="РНВ",$E85,IF(AZ85="РНВ",$E85,IF(BA85="РНВ",$E85,IF(BB85="РНВ",$E85,IF(BC85="РНВ",$E85,IF(BD85="РНВ",$E85,IF(BE85="РНВ",$E85,IF(BF85="РНВ",$E85,IF(BG85="РНВ",$E85,IF(BH85="РНВ",$E85,IF(BI85="РНВ",$E85,0)))))))))))) -> 0 | BW85: =IF(BK85="РНВ",$E85,IF(BL85="РНВ",$E85,IF(BM85="РНВ",$E85,IF(BN85="РНВ",$E85,IF(BO85="РНВ",$E85,IF(BP85="РНВ",$E85,IF(BQ85="РНВ",$E85,IF(BR85="РНВ",$E85,IF(BS85="РНВ",$E85,IF(BT85="РНВ",$E85,IF(BU85="РНВ",$E85,IF(BV85="РНВ",$E85,0)))))))))))) -> 0 | CJ85: =IF(BX85="РНВ",$E85,IF(BY85="РНВ",$E85,IF(BZ85="РНВ",$E85,IF(CA85="РНВ",$E85,IF(CB85="РНВ",$E85,IF(CC85="РНВ",$E85,IF(CD85="РНВ",$E85,IF(CE85="РНВ",$E85,IF(CF85="РНВ",$E85,IF(CG85="РНВ",$E85,IF(CH85="РНВ",$E85,IF(CI85="РНВ",$E85,0)))))))))))) -> 0
AK86: =IF(AK85>0,$E85/$F85,0) -> 0 | AL86: =IF(AL85>0,$E85/$F85,0) -> 0 | AM86: =IF(AM85>0,$E85/$F85,0) -> 0 | AN86: =IF(AN85>0,$E85/$F85,0) -> 0 | AO86: =IF(AO85>0,$E85/$F85,0) -> 0 | AP86: =IF(AP85>0,$E85/$F85,0) -> 0 | AQ86: =IF(AQ85>0,$E85/$F85,0) -> 0 | AR86: =IF(AR85>0,$E85/$F85,0) -> 0 | ... AV86: =IF(AV85>0,$E85/$F85,0) -> 0 | AX86: =IF(AX85>0,$E85/$F85,0) -> 0 | AY86: =IF(AY85>0,$E85/$F85,0) -> 0 | AZ86: =IF(AZ85>0,$E85/$F85,0) -> 0 | BA86: =IF(BA85>0,$E85/$F85,0) -> 0 | BB86: =IF(BB85>0,$E85/$F85,0) -> 0 | BC86: =IF(BC85>0,$E85/$F85,0) -> 0 | BD86: =IF(BD85>0,$E85/$F85,0) -> 0 | BE86: =IF(BE85>0,$E85/$F85,0) -> 0 | ... BI86: =IF(BI85>0,$E85/$F85,0) -> 0 | BK86: =IF(BK85>0,$E85/$F85,0) -> 0 | BL86: =IF(BL85>0,$E85/$F85,0) -> 0 | BM86: =IF(BM85>0,$E85/$F85,0) -> 0 | BN86: =IF(BN85>0,$E85/$F85,0) -> 0 | BO86: =IF(BO85>0,$E85/$F85,0) -> 0 | BP86: =IF(BP85>0,$E85/$F85,0) -> 0 | BQ86: =IF(BQ85>0,$E85/$F85,0) -> 0 | BR86: =IF(BR85>0,$E85/$F85,0) -> 0 | ... BV86: =IF(BV85>0,$E85/$F85,0) -> 0 | BX86: =IF(BX85>0,$E85/$F85,0) -> 0 | BY86: =IF(BY85>0,$E85/$F85,0) -> 0 | BZ86: =IF(BZ85>0,$E85/$F85,0) -> 0 | CA86: =IF(CA85>0,$E85/$F85,0) -> 0 | CB86: =IF(CB85>0,$E85/$F85,0) -> 0 | CC86: =IF(CC85>0,$E85/$F85,0) -> 0 | CD86: =IF(CD85>0,$E85/$F85,0) -> 0 | CE86: =IF(CE85>0,$E85/$F85,0) -> 0 | ... CI86: =IF(CI85>0,$E85/$F85,0) -> 0
A87: ИТОГО | C87: Строительство | E87: =SUMIF($C$7:$C$86,C87,$E$7:$E$86) -> 62824.74 | W87: =IF(K87="РНВ",$E87,IF(L87="РНВ",$E87,IF(M87="РНВ",$E87,IF(N87="РНВ",$E87,IF(O87="РНВ",$E87,IF(P87="РНВ",$E87,IF(Q87="РНВ",$E87,IF(R87="РНВ",$E87,IF(S87="РНВ",$E87,IF(T87="РНВ",$E87,IF(U87="РНВ",$E87,IF(V87="РНВ",$E87,0)))))))))))) -> 0 | AJ87: =IF(X87="РНВ",$E87,IF(Y87="РНВ",$E87,IF(Z87="РНВ",$E87,IF(AA87="РНВ",$E87,IF(AB87="РНВ",$E87,IF(AC87="РНВ",$E87,IF(AD87="РНВ",$E87,IF(AE87="РНВ",$E87,IF(AF87="РНВ",$E87,IF(AG87="РНВ",$E87,IF(AH87="РНВ",$E87,IF(AI87="РНВ",$E87,0)))))))))))) -> 0 | AW87: =IF(AK87="РНВ",$E87,IF(AL87="РНВ",$E87,IF(AM87="РНВ",$E87,IF(AN87="РНВ",$E87,IF(AO87="РНВ",$E87,IF(AP87="РНВ",$E87,IF(AQ87="РНВ",$E87,IF(AR87="РНВ",$E87,IF(AS87="РНВ",$E87,IF(AT87="РНВ",$E87,IF(AU87="РНВ",$E87,IF(AV87="РНВ",$E87,0)))))))))))) -> 0 | BJ87: =IF(AX87="РНВ",$E87,IF(AY87="РНВ",$E87,IF(AZ87="РНВ",$E87,IF(BA87="РНВ",$E87,IF(BB87="РНВ",$E87,IF(BC87="РНВ",$E87,IF(BD87="РНВ",$E87,IF(BE87="РНВ",$E87,IF(BF87="РНВ",$E87,IF(BG87="РНВ",$E87,IF(BH87="РНВ",$E87,IF(BI87="РНВ",$E87,0)))))))))))) -> 0 | BW87: =IF(BK87="РНВ",$E87,IF(BL87="РНВ",$E87,IF(BM87="РНВ",$E87,IF(BN87="РНВ",$E87,IF(BO87="РНВ",$E87,IF(BP87="РНВ",$E87,IF(BQ87="РНВ",$E87,IF(BR87="РНВ",$E87,IF(BS87="РНВ",$E87,IF(BT87="РНВ",$E87,IF(BU87="РНВ",$E87,IF(BV87="РНВ",$E87,0)))))))))))) -> 0 | CJ87: =IF(BX87="РНВ",$E87,IF(BY87="РНВ",$E87,IF(BZ87="РНВ",$E87,IF(CA87="РНВ",$E87,IF(CB87="РНВ",$E87,IF(CC87="РНВ",$E87,IF(CD87="РНВ",$E87,IF(CE87="РНВ",$E87,IF(CF87="РНВ",$E87,IF(CG87="РНВ",$E87,IF(CH87="РНВ",$E87,IF(CI87="РНВ",$E87,0)))))))))))) -> 0
C88: Проектирование, экспертиза, получение РНС | E88: =SUMIF($C$7:$C$86,C88,$E$7:$E$86) -> 66339.04
C89: Поиск участка | E89: =SUMIF($C$7:$C$86,C89,$E$7:$E$86) -> 110307.79 | W89: =IF(K89="РНВ",$E89,IF(L89="РНВ",$E89,IF(M89="РНВ",$E89,IF(N89="РНВ",$E89,IF(O89="РНВ",$E89,IF(P89="РНВ",$E89,IF(Q89="РНВ",$E89,IF(R89="РНВ",$E89,IF(S89="РНВ",$E89,IF(T89="РНВ",$E89,IF(U89="РНВ",$E89,IF(V89="РНВ",$E89,0)))))))))))) -> 0 | AJ89: =IF(X89="РНВ",$E89,IF(Y89="РНВ",$E89,IF(Z89="РНВ",$E89,IF(AA89="РНВ",$E89,IF(AB89="РНВ",$E89,IF(AC89="РНВ",$E89,IF(AD89="РНВ",$E89,IF(AE89="РНВ",$E89,IF(AF89="РНВ",$E89,IF(AG89="РНВ",$E89,IF(AH89="РНВ",$E89,IF(AI89="РНВ",$E89,0)))))))))))) -> 0 | AW89: =IF(AK89="РНВ",$E89,IF(AL89="РНВ",$E89,IF(AM89="РНВ",$E89,IF(AN89="РНВ",$E89,IF(AO89="РНВ",$E89,IF(AP89="РНВ",$E89,IF(AQ89="РНВ",$E89,IF(AR89="РНВ",$E89,IF(AS89="РНВ",$E89,IF(AT89="РНВ",$E89,IF(AU89="РНВ",$E89,IF(AV89="РНВ",$E89,0)))))))))))) -> 0 | BJ89: =IF(AX89="РНВ",$E89,IF(AY89="РНВ",$E89,IF(AZ89="РНВ",$E89,IF(BA89="РНВ",$E89,IF(BB89="РНВ",$E89,IF(BC89="РНВ",$E89,IF(BD89="РНВ",$E89,IF(BE89="РНВ",$E89,IF(BF89="РНВ",$E89,IF(BG89="РНВ",$E89,IF(BH89="РНВ",$E89,IF(BI89="РНВ",$E89,0)))))))))))) -> 0 | BW89: =IF(BK89="РНВ",$E89,IF(BL89="РНВ",$E89,IF(BM89="РНВ",$E89,IF(BN89="РНВ",$E89,IF(BO89="РНВ",$E89,IF(BP89="РНВ",$E89,IF(BQ89="РНВ",$E89,IF(BR89="РНВ",$E89,IF(BS89="РНВ",$E89,IF(BT89="РНВ",$E89,IF(BU89="РНВ",$E89,IF(BV89="РНВ",$E89,0)))))))))))) -> 0 | CJ89: =IF(BX89="РНВ",$E89,IF(BY89="РНВ",$E89,IF(BZ89="РНВ",$E89,IF(CA89="РНВ",$E89,IF(CB89="РНВ",$E89,IF(CC89="РНВ",$E89,IF(CD89="РНВ",$E89,IF(CE89="РНВ",$E89,IF(CF89="РНВ",$E89,IF(CG89="РНВ",$E89,IF(CH89="РНВ",$E89,IF(CI89="РНВ",$E89,0)))))))))))) -> 0
C90: Приобретение прав на участок | E90: =SUMIF($C$7:$C$86,C90,$E$7:$E$86) -> 114499
C91: Есть право на зу, ждет реализации | E91: =SUMIF($C$7:$C$86,C91,$E$7:$E$86) -> 138041.17
C92: Завершен | E92: =SUMIF($C$7:$C$86,C92,$E$7:$E$86) -> 56846
C93: Стратегия 2026 | E93: 106368
C94: Стратегия 2027 | E94: =322819+E93 -> 429187
G95: =G86+G80+G76+G56+G54+G52+G46+G44+G42+G40+G38+G36+G34+G32+G30+G28+G26+G24+G20+G18+G16+G14+G12+G10+G8 -> 0 | H95: =H86+H80+H76+H56+H54+H52+H46+H44+H42+H40+H38+H36+H34+H32+H30+H28+H26+H24+H20+H18+H16+H14+H12+H10+H8 -> 0 | I95: =I86+I80+I76+I56+I54+I52+I46+I44+I42+I40+I38+I36+I34+I32+I30+I28+I26+I24+I20+I18+I16+I14+I12+I10+I8 -> 0 | J95: =J86+J80+J76+J56+J54+J52+J46+J44+J42+J40+J38+J36+J34+J32+J30+J28+J26+J24+J20+J18+J16+J14+J12+J10+J8 -> 0 | K95: =K86+K80+K76+K56+K54+K52+K46+K44+K42+K40+K38+K36+K34+K32+K30+K28+K26+K24+K20+K18+K16+K14+K12+K10+K8 -> 0 | L95: =L86+L80+L76+L56+L54+L52+L46+L44+L42+L40+L38+L36+L34+L32+L30+L28+L26+L24+L20+L18+L16+L14+L12+L10+L8 -> 0 | M95: =M86+M80+M76+M56+M54+M52+M46+M44+M42+M40+M38+M36+M34+M32+M30+M28+M26+M24+M20+M18+M16+M14+M12+M10+M8 -> 0 | N95: =N86+N80+N76+N56+N54+N52+N46+N44+N42+N40+N38+N36+N34+N32+N30+N28+N26+N24+N20+N18+N16+N14+N12+N10+N8 -> 0 | ... AJ95: =AJ86+AJ80+AJ76+AJ56+AJ54+AJ52+AJ46+AJ44+AJ42+AJ40+AJ38+AJ36+AJ34+AJ32+AJ30+AJ28+AJ26+AJ24+AJ20+AJ18+AJ16+AJ14+AJ12+AJ10+AJ8 -> 0
A96: Итого в строительстве м2 по месяцам | AK96: =AK86+AK84+AK82+AK80+AK78+AK76+AK74+AK72+AK70+AK68+AK66+AK64+AK62+AK60+AK58+AK56+AK54+AK52+AK46+AK44+AK42+AK40+AK38+AK36+AK34+AK32+AK30+AK28+AK26+AK24+AK22+AK20+AK18+AK16+AK14+AK12+AK10+AK8 -> 4333.0326 | AL96: =AL86+AL84+AL82+AL80+AL78+AL76+AL74+AL72+AL70+AL68+AL66+AL64+AL62+AL60+AL58+AL56+AL54+AL52+AL46+AL44+AL42+AL40+AL38+AL36+AL34+AL32+AL30+AL28+AL26+AL24+AL22+AL20+AL18+AL16+AL14+AL12+AL10+AL8 -> 4333.0326 | AM96: =AM86+AM84+AM82+AM80+AM78+AM76+AM74+AM72+AM70+AM68+AM66+AM64+AM62+AM60+AM58+AM56+AM54+AM52+AM46+AM44+AM42+AM40+AM38+AM36+AM34+AM32+AM30+AM28+AM26+AM24+AM22+AM20+AM18+AM16+AM14+AM12+AM10+AM8 -> 5050.8104 | AN96: =AN86+AN84+AN82+AN80+AN78+AN76+AN74+AN72+AN70+AN68+AN66+AN64+AN62+AN60+AN58+AN56+AN54+AN52+AN46+AN44+AN42+AN40+AN38+AN36+AN34+AN32+AN30+AN28+AN26+AN24+AN22+AN20+AN18+AN16+AN14+AN12+AN10+AN8 -> 5566.2628 | AO96: =AO86+AO84+AO82+AO80+AO78+AO76+AO74+AO72+AO70+AO68+AO66+AO64+AO62+AO60+AO58+AO56+AO54+AO52+AO46+AO44+AO42+AO40+AO38+AO36+AO34+AO32+AO30+AO28+AO26+AO24+AO22+AO20+AO18+AO16+AO14+AO12+AO10+AO8 -> 5566.2628 | AP96: =AP86+AP84+AP82+AP80+AP78+AP76+AP74+AP72+AP70+AP68+AP66+AP64+AP62+AP60+AP58+AP56+AP54+AP52+AP46+AP44+AP42+AP40+AP38+AP36+AP34+AP32+AP30+AP28+AP26+AP24+AP22+AP20+AP18+AP16+AP14+AP12+AP10+AP8 -> 5566.2628 | AQ96: =AQ86+AQ84+AQ82+AQ80+AQ78+AQ76+AQ74+AQ72+AQ70+AQ68+AQ66+AQ64+AQ62+AQ60+AQ58+AQ56+AQ54+AQ52+AQ46+AQ44+AQ42+AQ40+AQ38+AQ36+AQ34+AQ32+AQ30+AQ28+AQ26+AQ24+AQ22+AQ20+AQ18+AQ16+AQ14+AQ12+AQ10+AQ8 -> 5307.5869 | AR96: =AR86+AR84+AR82+AR80+AR78+AR76+AR74+AR72+AR70+AR68+AR66+AR64+AR62+AR60+AR58+AR56+AR54+AR52+AR46+AR44+AR42+AR40+AR38+AR36+AR34+AR32+AR30+AR28+AR26+AR24+AR22+AR20+AR18+AR16+AR14+AR12+AR10+AR8 -> 5307.5869 | ... AV96: =AV86+AV84+AV82+AV80+AV78+AV76+AV74+AV72+AV70+AV68+AV66+AV64+AV62+AV60+AV58+AV56+AV54+AV52+AV46+AV44+AV42+AV40+AV38+AV36+AV34+AV32+AV30+AV28+AV26+AV24+AV22+AV20+AV18+AV16+AV14+AV12+AV10+AV8 -> 5880.3399 | AX96: =AX86+AX84+AX82+AX80+AX78+AX76+AX74+AX72+AX70+AX68+AX66+AX64+AX62+AX60+AX58+AX56+AX54+AX52+AX46+AX44+AX42+AX40+AX38+AX36+AX34+AX32+AX30+AX28+AX26+AX24+AX22+AX20+AX18+AX16+AX14+AX12+AX10+AX8 -> 5004.2478 | AY96: =AY86+AY84+AY82+AY80+AY78+AY76+AY74+AY72+AY70+AY68+AY66+AY64+AY62+AY60+AY58+AY56+AY54+AY52+AY46+AY44+AY42+AY40+AY38+AY36+AY34+AY32+AY30+AY28+AY26+AY24+AY22+AY20+AY18+AY16+AY14+AY12+AY10+AY8 -> 5004.2478 | AZ96: =AZ86+AZ84+AZ82+AZ80+AZ78+AZ76+AZ74+AZ72+AZ70+AZ68+AZ66+AZ64+AZ62+AZ60+AZ58+AZ56+AZ54+AZ52+AZ46+AZ44+AZ42+AZ40+AZ38+AZ36+AZ34+AZ32+AZ30+AZ28+AZ26+AZ24+AZ22+AZ20+AZ18+AZ16+AZ14+AZ12+AZ10+AZ8 -> 5977.4502 | BA96: =BA86+BA84+BA82+BA80+BA78+BA76+BA74+BA72+BA70+BA68+BA66+BA64+BA62+BA60+BA58+BA56+BA54+BA52+BA46+BA44+BA42+BA40+BA38+BA36+BA34+BA32+BA30+BA28+BA26+BA24+BA22+BA20+BA18+BA16+BA14+BA12+BA10+BA8 -> 6576.7002 | BB96: =BB86+BB84+BB82+BB80+BB78+BB76+BB74+BB72+BB70+BB68+BB66+BB64+BB62+BB60+BB58+BB56+BB54+BB52+BB46+BB44+BB42+BB40+BB38+BB36+BB34+BB32+BB30+BB28+BB26+BB24+BB22+BB20+BB18+BB16+BB14+BB12+BB10+BB8 -> 7027.3572 | BC96: =BC86+BC84+BC82+BC80+BC78+BC76+BC74+BC72+BC70+BC68+BC66+BC64+BC62+BC60+BC58+BC56+BC54+BC52+BC46+BC44+BC42+BC40+BC38+BC36+BC34+BC32+BC30+BC28+BC26+BC24+BC22+BC20+BC18+BC16+BC14+BC12+BC10+BC8 -> 7317.9224 | BD96: =BD86+BD84+BD82+BD80+BD78+BD76+BD74+BD72+BD70+BD68+BD66+BD64+BD62+BD60+BD58+BD56+BD54+BD52+BD46+BD44+BD42+BD40+BD38+BD36+BD34+BD32+BD30+BD28+BD26+BD24+BD22+BD20+BD18+BD16+BD14+BD12+BD10+BD8 -> 7317.9224 | BE96: =BE86+BE84+BE82+BE80+BE78+BE76+BE74+BE72+BE70+BE68+BE66+BE64+BE62+BE60+BE58+BE56+BE54+BE52+BE46+BE44+BE42+BE40+BE38+BE36+BE34+BE32+BE30+BE28+BE26+BE24+BE22+BE20+BE18+BE16+BE14+BE12+BE10+BE8 -> 7728.6724 | ... BI96: =BI86+BI84+BI82+BI80+BI78+BI76+BI74+BI72+BI70+BI68+BI66+BI64+BI62+BI60+BI58+BI56+BI54+BI52+BI46+BI44+BI42+BI40+BI38+BI36+BI34+BI32+BI30+BI28+BI26+BI24+BI22+BI20+BI18+BI16+BI14+BI12+BI10+BI8 -> 7120.502 | BK96: =BK86+BK84+BK82+BK80+BK78+BK76+BK74+BK72+BK70+BK68+BK66+BK64+BK62+BK60+BK58+BK56+BK54+BK52+BK46+BK44+BK42+BK40+BK38+BK36+BK34+BK32+BK30+BK28+BK26+BK24+BK22+BK20+BK18+BK16+BK14+BK12+BK10+BK8 -> 6627.6256 | BL96: =BL86+BL84+BL82+BL80+BL78+BL76+BL74+BL72+BL70+BL68+BL66+BL64+BL62+BL60+BL58+BL56+BL54+BL52+BL46+BL44+BL42+BL40+BL38+BL36+BL34+BL32+BL30+BL28+BL26+BL24+BL22+BL20+BL18+BL16+BL14+BL12+BL10+BL8 -> 6627.6256 | BM96: =BM86+BM84+BM82+BM80+BM78+BM76+BM74+BM72+BM70+BM68+BM66+BM64+BM62+BM60+BM58+BM56+BM54+BM52+BM46+BM44+BM42+BM40+BM38+BM36+BM34+BM32+BM30+BM28+BM26+BM24+BM22+BM20+BM18+BM16+BM14+BM12+BM10+BM8 -> 7261.1018 | BN96: =BN86+BN84+BN82+BN80+BN78+BN76+BN74+BN72+BN70+BN68+BN66+BN64+BN62+BN60+BN58+BN56+BN54+BN52+BN46+BN44+BN42+BN40+BN38+BN36+BN34+BN32+BN30+BN28+BN26+BN24+BN22+BN20+BN18+BN16+BN14+BN12+BN10+BN8 -> 6381.4959 | BO96: =BO86+BO84+BO82+BO80+BO78+BO76+BO74+BO72+BO70+BO68+BO66+BO64+BO62+BO60+BO58+BO56+BO54+BO52+BO46+BO44+BO42+BO40+BO38+BO36+BO34+BO32+BO30+BO28+BO26+BO24+BO22+BO20+BO18+BO16+BO14+BO12+BO10+BO8 -> 5658.603 | BP96: =BP86+BP84+BP82+BP80+BP78+BP76+BP74+BP72+BP70+BP68+BP66+BP64+BP62+BP60+BP58+BP56+BP54+BP52+BP46+BP44+BP42+BP40+BP38+BP36+BP34+BP32+BP30+BP28+BP26+BP24+BP22+BP20+BP18+BP16+BP14+BP12+BP10+BP8 -> 4404.1586 | BQ96: =BQ86+BQ84+BQ82+BQ80+BQ78+BQ76+BQ74+BQ72+BQ70+BQ68+BQ66+BQ64+BQ62+BQ60+BQ58+BQ56+BQ54+BQ52+BQ46+BQ44+BQ42+BQ40+BQ38+BQ36+BQ34+BQ32+BQ30+BQ28+BQ26+BQ24+BQ22+BQ20+BQ18+BQ16+BQ14+BQ12+BQ10+BQ8 -> 4404.1586 | BR96: =BR86+BR84+BR82+BR80+BR78+BR76+BR74+BR72+BR70+BR68+BR66+BR64+BR62+BR60+BR58+BR56+BR54+BR52+BR46+BR44+BR42+BR40+BR38+BR36+BR34+BR32+BR30+BR28+BR26+BR24+BR22+BR20+BR18+BR16+BR14+BR12+BR10+BR8 -> 4404.1586 | ... BV96: =BV86+BV84+BV82+BV80+BV78+BV76+BV74+BV72+BV70+BV68+BV66+BV64+BV62+BV60+BV58+BV56+BV54+BV52+BV46+BV44+BV42+BV40+BV38+BV36+BV34+BV32+BV30+BV28+BV26+BV24+BV22+BV20+BV18+BV16+BV14+BV12+BV10+BV8 -> 3500.838 | BX96: =BX86+BX84+BX82+BX80+BX78+BX76+BX74+BX72+BX70+BX68+BX66+BX64+BX62+BX60+BX58+BX56+BX54+BX52+BX46+BX44+BX42+BX40+BX38+BX36+BX34+BX32+BX30+BX28+BX26+BX24+BX22+BX20+BX18+BX16+BX14+BX12+BX10+BX8 -> 3573.8476 | BY96: =BY86+BY84+BY82+BY80+BY78+BY76+BY74+BY72+BY70+BY68+BY66+BY64+BY62+BY60+BY58+BY56+BY54+BY52+BY46+BY44+BY42+BY40+BY38+BY36+BY34+BY32+BY30+BY28+BY26+BY24+BY22+BY20+BY18+BY16+BY14+BY12+BY10+BY8 -> 3573.8476 | BZ96: =BZ86+BZ84+BZ82+BZ80+BZ78+BZ76+BZ74+BZ72+BZ70+BZ68+BZ66+BZ64+BZ62+BZ60+BZ58+BZ56+BZ54+BZ52+BZ46+BZ44+BZ42+BZ40+BZ38+BZ36+BZ34+BZ32+BZ30+BZ28+BZ26+BZ24+BZ22+BZ20+BZ18+BZ16+BZ14+BZ12+BZ10+BZ8 -> 3573.8476 | CA96: =CA86+CA84+CA82+CA80+CA78+CA76+CA74+CA72+CA70+CA68+CA66+CA64+CA62+CA60+CA58+CA56+CA54+CA52+CA46+CA44+CA42+CA40+CA38+CA36+CA34+CA32+CA30+CA28+CA26+CA24+CA22+CA20+CA18+CA16+CA14+CA12+CA10+CA8 -> 3457.9686 | CB96: =CB86+CB84+CB82+CB80+CB78+CB76+CB74+CB72+CB70+CB68+CB66+CB64+CB62+CB60+CB58+CB56+CB54+CB52+CB46+CB44+CB42+CB40+CB38+CB36+CB34+CB32+CB30+CB28+CB26+CB24+CB22+CB20+CB18+CB16+CB14+CB12+CB10+CB8 -> 3167.4033 | CC96: =CC86+CC84+CC82+CC80+CC78+CC76+CC74+CC72+CC70+CC68+CC66+CC64+CC62+CC60+CC58+CC56+CC54+CC52+CC46+CC44+CC42+CC40+CC38+CC36+CC34+CC32+CC30+CC28+CC26+CC24+CC22+CC20+CC18+CC16+CC14+CC12+CC10+CC8 -> 2450.7367 | CD96: =CD86+CD84+CD82+CD80+CD78+CD76+CD74+CD72+CD70+CD68+CD66+CD64+CD62+CD60+CD58+CD56+CD54+CD52+CD46+CD44+CD42+CD40+CD38+CD36+CD34+CD32+CD30+CD28+CD26+CD24+CD22+CD20+CD18+CD16+CD14+CD12+CD10+CD8 -> 2450.7367 | CE96: =CE86+CE84+CE82+CE80+CE78+CE76+CE74+CE72+CE70+CE68+CE66+CE64+CE62+CE60+CE58+CE56+CE54+CE52+CE46+CE44+CE42+CE40+CE38+CE36+CE34+CE32+CE30+CE28+CE26+CE24+CE22+CE20+CE18+CE16+CE14+CE12+CE10+CE8 -> 2039.9867 | ... CI96: =CI86+CI84+CI82+CI80+CI78+CI76+CI74+CI72+CI70+CI68+CI66+CI64+CI62+CI60+CI58+CI56+CI54+CI52+CI46+CI44+CI42+CI40+CI38+CI36+CI34+CI32+CI30+CI28+CI26+CI24+CI22+CI20+CI18+CI16+CI14+CI12+CI10+CI8 -> 1329.1429
A97: Итого в строительстве объектов | AK97: =COUNTIF(AK7:AK86,">2") -> 10 | AL97: =COUNTIF(AL7:AL86,">2") -> 10 | AM97: =COUNTIF(AM7:AM86,">2") -> 11 | AN97: =COUNTIF(AN7:AN86,">2") -> 12 | AO97: =COUNTIF(AO7:AO86,">2") -> 12 | AP97: =COUNTIF(AP7:AP86,">2") -> 12 | AQ97: =COUNTIF(AQ7:AQ86,">2") -> 11 | AR97: =COUNTIF(AR7:AR86,">2") -> 11 | ... AV97: =COUNTIF(AV7:AV86,">2") -> 14 | AX97: =COUNTIF(AX7:AX86,">2") -> 12 | AY97: =COUNTIF(AY7:AY86,">2") -> 12 | AZ97: =COUNTIF(AZ7:AZ86,">2") -> 14 | BA97: =COUNTIF(BA7:BA86,">2") -> 15 | BB97: =COUNTIF(BB7:BB86,">2") -> 16 | BC97: =COUNTIF(BC7:BC86,">2") -> 17 | BD97: =COUNTIF(BD7:BD86,">2") -> 17 | BE97: =COUNTIF(BE7:BE86,">2") -> 18 | ... BI97: =COUNTIF(BI7:BI86,">2") -> 17 | BK97: =COUNTIF(BK7:BK86,">2") -> 17 | BL97: =COUNTIF(BL7:BL86,">2") -> 17 | BM97: =COUNTIF(BM7:BM86,">2") -> 19 | BN97: =COUNTIF(BN7:BN86,">2") -> 17 | BO97: =COUNTIF(BO7:BO86,">2") -> 16 | BP97: =COUNTIF(BP7:BP86,">2") -> 14 | BQ97: =COUNTIF(BQ7:BQ86,">2") -> 14 | BR97: =COUNTIF(BR7:BR86,">2") -> 14 | ... BV97: =COUNTIF(BV7:BV86,">2") -> 11 | BX97: =COUNTIF(BX7:BX86,">2") -> 11 | BY97: =COUNTIF(BY7:BY86,">2") -> 11 | BZ97: =COUNTIF(BZ7:BZ86,">2") -> 11 | CA97: =COUNTIF(CA7:CA86,">2") -> 10 | CB97: =COUNTIF(CB7:CB86,">2") -> 9 | CC97: =COUNTIF(CC7:CC86,">2") -> 7 | CD97: =COUNTIF(CD7:CD86,">2") -> 7 | CE97: =COUNTIF(CE7:CE86,">2") -> 6 | ... CI97: =COUNTIF(CI7:CI86,">2") -> 4

Sheet стратегия 2 под 100 тыс (реал-)
A1: Проект | B1: Мощность проекта, м2 | D1: Этажность | E1: Срок реализации, мес | F1: 3 кв. 2022 | G1: 4 кв. 2022 | J1: 1 кв. 2023 | M1: 2 кв. 2023 | P1: 3 кв. 2023 | S1: 4 кв. 2023 | V1: 1 кв. 2024 | Y1: 2 кв. 2024 | AB1: 3 кв. 2024 | AE1: 4 кв. 2024 | AH1: 1 кв. 2025 | AK1: 2 кв. 2025 | AN1: 3 кв. 2025 | AQ1: 4 кв. 2025 | AT1: 1 кв. 2026 | AW1: 2 кв. 2026 | AZ1: 3 кв. 2026 | BC1: 4 кв. 2026 | BF1: 1 кв. 2027 | BI1: 2 кв. 2027 | BL1: 3 кв. 2027 | BO1: 4 кв. 2027
F2: 44805 | G2: 44835 | H2: 44866 | I2: 44896 | J2: 44927 | K2: 44958 | L2: 44986 | M2: 45017 | N2: 45047 | O2: 45078 | P2: 45108 | Q2: 45139 | R2: 45170 | S2: 45200 | T2: 45231 | U2: 45261 | V2: 45292 | W2: 45323 | X2: 45352 | Y2: 45383 | Z2: 45413 | AA2: 45444 | AB2: 45474 | AC2: 45505 | AD2: 45536 | AE2: 45566 | AF2: 45597 | AG2: 45627 | AH2: 45658 | AI2: 45689 | AJ2: 45717 | AK2: 45748 | AL2: 45778 | AM2: 45809 | AN2: 45839 | AO2: 45870 | AP2: 45901 | AQ2: 45931 | AR2: 45962 | AS2: 45992 | AT2: 46023 | AU2: 46054 | AV2: 46082 | AW2: 46113 | AX2: 46143 | AY2: 46174 | AZ2: 46204 | BA2: 46235 | BB2: 46266 | BC2: 46296 | BD2: 46327 | BE2: 46357 | BF2: 46388 | BG2: 46419 | BH2: 46447 | BI2: 46478 | BJ2: 46508 | BK2: 46539 | BL2: 46569 | BM2: 46600 | BN2: 46631 | BO2: 46661 | BP2: 46692 | BQ2: 46722
B3: Продаваемая площадь | C3: Общая площадь | F3: 1 | G3: 2 | H3: 3 | I3: 4 | J3: 5 | K3: 6 | L3: 7 | M3: 8 | N3: 9 | O3: 10 | P3: 11 | Q3: 12 | R3: 13 | S3: 14 | T3: 15 | U3: 16 | V3: 17 | W3: 18 | X3: 19 | Y3: 20 | Z3: 21 | AA3: 22 | AB3: 23 | AC3: 24 | AD3: 25 | AE3: 26 | AF3: 27 | AG3: 28 | AH3: 29 | AI3: 30 | AJ3: 31 | AK3: 32 | AL3: 33 | AM3: 34 | AN3: 35 | AO3: 36 | AP3: 37 | AQ3: 38 | AR3: 39 | AS3: 40 | AT3: 41 | AU3: 42 | AV3: 43 | AW3: 44 | AX3: 45 | AY3: 46 | AZ3: 47 | BA3: 48 | BB3: 49 | BC3: 50 | BD3: 51 | BE3: 52 | BF3: 53 | BG3: 54 | BH3: 55 | BI3: 53 | BJ3: 54 | BK3: 55 | BL3: 53 | BM3: 54 | BN3: 55 | BO3: 53 | BP3: 54 | BQ3: 55
A4: Доп.продажи К2, тыс.руб. | I4: =I5*I6 -> 20466.707 | J4: =J5*J6 -> 17790.157 | K4: =K5*K6 -> 7738.543 | L4: =L5*L6 -> 20996.775 | M4: =M5*M6 -> 19538.496 | N4: =N21 -> 0 | O4: =O21 -> 0 | P4: =P21 -> 0 | Q4: =Q21 -> 0 | R4: =R21 -> 0
A5: Кедровый 2, м2 | I5: 309.6 | J5: 288.50756 | K5: 117.09 | L5: 321.4 | M5: 301.52
A6: Кедровый 2, тыс.руб./м2 | I6: 66.106935 | J6: 61.662707 | K6: 66.090554 | L6: 65.329107 | M6: 64.8
A7: Наполнение эскроу К2, тыс.руб. | I7: =I8*I9 -> 26815.7 | J7: =J8*J9 -> 20402.755 | K7: =K8*K9 -> 42045.105 | L7: =L8*L9 -> 39113.36 | M7: =M8*M9 -> 30993.248 | N7: =N8*N9 -> 46900 | O7: =O8*O9 -> 50625 | P7: =P8*P9 -> 53430 | ... R7: =R8*R9 -> 72280
A8: Кедровый 2, м2 | F8: =F10/F12 -> 1.1373577 | I8: =719-I5 -> 409.4 | J8: =600-J5 -> 311.49244 | K8: =759-K5 -> 641.91 | L8: =900-L5 -> 578.6 | M8: =760-M5 -> 458.48 | N8: 700 | O8: 750 | P8: 780 | Q8: 930 | R8: 1040
A9: Кедровый 2, тыс.руб./м2 | I9: 65.5 | J9: 65.5 | K9: 65.5 | L9: 67.6 | M9: 67.6 | N9: 67 | O9: 67.5 | P9: 68.5 | Q9: 69.5 | R9: 69.5
A10: Наполнение ЭСКРОУ накопительно | F10: 265886.42 | G10: 296491.57 | H10: 318795.86 | I10: =H10+I7 -> 345611.56 | J10: =I10+J7 -> 366014.32 | K10: =J10+K7 -> 408059.42 | L10: =K10+L7 -> 447172.78 | M10: =L10+M7 -> 478166.03 | N10: =M10+N7 -> 525066.03 | O10: =N10+O7 -> 575691.03 | P10: =O10+P7 -> 629121.03 | ... R10: =Q10+R7 -> 766036.03
A11: Выборка НКЛ К2 (с дек.22 расчетно) | F11: 36485.232 | G11: 31537.208 | H11: 27893.471 | I11: 32000 | J11: 32000 | K11: 32000 | L11: 45000 | M11: 50000 | N11: 50000 | O11: 50000 | P11: 50000 | Q11: 61135.156 | R11: 61135.156
A12: Остаток ссудной задолженности | F12: 233775.55 | G12: 265312.76 | H12: 293206.23 | I12: =H12+I11 -> 325206.23 | J12: =I12+J11 -> 357206.23 | K12: =J12+K11 -> 389206.23 | L12: =K12+L11 -> 434206.23 | M12: =L12+M11 -> 484206.23 | N12: =M12+N11 -> 534206.23 | O12: =N12+O11 -> 584206.23 | P12: =O12+P11 -> 634206.23 | ... R12: =Q12+R11 -> 756476.54
A13: Ставка по эскроу, исходя из наполнения | F13: =IF(F10/F12>1.5,#REF!,IF(F10/F12>1.4,#REF!,IF(F10/F12>1.3,#REF!,IF(F10/F12>1.2,#REF!,IF(F10/F12>1.1,#REF!,IF(F10/F12>1,#REF!,IF(F10/F12<1,17.73))))))) -> #REF! | G13: =IF(G10/G12>1.5,#REF!,IF(G10/G12>1.4,#REF!,IF(G10/G12>1.3,#REF!,IF(G10/G12>1.2,#REF!,IF(G10/G12>1.1,#REF!,IF(G10/G12>1,#REF!,IF(G10/G12<1,17.73))))))) -> #REF! | H13: =IF(H10/H12>1.5,#REF!,IF(H10/H12>1.4,#REF!,IF(H10/H12>1.3,#REF!,IF(H10/H12>1.2,#REF!,IF(H10/H12>1.1,#REF!,IF(H10/H12>1,#REF!,IF(H10/H12<1,17.73))))))) -> #REF! | I13: =IF(I10/I12>1.5,#REF!,IF(I10/I12>1.4,#REF!,IF(I10/I12>1.3,#REF!,IF(I10/I12>1.2,#REF!,IF(I10/I12>1.1,#REF!,IF(I10/I12>1,#REF!,IF(I10/I12<1,17.73))))))) -> #REF! | J13: =IF(J10/J12>1.5,#REF!,IF(J10/J12>1.4,#REF!,IF(J10/J12>1.3,#REF!,IF(J10/J12>1.2,#REF!,IF(J10/J12>1.1,#REF!,IF(J10/J12>1,#REF!,IF(J10/J12<1,17.73))))))) -> #REF! | K13: =IF(K10/K12>1.5,#REF!,IF(K10/K12>1.4,#REF!,IF(K10/K12>1.3,#REF!,IF(K10/K12>1.2,#REF!,IF(K10/K12>1.1,#REF!,IF(K10/K12>1,#REF!,IF(K10/K12<1,17.73))))))) -> #REF! | L13: =IF(L10/L12>1.5,#REF!,IF(L10/L12>1.4,#REF!,IF(L10/L12>1.3,#REF!,IF(L10/L12>1.2,#REF!,IF(L10/L12>1.1,#REF!,IF(L10/L12>1,#REF!,IF(L10/L12<1,17.73))))))) -> #REF! | M13: =IF(M10/M12>1.5,#REF!,IF(M10/M12>1.4,#REF!,IF(M10/M12>1.3,#REF!,IF(M10/M12>1.2,#REF!,IF(M10/M12>1.1,#REF!,IF(M10/M12>1,#REF!,IF(M10/M12<1,17.73))))))) -> 17.73 | ... R13: =IF(R10/R12>1.5,#REF!,IF(R10/R12>1.4,#REF!,IF(R10/R12>1.3,#REF!,IF(R10/R12>1.2,#REF!,IF(R10/R12>1.1,#REF!,IF(R10/R12>1,#REF!,IF(R10/R12<1,17.73))))))) -> #REF!
A14: Кедровый 1 | B14: 14439.4 | F14: РНВ
A15: Кедровый 2 | B15: 18331.74 | C15: 27707.46 | D15: 9 | E15: 26 | T15: РНВ | V15: закончить продажи (продаем по 60,875 млн в месяц в среднем)
A16: Павловск 1 | B16: 10065.54 | C16: 13453.37 | D16: 9 | E16: 24 | F16: кредит | L16: 18000 | U16: РНВ | V16: закончить продажи (продаем по 39 млн в месяц в среднем)
A17: Богучар 1 | B17: 10000 | C17: 13365.771 | D17: 9 | E17: 18 | F17: ЗУ | J17: 19000 | K17: проект (П+Р) + Благоустр (отдать на проектирование за 2 месяца) | L17: РНС - начало строительства (подготовить СП, набрать сотрудников, они должны изучить проект) | O17: кредит | AC17: РНВ | AD17: закончить продажи (продаем по 32 млн в месяц в среднем - депонирование)
A18: Муром 1 | B18: 25000 | C18: =B18*1.33 -> 33250 | D18: 9 | E18: 18 | J18: =15000+2500 -> 17500 | L18: 22000 | M18: проект (П+Р) + Благоустр (отдать на проектирование за 2 месяца) | N18: предпродажи (подготовить офис, набрать сотрудников) | O18: РНС - начало строительства (подготовить СП, набрать сотрудников, они должны изучить проект) | R18: кредит | AF18: РНВ | AG18: закончить продажи (продаем по 81 млн в месяц в среднем - депонирование)
A19: Старый Оскол | B19: 14000 | C19: =B19*1.33 -> 18620 | D19: 9 | E19: 18 | I19: 5000 | J19: 3000 | M19: 20000 | N19: проект (П+Р) + Благоустр (отдать на проектирование за 2 месяца) | O19: предпродажи (подготовить офис, набрать сотрудников) | P19: РНС - начало строительства (подготовить СП, набрать сотрудников, они должны изучить проект) | S19: кредит | AG19: РНВ | AH19: закончить продажи (продаем по 36 млн в месяц в среднем - депонирование)
A20: Павловск 2 (возможна замена локации) | B20: 18534.63 | C20: =B20*1.33 -> 24651.058 | D20: 9 | E20: 18 | F20: ЗУ | G20: ТУ | H20: проект (П+Р) + Благоустр (отдать на проектирование за 2 месяца) | I20: экспертиза | J20: предпродажи (подготовить офис, набрать сотрудников) | P20: РНС - начало строительства (подготовить СП, набрать сотрудников, они должны изучить проект) | S20: кредит | AG20: РНВ | AH20: закончить продажи (продаем по 53 млн в месяц в среднем - депонирование)
A21: Итого РАСХОДЫ, тыс.руб. | I21: =I19 -> 5000 | J21: =J19+J18+J17 -> 39500 | L21: =L18 -> 22000 | M21: =M19 -> 20000
A22: Итого | B22: =SUM(B14:B20) -> 110371.31
A23: Богучар 2 | B23: 10000 | C23: 13365.771 | D23: 9 | E23: 18 | F23: ЗУ (вместе с Б1) | G23: ТУ (вместе с Б1) | H23: проект (П+Р) + Благоустр (отдать на проектирование за 2 месяца) | I23: экспертиза | J23: предпродажи (подготовить офис, набрать сотрудников) | X23: РНС - начало строительства (подготовить СП, набрать сотрудников, они должны изучить проект) | AA23: кредит | AO23: РНВ | AP23: закончить продажи (продаем по 32 млн в месяц в среднем - депонирование)
A24: Муром 2 | B24: 25000 | C24: =C18 -> 33250 | D24: 10 | E24: 18 | I24: ЗУ | M24: проект (П+Р) + Благоустр (отдать на проектирование за 2 месяца) | N24: предпродажи (подготовить офис, набрать сотрудников) | Z24: РНС - начало строительства (подготовить СП, набрать сотрудников, они должны изучить проект) | AC24: кредит | AQ24: РНВ | AR24: закончить продажи (продаем по 81 млн в месяц в среднем - депонирование)
A25: Старый Оскол | B25: 6000 | C25: =B25*1.33 -> 7980 | D25: 9 | E25: 18 | H25: ЗУ | N25: проект (П+Р) + Благоустр (отдать на проектирование за 2 месяца) | O25: предпродажи (подготовить офис, набрать сотрудников) | P25: РНС - начало строительства (подготовить СП, набрать сотрудников, они должны изучить проект) | S25: кредит | AC25: РНС - начало строительства (подготовить СП, набрать сотрудников, они должны изучить проект) | AF25: кредит | AT25: РНВ | AU25: закончить продажи (продаем по 36 млн в месяц в среднем - депонирование)
A26: За стратегией | B26: =B25+B23+B24 -> 41000 | C26: =C25+C23+C24 -> 54595.771
J31: =B15+B16+B14 -> 42836.68 | V31: =B17+B18+B20+B19+#REF! -> #REF! | AH31: =#REF!+B22+#REF!+B23 -> #REF! | AT31: =#REF!++B22+#REF! -> #REF!
V32: =V31+J31 -> #REF! | AH32: =AH31+V32 -> #REF!
AL34: нужно 2-3 локации (если один литер 18-20 м2) | AM34: =AH31-100000 -> #REF!

Sheet стратегия 2 под 100 тыс
A1: Проект | B1: Мощность проекта, м2 | D1: Этажность | E1: Срок реализации, мес | F1: 3 кв. 2022 | G1: 4 кв. 2022 | J1: 1 кв. 2023 | M1: 2 кв. 2023 | P1: 3 кв. 2023 | S1: 4 кв. 2023 | V1: 1 кв. 2024 | Y1: 2 кв. 2024 | AB1: 3 кв. 2024 | AE1: 4 кв. 2024 | AH1: 1 кв. 2025 | AK1: 2 кв. 2025 | AN1: 3 кв. 2025 | AQ1: 4 кв. 2025 | AT1: 1 кв. 2026 | AW1: 2 кв. 2026 | AZ1: 3 кв. 2026 | BC1: 4 кв. 2026 | BF1: 1 кв. 2027 | BI1: 2 кв. 2027 | BL1: 3 кв. 2027 | BO1: 4 кв. 2027
F2: 44805 | G2: 44835 | H2: 44866 | I2: 44896 | J2: 44927 | K2: 44958 | L2: 44986 | M2: 45017 | N2: 45047 | O2: 45078 | P2: 45108 | Q2: 45139 | R2: 45170 | S2: 45200 | T2: 45231 | U2: 45261 | V2: 45292 | W2: 45323 | X2: 45352 | Y2: 45383 | Z2: 45413 | AA2: 45444 | AB2: 45474 | AC2: 45505 | AD2: 45536 | AE2: 45566 | AF2: 45597 | AG2: 45627 | AH2: 45658 | AI2: 45689 | AJ2: 45717 | AK2: 45748 | AL2: 45778 | AM2: 45809 | AN2: 45839 | AO2: 45870 | AP2: 45901 | AQ2: 45931 | AR2: 45962 | AS2: 45992 | AT2: 46023 | AU2: 46054 | AV2: 46082 | AW2: 46113 | AX2: 46143 | AY2: 46174 | AZ2: 46204 | BA2: 46235 | BB2: 46266 | BC2: 46296 | BD2: 46327 | BE2: 46357 | BF2: 46388 | BG2: 46419 | BH2: 46447 | BI2: 46478 | BJ2: 46508 | BK2: 46539 | BL2: 46569 | BM2: 46600 | BN2: 46631 | BO2: 46661 | BP2: 46692 | BQ2: 46722
B3: Продаваемая площадь | C3: Общая площадь | F3: 1 | G3: 2 | H3: 3 | I3: 4 | J3: 5 | K3: 6 | L3: 7 | M3: 8 | N3: 9 | O3: 10 | P3: 11 | Q3: 12 | R3: 13 | S3: 14 | T3: 15 | U3: 16 | V3: 17 | W3: 18 | X3: 19 | Y3: 20 | Z3: 21 | AA3: 22 | AB3: 23 | AC3: 24 | AD3: 25 | AE3: 26 | AF3: 27 | AG3: 28 | AH3: 29 | AI3: 30 | AJ3: 31 | AK3: 32 | AL3: 33 | AM3: 34 | AN3: 35 | AO3: 36 | AP3: 37 | AQ3: 38 | AR3: 39 | AS3: 40 | AT3: 41 | AU3: 42 | AV3: 43 | AW3: 44 | AX3: 45 | AY3: 46 | AZ3: 47 | BA3: 48 | BB3: 49 | BC3: 50 | BD3: 51 | BE3: 52 | BF3: 53 | BG3: 54 | BH3: 55 | BI3: 53 | BJ3: 54 | BK3: 55 | BL3: 53 | BM3: 54 | BN3: 55 | BO3: 53 | BP3: 54 | BQ3: 55
A4: Кедровый 1 | B4: 14439.4 | F4: РНВ
A5: Кедровый 2 | B5: 18331.74 | C5: 27707.46 | D5: 9 | E5: 26 | T5: РНВ | V5: закончить продажи (продаем по 60,875 млн в месяц в среднем)
A6: Павловск 1 | B6: 10065.54 | C6: 13453.37 | D6: 9 | E6: 24 | F6: кредит | L6: 18000 | U6: РНВ | V6: закончить продажи (продаем по 39 млн в месяц в среднем)
A7: Богучар 1 | B7: 10000 | C7: 13365.771 | D7: 9 | E7: 18 | F7: ЗУ | J7: 19000 | K7: проект (П+Р) + Благоустр (отдать на проектирование за 2 месяца) | L7: РНС - начало строительства (подготовить СП, набрать сотрудников, они должны изучить проект) | O7: кредит | AC7: РНВ | AD7: закончить продажи (продаем по 32 млн в месяц в среднем - депонирование)
A8: Муром 1 | B8: 25000 | C8: =B8*1.33 -> 33250 | D8: 9 | E8: 18 | I8: ЗУ 15000 | J8: 2500 | L8: 22000 | M8: проект (П+Р) + Благоустр (отдать на проектирование за 2 месяца) | N8: предпродажи (подготовить офис, набрать сотрудников) | O8: РНС - начало строительства (подготовить СП, набрать сотрудников, они должны изучить проект) | R8: кредит | AF8: РНВ | AG8: закончить продажи (продаем по 81 млн в месяц в среднем - депонирование)
A9: Старый Оскол | B9: 14000 | C9: =B9*1.33 -> 18620 | D9: 9 | E9: 18 | H9: ЗУ 5000 | J9: 3000 | M9: 20000 | N9: проект (П+Р) + Благоустр (отдать на проектирование за 2 месяца) | O9: предпродажи (подготовить офис, набрать сотрудников) | P9: РНС - начало строительства (подготовить СП, набрать сотрудников, они должны изучить проект) | S9: кредит | AG9: РНВ | AH9: закончить продажи (продаем по 36 млн в месяц в среднем - депонирование)
A10: Павловск 2 (возможна замена локации) | B10: 18534.63 | C10: =B10*1.33 -> 24651.058 | D10: 9 | E10: 18 | F10: ЗУ | G10: ТУ | H10: проект (П+Р) + Благоустр (отдать на проектирование за 2 месяца) | I10: экспертиза | J10: предпродажи (подготовить офис, набрать сотрудников) | P10: РНС - начало строительства (подготовить СП, набрать сотрудников, они должны изучить проект) | S10: кредит | AG10: РНВ | AH10: закончить продажи (продаем по 53 млн в месяц в среднем - депонирование)
A11: Итого | B11: =SUM(B4:B10) -> 110371.31
A12: Богучар 2 | B12: 10000 | C12: 13365.771 | D12: 9 | E12: 18 | F12: ЗУ (вместе с Б1) | G12: ТУ (вместе с Б1) | H12: проект (П+Р) + Благоустр (отдать на проектирование за 2 месяца) | I12: экспертиза | J12: предпродажи (подготовить офис, набрать сотрудников) | X12: РНС - начало строительства (подготовить СП, набрать сотрудников, они должны изучить проект) | AA12: кредит | AO12: РНВ | AP12: закончить продажи (продаем по 32 млн в месяц в среднем - депонирование)
A13: Муром 2 | B13: 25000 | C13: =C8 -> 33250 | D13: 10 | E13: 18 | I13: ЗУ | M13: проект (П+Р) + Благоустр (отдать на проектирование за 2 месяца) | N13: предпродажи (подготовить офис, набрать сотрудников) | Z13: РНС - начало строительства (подготовить СП, набрать сотрудников, они должны изучить проект) | AC13: кредит | AQ13: РНВ | AR13: закончить продажи (продаем по 81 млн в месяц в среднем - депонирование)
A14: Старый Оскол | B14: 6000 | C14: =B14*1.33 -> 7980 | D14: 9 | E14: 18 | H14: ЗУ | N14: проект (П+Р) + Благоустр (отдать на проектирование за 2 месяца) | O14: предпродажи (подготовить офис, набрать сотрудников) | P14: РНС - начало строительства (подготовить СП, набрать сотрудников, они должны изучить проект) | S14: кредит | AC14: РНС - начало строительства (подготовить СП, набрать сотрудников, они должны изучить проект) | AF14: кредит | AT14: РНВ | AU14: закончить продажи (продаем по 36 млн в месяц в среднем - депонирование)
A15: За стратегией | B15: =B14+B12+B13 -> 41000 | C15: =C14+C12+C13 -> 54595.771
J20: =B5+B6+B4 -> 42836.68 | V20: =B7+B8+B10+B9+#REF! -> #REF! | AH20: =#REF!+B11+#REF!+B12 -> #REF! | AT20: =#REF!++B11+#REF! -> #REF!
V21: =V20+J20 -> #REF! | AH21: =AH20+V21 -> #REF!
AL23: нужно 2-3 локации (если один литер 18-20 м2) | AM23: =AH20-100000 -> #REF!

Sheet стратегия 1
A1: Проект | B1: Мощность проекта, м2 | D1: Этажность | E1: Срок реализации, мес | F1: 3 кв. 2022 | G1: 4 кв. 2022 | J1: 1 кв. 2023 | M1: 2 кв. 2023 | P1: 3 кв. 2023 | S1: 4 кв. 2023 | V1: 1 кв. 2024 | Y1: 2 кв. 2024 | AB1: 3 кв. 2024 | AE1: 4 кв. 2024 | AH1: 1 кв. 2025 | AK1: 2 кв. 2025 | AN1: 3 кв. 2025 | AQ1: 4 кв. 2025 | AT1: 1 кв. 2026 | AW1: 2 кв. 2026 | AZ1: 3 кв. 2026 | BC1: 4 кв. 2026 | BF1: 1 кв. 2027 | BI1: 2 кв. 2027 | BL1: 3 кв. 2027 | BO1: 4 кв. 2027
F2: 44805 | G2: 44835 | H2: 44866 | I2: 44896 | J2: 44927 | K2: 44958 | L2: 44986 | M2: 45017 | N2: 45047 | O2: 45078 | P2: 45108 | Q2: 45139 | R2: 45170 | S2: 45200 | T2: 45231 | U2: 45261 | V2: 45292 | W2: 45323 | X2: 45352 | Y2: 45383 | Z2: 45413 | AA2: 45444 | AB2: 45474 | AC2: 45505 | AD2: 45536 | AE2: 45566 | AF2: 45597 | AG2: 45627 | AH2: 45658 | AI2: 45689 | AJ2: 45717 | AK2: 45748 | AL2: 45778 | AM2: 45809 | AN2: 45839 | AO2: 45870 | AP2: 45901 | AQ2: 45931 | AR2: 45962 | AS2: 45992 | AT2: 46023 | AU2: 46054 | AV2: 46082 | AW2: 46113 | AX2: 46143 | AY2: 46174 | AZ2: 46204 | BA2: 46235 | BB2: 46266 | BC2: 46296 | BD2: 46327 | BE2: 46357 | BF2: 46388 | BG2: 46419 | BH2: 46447 | BI2: 46478 | BJ2: 46508 | BK2: 46539 | BL2: 46569 | BM2: 46600 | BN2: 46631 | BO2: 46661 | BP2: 46692 | BQ2: 46722
B3: Продаваемая площадь | C3: Общая площадь | F3: 1 | G3: 2 | H3: 3 | I3: 4 | J3: 5 | K3: 6 | L3: 7 | M3: 8 | N3: 9 | O3: 10 | P3: 11 | Q3: 12 | R3: 13 | S3: 14 | T3: 15 | U3: 16 | V3: 17 | W3: 18 | X3: 19 | Y3: 20 | Z3: 21 | AA3: 22 | AB3: 23 | AC3: 24 | AD3: 25 | AE3: 26 | AF3: 27 | AG3: 28 | AH3: 29 | AI3: 30 | AJ3: 31 | AK3: 32 | AL3: 33 | AM3: 34 | AN3: 35 | AO3: 36 | AP3: 37 | AQ3: 38 | AR3: 39 | AS3: 40 | AT3: 41 | AU3: 42 | AV3: 43 | AW3: 44 | AX3: 45 | AY3: 46 | AZ3: 47 | BA3: 48 | BB3: 49 | BC3: 50 | BD3: 51 | BE3: 52 | BF3: 53 | BG3: 54 | BH3: 55 | BI3: 53 | BJ3: 54 | BK3: 55 | BL3: 53 | BM3: 54 | BN3: 55 | BO3: 53 | BP3: 54 | BQ3: 55
A4: Кедровый 1 | B4: 14439.4 | F4: РНВ
A5: Кедровый 2 | B5: 18331.74 | C5: 27707.46 | D5: 9 | E5: 26 | T5: РНВ
A6: Павловск 1 | B6: 10065.54 | C6: 13453.37 | D6: 9 | E6: 24 | F6: кредит | U6: РНВ
A7: Богучар 1 | B7: 10000 | C7: 13365.771 | D7: 9 | E7: 18 | L7: начало строительства | O7: кредит | AC7: РНВ
A8: Муром 1 | B8: 20277.667 | C8: 27402.252 | D8: 10 | E8: 18 | O8: начало строительства | R8: кредит | AF8: РНВ
A9: Борисоглебск 1 очередь (1-2Л) | B9: 11184 | C9: 15113.514 | D9: 5 | E9: 18 | X9: начало строительства | AA9: кредит | AO9: РНВ
A10: Павловск 2 | B10: 18534.63 | C10: 27922.43 | D10: 9 | E10: 18 | AA10: начало строительства | AD10: кредит | AR10: РНВ
A11: Богучар 2 | B11: 10000 | C11: 13365.771 | D11: 9 | E11: 18 | AL11: начало строительства | AO11: кредит | BC11: РНВ
A12: Мичуринск 1 | B12: 16222 | C12: 21922 | D12: 8 | E12: 18 | Y12: начало строительства | AB12: кредит | AP12: РНВ
A13: нужна еще локация | AE13: начало строительства | AH13: кредит | AV13: РНВ
A14: нужна еще локация | AJ14: начало строительства | AM14: кредит | BA14: РНВ
A15: Борисоглебск 2 очередь (3-4Л) | B15: =B9 -> 11184 | C15: =C9 -> 15113.514 | D15: 5 | E15: 18 | AV15: начало строительства | AY15: кредит | BM15: РНВ
A16: Муром 2 | B16: 20277.667 | C16: =C8 -> 27402.252 | D16: 10 | E16: 18
A17: до красной линии | B17: =SUM(B5:B12) -> 114615.58 | C17: =SUM(C5:C12) -> 160252.57
A18: все вместе | B18: =B17+B15+B16 -> 146077.24 | C18: =C17+C15+C16 -> 202768.33
A21: Муром 2 сможем начать только в мае 27 года
A22: Бк 2 сможем начать только в марте 26
J23: =B5+B6+B4 -> 42836.68 | V23: =B7+B8 -> 30277.667 | AH23: =B9+B10+B12 -> 45940.63 | AT23: =B11++B13+B14 -> 10000
A24: Борисоглебск | V24: =V23+J23 -> 73114.347 | AH24: =AH23+V24 -> 119054.98
A25: Мичуринск | B25: 8 эт | C25: 10000000
